Workbook
Name ExternalData_1: 详情!$C$14:$C$99
Name ExternalData_1: 业务报告!#REF!
Name ExternalData_2: 业务报告!$A$1:$B$50
Name ExternalData_1: WT报告!$A$1:$B$26
Name ExternalData_1: SP!$A$1:$B$23
Name ExternalData_1: SD!$A$1:$C$33
Name ExternalData_1: SB!#REF!
Name ExternalData_2: SB!$A$1:$C$56
Name ExternalData_1: Base!$A$1:$B$7
Name attributeMapFeedProductType: [1]AttributePTDMAP!$B$1
Name optionalAttributePTDMap: [1]AttributePTDMAP!$A$13:$B$236
Name preferredAttributePTDMap: [1]AttributePTDMAP!$A$237:$B$237

Sheet 详情
A1: 子表-基础数据部分 | B1: 位置 | C1: 名称 | D1: 解释 | E1: 公式
B2: $P$2 | C2: SKU1 | D2: 来自于Base的D2 到 D4 | E2: Base!$D$2:$D$4
B3: $T$2 | C3: SKU2
B4: $X$2 | C4: WOOT
B5: $N5 | C5: 日期
B6: $AC$1 | D6: 综合成本 含头程
B7: $AC$2 | D7: 人民币转美元汇率
B8: $AD$1 | D8: FBA派送费
B9: $AD$2 | D9: 销售佣金率
B10: $AH$2 | E10: 79.99*(1-15%-4%-$AB$2)-$AD$1-$AC$1/$AC$2
B11: $AG$2 | E11: 59.96*(1-5%)-89.99*15%-AC1/AC2
A13: 模块 | B13: 单元格位置 | C13: 名称 | D13: 介绍 | E13: 公式
B14: A5 | C14: 问题 | D14: 满足 业务报告.日期 = 子表.日期 业务报告.MSKU/WOOT ASIN = 子表.SKU1 获取 业务报告.问题/规划 | E14: IFERROR(LOOKUP(1,0/((业务报告!$A:$A=$N5)*(业务报告!$B:$B=$P$2)),业务报告!AU:AU),"")
B15: B5 | C15: 调整 | D15: 满足 业务报告.日期 = 子表.日期 业务报告.MSKU/WOOT ASIN = 子表.SKU1 获取 业务报告.调整 | E15: IFERROR(LOOKUP(1,0/((业务报告!$A:$A=$N5)*(业务报告!$B:$B=$P$2)),业务报告!AV:AV),"")
B16: C5 | C16: 大类排名 | D16: 满足 业务报告.日期 = 子表.日期 业务报告.MSKU/WOOT ASIN = 子表.SKU1 获取 累加 业务报告.大类排名（一般只有一条） | E16: SUMIFS(业务报告!AC:AC,业务报告!$A:$A,$N5,业务报告!$B:$B,$P$2)
B17: D5 | C17: 小类排名 | D17: 满足 业务报告.日期 = 子表.日期 业务报告.MSKU/WOOT ASIN = 子表.SKU1 获取 累加 业务报告.小类排名（一般只有一条） | E17: SUMIFS(业务报告!AD:AD,业务报告!$A:$A,$N5,业务报告!$B:$B,$P$2)
B18: E5 | C18: KW(Laser)自然位 | D18: 满足 业务报告.日期 = 子表.日期 业务报告.MSKU/WOOT ASIN = 子表.SKU1 获取 业务报告.KW(Laser)自然位 | E18: _xlfn.XLOOKUP($N5&$P$2,业务报告!$A:$A&业务报告!$B:$B,业务报告!AE:AE,"")
B19: F5 | C19: 活动 | D19: 满足 业务报告.日期 = 子表.日期 业务报告.MSKU/WOOT ASIN = 子表.SKU1 获取 业务报告.活动 否则为0 | E19: IFERROR(LOOKUP(1,0/((业务报告!$A:$A=$N5)*(业务报告!$B:$B=$P$2)),业务报告!AK:AK),0)
B20: G5 | C20: 划线价/VC LP | D20: 满足 业务报告.日期 = 子表.日期 业务报告.MSKU/WOOT ASIN = 子表.SKU1 获取 累加 业务报告.划线价/VC MSRP（一般只有一条） | E20: SUMIFS(业务报告!AF:AF,业务报告!$A:$A,$N5,业务报告!$B:$B,$P$2)
B21: H5 | C21: 折扣 | D21: 满足 业务报告.日期 = 子表.日期 业务报告.MSKU/WOOT ASIN = 子表.SKU1 获取 业务报告.折扣额/VC-CPN&Promo 否则为0 | E21: IFERROR(LOOKUP(1,0/((业务报告!$A:$A=$N5)*(业务报告!B:B=$P$2)),业务报告!AG:AG),0)
B22: I5 | C22: 成交价 | D22: 满足 业务报告.日期 = 子表.日期 业务报告.MSKU/WOOT ASIN = 子表.SKU1 获取 业务报告.成交价/VC采购价 否则为0 | E22: IFERROR(LOOKUP(1,0/((业务报告!$A:$A=$N5)*(业务报告!$B:$B=$P$2)),业务报告!AH:AH),0)
B23: J5 | C23: WT采购价 | D23: 满足 WT报告.报告日期 = 子表.日期 WT报告.子Asin = 子表.WOOT 获取 累加 WT报告.采购价（一般只有一条） | E23: SUMIFS(WT报告!A:A,WT报告!$C:$C,$N5,WT报告!$H:$H,$X$2)
B24: K5 | C24: 评论星级 | D24: 满足 业务报告.日期 = 子表.日期 业务报告.MSKU/WOOT ASIN = 子表.SKU1 获取 累加 业务报告.评论星级（一般只有一条） | E24: IFERROR(LOOKUP(1,0/((业务报告!$A:$A=$N5)*(业务报告!$B:$B=$P$2)),业务报告!AI:AI),0)
B25: L5 | C25: 新差评 | D25: 满足 业务报告.日期 = 子表.日期 业务报告.MSKU/WOOT ASIN = 子表.SKU1 获取 累加 业务报告.差评（一般只有一条） | E25: IFERROR(LOOKUP(1,0/((业务报告!$A:$A=$N5)*(业务报告!$B:$B=$P$2)),业务报告!AJ:AJ),0)
B26: M5 | C26: 星期 | D26: 星期选择完自动生成 | E26: IFERROR("周"&WEEKDAY(N5,2),"-")
A27: 销售数据 - TM002 | B27: N5 | C27: 日期 | D27: 日期选择完自动生成 | E27: DATE($O$1,$O$2,1)
B28: O5 | C28: 移动 | D28: 满足 业务报告.日期 = 子表.日期 业务报告.MSKU/WOOT ASIN = 子表.SKU1 数据一 累加 业务报告.会话次数 –APP（一般只有一条） 满足 业务报告.日期 = 子表.日期 业务报告.MSKU/WOOT ASIN = 子表.SKU2 数据二 累加 业务报告.会话次数 –APP（一般只有一条） 最后结果 数据一 + 数据二 | E28: SUMIFS(业务报告!G:G,业务报告!$A:$A,$N5,业务报告!$B:$B,$P$2)+SUMIFS(业务报告!G:G,业务报告!$A:$A,$N5,业务报告!$B:$B,$T$2)
B29: P5 | C29: PC | D29: 满足 业务报告.日期 = 子表.日期 业务报告.MSKU/WOOT ASIN = 子表.SKU1 数据一 累加 业务报告.会话次数 – PC（一般只有一条） 满足 业务报告.日期 = 子表.日期 业务报告.MSKU/WOOT ASIN = 子表.SKU2 数据二 累加 业务报告.会话次数 – PC（一般只有一条） 最后结果 数据一 + 数据二 | E29: SUMIFS(业务报告!H:H,业务报告!$A:$A,$N5,业务报告!$B:$B,$P$2)+SUMIFS(业务报告!H:H,业务报告!$A:$A,$N5,业务报告!$B:$B,$T$2)
B30: Q5 | C30: 访客数 | D30: 满足 业务报告.日期 = 子表.日期 业务报告.MSKU/WOOT ASIN = 子表.SKU1 数据一 累加 业务报告.会话次数 – 总计（一般只有一条） 满足 业务报告.日期 = 子表.日期 业务报告.MSKU/WOOT ASIN = 子表.SKU2 数据二 累加 业务报告.会话次数 – 总计（一般只有一条） 最后结果 数据一 + 数据二 | E30: SUMIFS(业务报告!I:I,业务报告!$A:$A,$N5,业务报告!$B:$B,$P$2)+SUMIFS(业务报告!I:I,业务报告!$A:$A,$N5,业务报告!$B:$B,$T$2)
B31: R5 | C31: 销量 | D31: 满足 业务报告.日期 = 子表.日期 业务报告.MSKU/WOOT ASIN = 子表.SKU1 数据一 累加 业务报告.已订购商品数量（一般只有一条） 满足 业务报告.日期 = 子表.日期 业务报告.MSKU/WOOT ASIN = 子表.SKU2 数据二 累加 业务报告.已订购商品数量（一般只有一条） 最后结果 数据一 + 数据二 | E31: SUMIFS(业务报告!T:T,业务报告!$A:$A,$N5,业务报告!$B:$B,$P$2)+SUMIFS(业务报告!T:T,业务报告!$A:$A,$N5,业务报告!$B:$B,$T$2)
B32: S5 | C32: 销量转化率 | D32: (子表.销量 + 子表.WT单量) / 访客数 | E32: IFERROR((R5+V5)/Q5,0)
B33: T5 | C33: 销售额 | D33: 满足 业务报告.日期 = 子表.日期 业务报告.MSKU/WOOT ASIN = 子表.SKU1 数据一 累加 业务报告.已订购商品销售额（一般只有一条） 满足 业务报告.日期 = 子表.日期 业务报告.MSKU/WOOT ASIN = 子表.SKU2 数据二 累加 业务报告.已订购商品销售额（一般只有一条） 最后结果 数据一 + 数据二 | E33: SUMIFS(业务报告!X:X,业务报告!$A:$A,$N5,业务报告!$B:$B,$P$2)+SUMIFS(业务报告!X:X,业务报告!$A:$A,$N5,业务报告!$B:$B,$T$2)
B34: U5 | C34: 测评单量 | D34: 满足 业务报告.日期 = 子表.日期 业务报告.MSKU/WOOT ASIN = 子表.SKU1 数据一 累加 业务报告.主售送测单（一般只有一条） 满足 业务报告.日期 = 子表.日期 业务报告.MSKU/WOOT ASIN = 子表.SKU1 数据二 累加 业务报告.VC送测单（一般只有一条） 最后结果 数据一 + 数据二 | E34: SUMIFS(业务报告!AO:AO,业务报告!$A:$A,$N5,业务报告!$B:$B,$P$2)+SUMIFS(业务报告!AP:AP,业务报告!$A:$A,$N5,业务报告!$B:$B,$P$2)
B35: V5 | C35: WT单量 | D35: 满足 WT报告.报告日期 = 子表.日期 WT报告.子Asin = 子表.WOOT 获取 累加 WT报告.Woot订单数量（一般只有一条） | E35: SUMIFS(WT报告!I:I,WT报告!$C:$C,$N5,WT报告!$H:$H,$X$2)
B36: W5 | C36: WT销售额 | D36: 满足 WT报告.报告日期 = 子表.日期 WT报告.子Asin = 子表.WOOT 获取 累加 WT报告.总销售额（一般只有一条） | E36: SUMIFS(WT报告!Z:Z,WT报告!$C:$C,$N5,WT报告!$H:$H,$X$2)
B37: X5 | C37: 父体单量 | D37: 满足 业务报告.日期 = 子表.日期 业务报告.MSKU/WOOT ASIN = 子表.SKU1 数据一 累加 业务报告.父体单（一般只有一条） 满足 业务报告.日期 = 子表.日期 业务报告.MSKU/WOOT ASIN = 子表.SKU2 数据二 累加 业务报告.父体单（一般只有一条） 最后结果 数据一 + 数据二 + 子表.WT单量 | E37: SUMIFS(业务报告!AS:AS,业务报告!$A:$A,$N5,业务报告!$B:$B,$P$2)+SUMIFS(业务报告!AS:AS,业务报告!$A:$A,$N5,业务报告!$B:$B,$T$2)+V5
A38: 毛利润 | B38: Y5 | C38: 测评费用US$ | D38: 满足 业务报告.日期 = 子表.日期 业务报告.MSKU/WOOT ASIN = 子表.SKU1 数据一 业务报告.主售送测单 * 业务报告*主售测评成本￥/ 汇率 满足 业务报告.日期 = 子表.日期 业务报告.MSKU/WOOT ASIN = 子表.SKU1 数据二 业务报告.VC送测单 * 业务报告*VC测评成本￥/汇率 最后结果 数据一 + 数据二 | E38: SUMIFS(业务报告!AO:AO,业务报告!$A:$A,$N5,业务报告!$B:$B,$P$2)*SUMIFS(业务报告!AM:AM,业务报告!$A:$A,$N5,业务报告!$B:$B,$P$2)/$AC$2+SUMIFS(业务报告!AP:AP,业务报告!$A:$A,$N5,业务报告!$B:$B,$P$2)*SUMIFS(业务报告!AN:AN,业务报告!$A:$A,$N5,业务报告!$B:$B,$P$2)/$AC$2
B39: Z5 | C39: SC广告利润$ | D39: （子表.成交价 *（1 - 子表.销售佣金率 - 4% -10%） - 子表FBA派送费 - 子表.综合成本 含头程/子表.人民币转美元汇率）* 子表.AD单 - 子表.广告费 | E39: (I5*(1-$AD$2-4%-10%)-$AD$1-$AC$1/$AC$2)*BB5-BC5
B40: AA5 | C40: SC利润US$ | D40: 如果 子表.销量 > 子表.WT单量 根据 业务报告.日期 = 子表.日期 业务报告.MSKU/WOOT ASIN = 子表.SKU1 数据一 等于业务报告.主售送测单 否则数据一 = 0 子表.SC广告利润$ * (子表.销量 - 数据一) - 子表.广告费 | E40: (I5*(1-$AD$2-4%-10%)-$AD$1-$AC$1/$AC$2)*(R5-IF(R5>V5,SUMIFS(业务报告!AO:AO,业务报告!$A:$A,$N5,业务报告!$B:$B,$P$2),0))-BC5
B41: AB5 | C41: SC毛利率 | D41: 子表.SC利润$ / (子表.成交价 * 子表.销量) ，出现错误为0 | E41: IFERROR(AA5/(I5*R5),0)
B42: AC5 | C42: WT广告利润$ | D42: AD单 * （WT采购价 - 综合成本含头程/人民币转美元汇率- WT采购价 *4%）- 广告费 | E42: AR5*(J5-$AC$1/$AC$2-J5*4%)-AS5
B43: AD5 | C43: WT利润US$ | D43: 如果 子表.销量 < 子表.WT单量 根据 业务报告.日期 = 子表.日期 业务报告.MSKU/WOOT ASIN = 子表.SKU1 数据一 等于业务报告.主售送测单 否则数据一 = 0 (WT单量 - 数据一) | E43: (V5-IF(R5<V5,SUMIFS(业务报告!AO:AO,业务报告!$A:$A,$N5,业务报告!$B:$B,$P$2),0))*(J5-$AC$1/$AC$2-J5*4%)-AS5
B44: AE5 | C44: SC变体利润$ | D44: 满足 业务报告.日期 = 子表.日期 业务报告.MSKU/WOOT ASIN = 子表.SKU1 数据一 业务报告.SC变体单 没有就为0 数据一 * $AH$2 | E44: IFERROR(LOOKUP(1,0/((业务报告!$A:$A=$N5)*(业务报告!$B:$B=$P$2)),业务报告!AQ:AQ),0)*$AH$2
B45: AF5 | C45: VC变体利润$ | D45: 满足 业务报告.日期 = 子表.日期 业务报告.MSKU/WOOT ASIN = 子表.SKU1 数据一 业务报告.VC变体单 没有就为0 数据一 * $AG$2 | E45: IFERROR(LOOKUP(1,0/((业务报告!$A:$A=$N5)*(业务报告!$B:$B=$P$2)),业务报告!AR:AR),0)*$AG$2
B46: AG5 | C46: 总利润US$ | D46: SC利润US$ + WT利润US$ + SC变体利润$ + VC变体利润$ - 测评费用US$ | E46: AA5+AD5+AE5+AF5-Y5
B47: AH5 | C47: 总毛利率 | D47: 总利润US$ / (销售额 + WT采购价 * WT单量) | E47: IFERROR((AG5)/(T5+J5*V5),0)
B48: AI5 | C48: 父体单个毛利 | D48: 总利润US$ / 父体单量 | E48: IFERROR((AG5)/(X5),0)
A49: SC广告数据汇总 | B49: AJ5 | C49: 总TACOS | D49: 广告费 / （WT单量 * WT采购价） | E49: IFERROR(AS5/(V5*J5),0)
B50: AK5 | C50: 总CPO | D50: 广告费 / WT单量 向上取一位小数 | E50: IFERROR(ROUNDUP(AS5/V5,1),0)
B51: AL5 | C51: 广告CPA | D51: 满足 WT报告.报告日期 = 子表.日期 WT报告.子Asin = 子表.WOOT 获取 累加 WT报告.单个广告订单的费用（一般只有一条） | E51: SUMIFS(WT报告!S:S,WT报告!$C:$C,$N5,WT报告!$H:$H,$X$2)
B52: AM5 | C52: 广告CVR | D52: AD单 / 点击 | E52: IFERROR((AR5)/AP5,0)
B53: AN5 | C53: CPC | D53: 满足 WT报告.报告日期 = 子表.日期 WT报告.子Asin = 子表.WOOT 获取 累加 WT报告.广告单次点击花费（一般只有一条） | E53: SUMIFS(WT报告!N:N,WT报告!$C:$C,$N5,WT报告!$H:$H,$X$2)
B54: AO5 | C54: 广告单占比 | D54: AD单 / WT单量 | E54: IFERROR(AR5/(V5),0)
B55: AP5 | C55: 点击 | D55: 满足 WT报告.报告日期 = 子表.日期 WT报告.子Asin = 子表.WOOT 获取 累加 WT报告.点击数量（一般只有一条） | E55: SUMIFS(WT报告!P:P,WT报告!$C:$C,$N5,WT报告!$H:$H,$X$2)
B56: AQ5 | C56: CTR | D56: 满足 WT报告.报告日期 = 子表.日期 WT报告.子Asin = 子表.WOOT 获取 累加 WT报告.广告点击率（一般只有一条） | E56: SUMIFS(WT报告!Q:Q,WT报告!$C:$C,$N5,WT报告!$H:$H,$X$2)
B57: AR5 | C57: AD单 | D57: 满足 WT报告.报告日期 = 子表.日期 WT报告.子Asin = 子表.WOOT 获取 累加 WT报告.广告订单数量（一般只有一条） | E57: SUMIFS(WT报告!J:J,WT报告!$C:$C,$N5,WT报告!$H:$H,$X$2)
B58: AS5 | C58: 广告费 | D58: 满足 WT报告.报告日期 = 子表.日期 WT报告.子Asin = 子表.WOOT 获取 累加 WT报告.广告花费（一般只有一条） | E58: SUMIFS(WT报告!M:M,WT报告!$C:$C,$N5,WT报告!$H:$H,$X$2)
B59: AT5 | C59: 总TACOS | D59: （SP广告数据.Spend + 展示型广告数据.Spend + 品牌视频广告数据.Spend） / (销量 * 成交价) | E59: IFERROR((BO5+BX5+CG5)/(R5*I5),0)
B60: AU5 | C60: 总CPO | D60: 广告费 / 销量 向上取一位小数 | E60: IFERROR(ROUNDUP(BC5/R5,1),0)
B61: AV5 | C61: 广告CPA | D61: 广告费/ AD单 向上取一位小数 | E61: IFERROR(ROUNDUP(BC5/BB5,1),0)
... B69: BD5 | C69: ACoS | D69: 广告费 / （SP广告数据.Sales + 展示型广告数据.Sales + 品牌视频广告数据.Sales ） | E69: IFERROR(BC5/(BM5+BV5+CE5),0)
A70: SP+SBV | B70: BE5 | C70: 广告CPA | D70: （SP广告数据.Spend + 品牌视频广告数据.Spend）/ SP+SBV . AD单 | E70: IFERROR(ROUNDUP((BO5+CG5)/BG5,1),0)
B71: BF5 | C71: 广告CVR | D71: SP+SBV . AD单 / (SP广告数据.Click + 品牌视频广告数据.Click) | E71: IFERROR(BG5/(BI5+CA5),0)
B72: BG5 | C72: AD单 | D72: SP广告数据.订单 + 品牌视频广告数据.订单 | E72: BL5+CD5
A73: SP广告数据 | B73: BH5 | C73: Impressions | D73: 满足 SP.日期 = 子表.日期 SP.广告ASIN = 子表.SKU1 数据一 累加 SP.展示量（一般只有一条） 满足 SP.日期 = 子表.日期 SP.广告ASIN = 子表.SKU2 数据二 累加 SP.展示量（一般只有一条） 最后结果 数据一 + 数据二 | E73: SUMIFS(SP!I:I,SP!A:A,N5,SP!H:H,$P$2)+SUMIFS(SP!I:I,SP!A:A,N5,SP!H:H,$T$2)
B74: BI5 | C74: Click | D74: 满足 SP.日期 = 子表.日期 SP.广告ASIN = 子表.SKU1 数据一 累加 SP.点击量（一般只有一条） 满足 SP.日期 = 子表.日期 SP.广告ASIN = 子表.SKU2 数据二 累加 SP.点击量（一般只有一条） 最后结果 数据一 + 数据二 | E74: SUMIFS(SP!J:J,SP!A:A,N5,SP!H:H,$P$2)+SUMIFS(SP!J:J,SP!A:A,N5,SP!H:H,$T$2)
B75: BJ5 | C75: CTR | D75: 满足 SP.日期 = 子表.日期 SP.广告ASIN = 子表.SKU1 数据一 累加 SP.点击率(CTR)（一般只有一条） 满足 SP.日期 = 子表.日期 SP.广告ASIN = 子表.SKU2 数据二 累加 SP.点击率(CTR)（一般只有一条） 最后结果 数据一 + 数据二 | E75: SUMIFS(SP!K:K,SP!A:A,N5,SP!H:H,$P$2)+SUMIFS(SP!K:K,SP!A:A,N5,SP!H:H,$T$2)
B76: BK5 | C76: CPC | D76: 满足 SP.日期 = 子表.日期 SP.广告ASIN = 子表.SKU1 数据一 累加 SP.每次点击成本(CPC)（一般只有一条） 满足 SP.日期 = 子表.日期 SP.广告ASIN = 子表.SKU2 数据二 累加 SP.每次点击成本(CPC)（一般只有一条） 最后结果 数据一 + 数据二 | E76: SUMIFS(SP!L:L,SP!A:A,N5,SP!H:H,$P$2)+SUMIFS(SP!L:L,SP!A:A,N5,SP!H:H,$T$2)
B77: BL5 | C77: 订单 | D77: 满足 SP.日期 = 子表.日期 SP.广告ASIN = 子表.SKU1 数据一 累加 SP.7天总订单数(#)（一般只有一条） 满足 SP.日期 = 子表.日期 SP.广告ASIN = 子表.SKU2 数据二 累加 SP.7天总订单数(#)（一般只有一条） 最后结果 数据一 + 数据二 | E77: SUMIFS(SP!Q:Q,SP!A:A,N6,SP!H:H,$P$2)+SUMIFS(SP!Q:Q,SP!A:A,N6,SP!H:H,$T$2)
B78: BM5 | C78: Sales | D78: 满足 SP.日期 = 子表.日期 SP.广告ASIN = 子表.SKU1 数据一 累加 SP.7天总销售量(#)（一般只有一条） 满足 SP.日期 = 子表.日期 SP.广告ASIN = 子表.SKU2 数据二 累加 SP.7天总销售量(#)（一般只有一条） 最后结果 数据一 + 数据二 | E78: SUMIFS(SP!R:R,SP!A:A,N6,SP!H:H,$P$2)+SUMIFS(SP!R:R,SP!A:A,N6,SP!H:H,$T$2)
B79: BN5 | C79: CR | D79: 满足 SP.日期 = 子表.日期 SP.广告ASIN = 子表.SKU1 数据一 累加 SP.7天的转化率（一般只有一条） 满足 SP.日期 = 子表.日期 SP.广告ASIN = 子表.SKU2 数据二 累加 SP.7天的转化率（一般只有一条） 最后结果 数据一 + 数据二 | E79: SUMIFS(SP!S:S,SP!A:A,N6,SP!H:H,$P$2)+SUMIFS(SP!S:S,SP!A:A,N6,SP!H:H,$T$2)
B80: BO5 | C80: Spend | D80: 满足 SP.日期 = 子表.日期 SP.广告ASIN = 子表.SKU1 数据一 累加 SP.花费（一般只有一条） 满足 SP.日期 = 子表.日期 SP.广告ASIN = 子表.SKU2 数据二 累加 SP.花费（一般只有一条） 最后结果 数据一 + 数据二 | E80: SUMIFS(SP!M:M,SP!A:A,N6,SP!H:H,$P$2)+SUMIFS(SP!M:M,SP!A:A,N6,SP!H:H,$T$2)
B81: BP5 | C81: ACOS | D81: 满足 SP.日期 = 子表.日期 SP.广告ASIN = 子表.SKU1 数据一 累加 SP.广告成本销售比(ACoS)（一般只有一条） 满足 SP.日期 = 子表.日期 SP.广告ASIN = 子表.SKU2 数据二 累加 SP.广告成本销售比(ACoS)（一般只有一条） 最后结果 数据一 + 数据二 | E81: SUMIFS(SP!O:O,SP!A:A,N6,SP!H:H,$P$2)+SUMIFS(SP!O:O,SP!A:A,N6,SP!H:H,$T$2)
A82: 展示型广告数据 | B82: BQ5 | C82: Impressions | D82: 满足 SD.日期 = 子表.日期 SD.广告SKU = 子表.SKU1 数据一 累加 SD.展示量（一般只有一条） 满足 SD.日期 = 子表.日期 SD.广告SKU = 子表.SKU2 数据二 累加 SD.展示量（一般只有一条） 最后结果 数据一 + 数据二 | E82: SUMIFS(SD!J:J,SD!A:A,N5,SD!H:H,$P$2)+SUMIFS(SD!J:J,SD!A:A,N5,SD!H:H,$T$2)
B83: BR5 | C83: Click | D83: 满足 SD.日期 = 子表.日期 SD.广告SKU = 子表.SKU1 数据一 累加 SD.点击量（一般只有一条） 满足 SD.日期 = 子表.日期 SD.广告SKU = 子表.SKU2 数据二 累加 SD.点击量（一般只有一条） 最后结果 数据一 + 数据二 | E83: SUMIFS(SD!L:L,SD!A:A,N5,SD!H:H,$P$2)+SUMIFS(SD!L:L,SD!A:A,N5,SD!H:H,$T$2)
B84: BS5 | C84: CTR | D84: Click / Impressions | E84: IFERROR(BR5/BQ5,0)
B85: BT5 | C85: CPC | D85: Spend / Click | E85: IFERROR(BX5/BR5,0)
B86: BU5 | C86: 订单 | D86: 满足 SD.日期 = 子表.日期 SD.广告SKU = 子表.SKU1 数据一 累加 SD.14天总销售量(#)（一般只有一条） 满足 SD.日期 = 子表.日期 SD.广告SKU = 子表.SKU2 数据二 累加 SD.14天总销售量(#)（一般只有一条） 最后结果 数据一 + 数据二 | E86: SUMIFS(SD!U:U,SD!A:A,N5,SD!H:H,$P$2)+SUMIFS(SD!U:U,SD!A:A,N5,SD!H:H,$T$2)
B87: BV5 | C87: Sales | D87: 满足 SD.日期 = 子表.日期 SD.广告SKU = 子表.SKU1 数据一 累加 SD.14天总销售额（一般只有一条） 满足 SD.日期 = 子表.日期 SD.广告SKU = 子表.SKU2 数据二 累加 SD.14天总销售额（一般只有一条） 最后结果 数据一 + 数据二 | E87: SUMIFS(SD!V:V,SD!A:A,N5,SD!H:H,$P$2)+SUMIFS(SD!V:V,SD!A:A,N5,SD!H:H,$T$2)
B88: BW5 | C88: CR | D88: 订单 / Click | E88: IFERROR(BU5/BR5,0)
B89: BX5 | C89: Spend | D89: 满足 SD.日期 = 子表.日期 SD.广告SKU = 子表.SKU1 数据一 累加 SD.花费（一般只有一条） 满足 SD.日期 = 子表.日期 SD.广告SKU = 子表.SKU2 数据二 累加 SD.花费（一般只有一条） 最后结果 数据一 + 数据二 | E89: SUMIFS(SD!O:O,SD!A:A,N5,SD!H:H,$P$2)+SUMIFS(SD!O:O,SD!A:A,N5,SD!H:H,$T$2)
B90: BY5 | C90: ACOS | D90: Spend / Sales | E90: IFERROR(BX5/BV5,0)
A91: 品牌视频广告数据 | B91: BZ5 | C91: Impressions | D91: 满足 SB.日期 = 子表.日期 SB.SKU/ASIN = 子表.SKU1 数据一 累加 SB.展示量（一般只有一条） 满足 SB.日期 = 子表.日期 SB.SKU/ASIN = 子表.SKU2 数据二 累加 SB.展示量（一般只有一条） 最后结果 数据一 + 数据二 | E91: SUMIFS(SB!H:H,SB!B:B,N5,SB!A:A,$P$2)+SUMIFS(SB!H:H,SB!B:B,N5,SB!A:A,$T$2)
B92: CA5 | C92: Click | D92: 满足 SB.日期 = 子表.日期 SB.SKU/ASIN = 子表.SKU1 数据一 累加 SB.点击量（一般只有一条） 满足 SB.日期 = 子表.日期 SB.SKU/ASIN = 子表.SKU2 数据二 累加 SB.点击量（一般只有一条） 最后结果 数据一 + 数据二 | E92: SUMIFS(SB!I:I,SB!B:B,N5,SB!A:A,$P$2)+SUMIFS(SB!I:I,SB!B:B,N5,SB!A:A,$T$2)
B93: CB5 | C93: CTR | D93: Click / Impressions | E93: IFERROR(CA5/BZ5,0)
B94: CC5 | C94: CPC | D94: Spend / Click | E94: IFERROR(CG5/CA5,0)
B95: CD5 | C95: 订单 | D95: 满足 SB.日期 = 子表.日期 SB.SKU/ASIN = 子表.SKU1 数据一 累加 SB.14天总销售量(#)（一般只有一条） 满足 SB.日期 = 子表.日期 SB.SKU/ASIN = 子表.SKU2 数据二 累加 SB.14天总销售量(#)（一般只有一条） 最后结果 数据一 + 数据二 | E95: SUMIFS(SB!Q:Q,SB!B:B,N5,SB!A:A,$P$2)+SUMIFS(SB!Q:Q,SB!B:B,N5,SB!A:A,$T$2)
B96: CE5 | C96: Sales | D96: 满足 SB.日期 = 子表.日期 SB.SKU/ASIN = 子表.SKU1 数据一 累加 SB.14天总销售额（一般只有一条） 满足 SB.日期 = 子表.日期 SB.SKU/ASIN = 子表.SKU2 数据二 累加 SB.14天总销售额（一般只有一条） 最后结果 数据一 + 数据二 | E96: SUMIFS(SB!O:O,SB!B:B,N5,SB!A:A,$P$2)+SUMIFS(SB!O:O,SB!B:B,N5,SB!A:A,$T$2)
B97: CF5 | C97: CR | D97: 订单 / Click | E97: IFERROR(CD5/CA5,0)
B98: CG5 | C98: Spend | D98: 满足 SB.日期 = 子表.日期 SB.SKU/ASIN = 子表.SKU1 数据一 累加 SB.花费（一般只有一条） 满足 SB.日期 = 子表.日期 SB.SKU/ASIN = 子表.SKU2 数据二 累加 SB.花费（一般只有一条） 最后结果 数据一 + 数据二 | E98: SUMIFS(SB!L:L,SB!B:B,N5,SB!A:A,$P$2)+SUMIFS(SB!L:L,SB!B:B,N5,SB!A:A,$T$2)
B99: CH5 | C99: ACOS | D99: Spend / Sales | E99: IFERROR(CG5/CE5,0)

Sheet 业务报告
A1: A1 | B1: 日期
A2: B1 | B2: MSKU/WOOT ASIN
A3: C1 | B3: 店铺
A4: D1 | B4: （父）ASIN
A5: E1 | B5: （子）ASIN
A6: F1 | B6: 商品名称
A7: G1 | B7: 会话次数 –APP
A8: H1 | B8: 会话次数 – PC
A9: I1 | B9: 会话次数 – 总计
A10: J1 | B10: 会话百分比 – 移动应用
A11: K1 | B11: 会话百分比 – 浏览器
A12: L1 | B12: 会话百分比 – 总计
... A50: AX1 | B50: None

Sheet WT报告
A1: A2 | B1: 采购价
A2: B2 | B2: 活动价
A3: C2 | B3: 报告日期
A4: D2 | B4: 报告日期
A5: E2 | B5: 星期
A6: F2 | B6: 订单编号
A7: G2 | B7: 产品名称
A8: H2 | B8: 子Asin
A9: I2 | B9: Woot订单数量
A10: J2 | B10: 广告订单数量
A11: K2 | B11: 广告的转化率
A12: L2 | B12: 广告投入产出比
... A26: Z2 | B26: 总销售额

Sheet SP
A1: A1 | B1: 日期
A2: B1 | B2: 广告组合名称
A3: C1 | B3: 货币
A4: D1 | B4: 广告活动名称
A5: E1 | B5: 广告组名称
A6: F1 | B6: Retailer
A7: G1 | B7: 广告SKU/VC-ASIN
A8: H1 | B8: 广告ASIN
A9: I1 | B9: 展示量
A10: J1 | B10: 点击量
A11: K1 | B11: 点击率(CTR)
A12: L1 | B12: 每次点击成本(CPC)
... A23: W1 | B23: 7天内其他SKU销售额

Sheet SD
A1: A1 | B1: 日期
A2: B1 | B2: 广告组合名称
A3: C1 | B3: 货币
A4: D1 | B4: 广告活动名称
A5: E1 | B5: 费用类型
A6: F1 | B6: 广告组名称
A7: G1 | B7: 竞价优化
A8: H1 | B8: 广告SKU
A9: I1 | B9: 广告ASIN
A10: J1 | B10: 展示量
A11: K1 | B11: 可查看的展现量
A12: L1 | B12: 点击量
... A33: AG1 | B33: 14 天内“品牌新客”已售商品数量 (#) -(点击)

Sheet SB
A1: A1 | B1: SKU/ASIN
A2: B1 | B2: 日期
A3: C1 | B3: 广告组合名称
A4: D1 | B4: 货币
A5: E1 | B5: 广告活动名称
A6: F1 | B6: 费用类型
A7: G1 | B7: 国家/地区
A8: H1 | B8: 展示量
A9: I1 | B9: 点击量
A10: J1 | B10: 点击率(CTR)
A11: K1 | B11: 每次点击成本(CPC)
A12: L1 | B12: 花费
... A56: BD1 | B56: Long-Term ROAS

Sheet Base
A1: A1 | B1: 站点
A2: B1 | B2: 店铺
A3: C1 | B3: 型号
A4: D1 | B4: SKU
A5: E1 | B5: ASIN
A6: F1 | B6: 品牌
A7: G1 | B7: 备注

Sheet Sheet7
N1: 年份 | O1: 2025 | P1: SKU1 | T1: SKU2 | X1: WOOT | AB1: 退货 | AC1: 182 | AD1: 5.87 | AE1: SCP0 | AF1: WTP0 | AG1: VCP0 | AH1: 变SCP0 | AI1: 价格 | AJ1: 广告数据汇总 | BH1: 广告明细
N2: 月份 | O2: 9 | P2: ZS-56AI-01ZJ | X2: B0FC6N29Y5 | AB2: 0.08 | AC2: 7.1 | AD2: 0.08 | AE2: =AI2*(1-$AD$2-4%-$AB$2)-$AD$1-$AC$1/$AC$2 -> 32.488197 | AF2: =AI2*60%*(1-4%)-AC1/AC2 -> 20.440437 | AG2: =59.96*(1-5%)-89.99*15%-AC1/AC2 -> 17.829697 | AH2: =79.99*(1-15%-4%-$AB$2)-$AD$1-$AC$1/$AC$2 -> 26.888897 | AI2: 79.99
N3: 销售数据 - TM002 | Y3: 毛利润 | AJ3: WOOT广告数据汇总 | AT3: SC广告数据汇总 | BE3: SP+SBV | BH3: SP广告数据 | BQ3: 展示型广告数据 | BZ3: 品牌视频广告数据
A4: 问题 | B4: 调整 | C4: 大类 排名 | D4: 小类 排名 | E4: KW (Laser)自然位 | F4: 活动 | G4: 划线价/ VC LP | H4: 折扣 | I4: 成交 价 | J4: WT采购价 | K4: 评论 星级 | L4: 新差 评 | M4: 星期 | N4: 日期 | O4: 移动 | P4: PC | Q4: 访客数 | R4: 销量 | S4: 销量 转化率 | T4: 销售额 | U4: 测评 单量 | V4: WT 单量 | W4: WT销售额 | X4: 父体 单量 | Y4: 测评 费用 US$ | Z4: SC 广告 利润$ | AA4: SC 利润 US$ | AB4: SC 毛利 率 | AC4: WT 广告利润$ | AD4: WT 利润 US$ | AE4: SC 变体 利润$ | AF4: VC 变体 利润$ | AG4: 总 利润 US$ | AH4: 总 毛利 率 | AI4: 父体 单个 毛利 | AJ4: 总T ACOS | AK4: 总CPO | AL4: 广告CPA | AM4: 广告 CVR | AN4: CPC | AO4: 广告单 占比 | AP4: 点击 | AQ4: CTR | AR4: AD 单 | AS4: 广告费 | AT4: 总T ACOS | AU4: 总CPO | AV4: 广告CPA | AW4: 广告 CVR | AX4: CPC | AY4: 广告单 占比 | AZ4: 点击 | BA4: CTR | BB4: AD 单 | BC4: 广告费 | BD4: ACoS | BE4: 广告CPA | BF4: 广告 CVR | BG4: AD 单 | BH4: Impressions | BI4: Click | BJ4: CTR | BK4: CPC | BL4: 订单 | BM4: Sales | BN4: CR | BO4: Spend | BP4: ACOS | BQ4: Impressions | BR4: Click | BS4: CTR | BT4: CPC | BU4: 订单 | BV4: Sales | BW4: CR | BX4: Spend | BY4: ACOS | BZ4: Impressions | CA4: Click | CB4: CTR | CC4: CPC | CD4: 订单 | CE4: Sales | CF4: CR | CG4: Spend | CH4: ACOS
A5: {=IFERROR(LOOKUP(1,0/(([2]业务报告!$A:$A=$N5)*([2]业务报告!$B:$B=$P$2)),[2]业务报告!AU:AU),"")} -> 0 | B5: {=IFERROR(LOOKUP(1,0/(([2]业务报告!$A:$A=$N5)*([2]业务报告!$B:$B=$P$2)),[2]业务报告!AV:AV),"")} -> 2.大词词组降低cpc 提高top位比例，广告点击去到top 点击17次，未转化，今晚再观察一晚不做调整，对跑出来不相关词做否定 | C5: =SUMIFS([2]业务报告!AC:AC,[2]业务报告!$A:$A,$N5,[2]业务报告!$B:$B,$P$2) -> 0 | D5: =SUMIFS([2]业务报告!AD:AD,[2]业务报告!$A:$A,$N5,[2]业务报告!$B:$B,$P$2) -> 0 | E5: {=_xlfn.XLOOKUP($N5&$P$2,[2]业务报告!$A:$A&[2]业务报告!$B:$B,[2]业务报告!AE:AE,"")} -> 0 | F5: {=IFERROR(LOOKUP(1,0/(([2]业务报告!$A:$A=$N5)*([2]业务报告!$B:$B=$P$2)),[2]业务报告!AK:AK),0)} -> WBD | G5: =SUMIFS([2]业务报告!AF:AF,[2]业务报告!$A:$A,$N5,[2]业务报告!$B:$B,$P$2) -> 319.89 | H5: {=IFERROR(LOOKUP(1,0/(([2]业务报告!$A:$A=$N5)*([2]业务报告!B:B=$P$2)),[2]业务报告!AG:AG),0)} -> / | I5: {=IFERROR(LOOKUP(1,0/(([2]业务报告!$A:$A=$N5)*([2]业务报告!$B:$B=$P$2)),[2]业务报告!AH:AH),0)} -> 79.99 | J5: =SUMIFS([2]WT报告!A:A,[2]WT报告!$C:$C,$N5,[2]WT报告!$H:$H,$X$2) -> 0 | K5: {=IFERROR(LOOKUP(1,0/(([2]业务报告!$A:$A=$N5)*([2]业务报告!$B:$B=$P$2)),[2]业务报告!AI:AI),0)} -> 0 | L5: {=IFERROR(LOOKUP(1,0/(([2]业务报告!$A:$A=$N5)*([2]业务报告!$B:$B=$P$2)),[2]业务报告!AJ:AJ),0)} -> 0 | M5: =IFERROR("周"&WEEKDAY(N5,2),"-") -> 周1 | N5: =DATE($O$1,$O$2,1) -> 45901 | O5: =SUMIFS([2]业务报告!G:G,[2]业务报告!$A:$A,$N5,[2]业务报告!$B:$B,$P$2)+SUMIFS([2]业务报告!G:G,[2]业务报告!$A:$A,$N5,[2]业务报告!$B:$B,$T$2) -> 0 | P5: =SUMIFS([2]业务报告!H:H,[2]业务报告!$A:$A,$N5,[2]业务报告!$B:$B,$P$2)+SUMIFS([2]业务报告!H:H,[2]业务报告!$A:$A,$N5,[2]业务报告!$B:$B,$T$2) -> 0 | Q5: =SUMIFS([2]业务报告!I:I,[2]业务报告!$A:$A,$N5,[2]业务报告!$B:$B,$P$2)+SUMIFS([2]业务报告!I:I,[2]业务报告!$A:$A,$N5,[2]业务报告!$B:$B,$T$2) -> 0 | R5: =SUMIFS([2]业务报告!T:T,[2]业务报告!$A:$A,$N5,[2]业务报告!$B:$B,$P$2)+SUMIFS([2]业务报告!T:T,[2]业务报告!$A:$A,$N5,[2]业务报告!$B:$B,$T$2) -> 0 | S5: =IFERROR((R5+V5)/Q5,0) -> 0 | T5: =SUMIFS([2]业务报告!X:X,[2]业务报告!$A:$A,$N5,[2]业务报告!$B:$B,$P$2)+SUMIFS([2]业务报告!X:X,[2]业务报告!$A:$A,$N5,[2]业务报告!$B:$B,$T$2) -> 0 | U5: =SUMIFS([2]业务报告!AO:AO,[2]业务报告!$A:$A,$N5,[2]业务报告!$B:$B,$P$2)+SUMIFS([2]业务报告!AP:AP,[2]业务报告!$A:$A,$N5,[2]业务报告!$B:$B,$P$2) -> 0 | V5: =SUMIFS([2]WT报告!I:I,[2]WT报告!$C:$C,$N5,[2]WT报告!$H:$H,$X$2) -> 0 | W5: =SUMIFS([2]WT报告!Z:Z,[2]WT报告!$C:$C,$N5,[2]WT报告!$H:$H,$X$2) -> 0 | X5: =SUMIFS([2]业务报告!AS:AS,[2]业务报告!$A:$A,$N5,[2]业务报告!$B:$B,$P$2)+SUMIFS([2]业务报告!AS:AS,[2]业务报告!$A:$A,$N5,[2]业务报告!$B:$B,$T$2)+V5 -> 0 | Y5: =SUMIFS([2]业务报告!AO:AO,[2]业务报告!$A:$A,$N5,[2]业务报告!$B:$B,$P$2)*SUMIFS([2]业务报告!AM:AM,[2]业务报告!$A:$A,$N5,[2]业务报告!$B:$B,$P$2)/$AC$2+SUMIFS([2]业务报告!AP:AP,[2]业务报告!$A:$A,$N5,[2]业务报告!$B:$B,$P$2)*SUMIFS([2]业务报告!AN:AN,[2]业务报告!$A:$A,$N5,[2]业务报告!$B:$B,$P$2)/$AC$2 -> 0 | Z5: =(I5*(1-$AD$2-4%-10%)-$AD$1-$AC$1/$AC$2)*BB5-BC5 -> 0 | AA5: =(I5*(1-$AD$2-4%-10%)-$AD$1-$AC$1/$AC$2)*(R5-IF(R5>V5,SUMIFS([2]业务报告!AO:AO,[2]业务报告!$A:$A,$N5,[2]业务报告!$B:$B,$P$2),0))-BC5 -> 0 | AB5: =IFERROR(AA5/(I5*R5),0) -> 0 | AC5: =AR5*(J5-$AC$1/$AC$2-J5*4%)-AS5 -> 0 | AD5: =(V5-IF(R5<V5,SUMIFS([2]业务报告!AO:AO,[2]业务报告!$A:$A,$N5,[2]业务报告!$B:$B,$P$2),0))*(J5-$AC$1/$AC$2-J5*4%)-AS5 -> 0 | AE5: {=IFERROR(LOOKUP(1,0/(([2]业务报告!$A:$A=$N5)*([2]业务报告!$B:$B=$P$2)),[2]业务报告!AQ:AQ),0)*$AH$2} -> 0 | AF5: {=IFERROR(LOOKUP(1,0/(([2]业务报告!$A:$A=$N5)*([2]业务报告!$B:$B=$P$2)),[2]业务报告!AR:AR),0)*$AG$2} -> 0 | AG5: =AA5+AD5+AE5+AF5-Y5 -> 0 | AH5: =IFERROR((AG5)/(T5+J5*V5),0) -> 0 | AI5: =IFERROR((AG5)/(X5),0) -> 0 | AJ5: =IFERROR(AS5/(V5*J5),0) -> 0 | AK5: =IFERROR(ROUNDUP(AS5/V5,1),0) -> 0 | AL5: =SUMIFS([2]WT报告!S:S,[2]WT报告!$C:$C,$N5,[2]WT报告!$H:$H,$X$2) -> 0 | AM5: =IFERROR((AR5)/AP5,0) -> 0 | AN5: =SUMIFS([2]WT报告!N:N,[2]WT报告!$C:$C,$N5,[2]WT报告!$H:$H,$X$2) -> 0 | AO5: =IFERROR(AR5/(V5),0) -> 0 | AP5: =SUMIFS([2]WT报告!P:P,[2]WT报告!$C:$C,$N5,[2]WT报告!$H:$H,$X$2) -> 0 | AQ5: =SUMIFS([2]WT报告!Q:Q,[2]WT报告!$C:$C,$N5,[2]WT报告!$H:$H,$X$2) -> 0 | AR5: =SUMIFS([2]WT报告!J:J,[2]WT报告!$C:$C,$N5,[2]WT报告!$H:$H,$X$2) -> 0 | AS5: =SUMIFS([2]WT报告!M:M,[2]WT报告!$C:$C,$N5,[2]WT报告!$H:$H,$X$2) -> 0 | AT5: =IFERROR((BO5+BX5+CG5)/(R5*I5),0) -> 0 | AU5: =IFERROR(ROUNDUP(BC5/R5,1),0) -> 0 | AV5: =IFERROR(ROUNDUP(BC5/BB5,1),0) -> 0 | AW5: =IFERROR((BB5)/AZ5,0) -> 0 | AX5: =IFERROR(BC5/AZ5,0) -> 0 | AY5: =IFERROR((BL5+BU5+CD5)/(R5+V5),0) -> 0 | AZ5: =BI5+BR5+CA5 -> 0 | BA5: =IFERROR((BI5+BR5+CA5)/(BH5+BQ5+BZ5),0) -> 0 | BB5: =BL5+BU5+CD5 -> 0 | BC5: =ROUND(BO5+BX5+CG5,2) -> 0 | BD5: =IFERROR(BC5/(BM5+BV5+CE5),0) -> 0 | BE5: =IFERROR(ROUNDUP((BO5+CG5)/BG5,1),0) -> 0 | BF5: =IFERROR(BG5/(BI5+CA5),0) -> 0 | BG5: =BL5+CD5 -> 0 | BH5: =SUMIFS([2]SP!J:J,[2]SP!A:A,N5,[2]SP!H:H,$P$2)+SUMIFS([2]SP!J:J,[2]SP!A:A,N5,[2]SP!H:H,$T$2) -> 0 | BI5: =SUMIFS([2]SP!K:K,[2]SP!A:A,N5,[2]SP!H:H,$P$2)+SUMIFS([2]SP!K:K,[2]SP!A:A,N5,[2]SP!H:H,$T$2) -> 0 | BJ5: =IFERROR(BI5/BH5,0) -> 0 | BK5: =IFERROR(BO5/BI5,0) -> 0 | BL5: =SUMIFS([2]SP!R:R,[2]SP!A:A,N5,[2]SP!H:H,$P$2)+SUMIFS([2]SP!R:R,[2]SP!A:A,N5,[2]SP!H:H,$T$2) -> 0 | BM5: =SUMIFS([2]SP!O:O,[2]SP!A:A,$N5,[2]SP!H:H,$P$2)+SUMIFS([2]SP!O:O,[2]SP!A:A,$N5,[2]SP!H:H,$T$2) -> 0 | BN5: =IFERROR(BL5/BI5,0) -> 0 | BO5: =SUMIFS([2]SP!N:N,[2]SP!A:A,N5,[2]SP!H:H,$P$2)+SUMIFS([2]SP!N:N,[2]SP!A:A,N5,[2]SP!H:H,$T$2) -> 0 | BP5: =IFERROR(BO5/BM5,0) -> 0 | BQ5: =SUMIFS([2]SD!J:J,[2]SD!A:A,N5,[2]SD!H:H,$P$2)+SUMIFS([2]SD!J:J,[2]SD!A:A,N5,[2]SD!H:H,$T$2) -> 0 | BR5: =SUMIFS([2]SD!L:L,[2]SD!A:A,N5,[2]SD!H:H,$P$2)+SUMIFS([2]SD!L:L,[2]SD!A:A,N5,[2]SD!H:H,$T$2) -> 0 | BS5: =IFERROR(BR5/BQ5,0) -> 0 | BT5: =IFERROR(BX5/BR5,0) -> 0 | BU5: =SUMIFS([2]SD!U:U,[2]SD!A:A,N5,[2]SD!H:H,$P$2)+SUMIFS([2]SD!U:U,[2]SD!A:A,N5,[2]SD!H:H,$T$2) -> 0 | BV5: =SUMIFS([2]SD!V:V,[2]SD!A:A,N5,[2]SD!H:H,$P$2)+SUMIFS([2]SD!V:V,[2]SD!A:A,N5,[2]SD!H:H,$T$2) -> 0 | BW5: =IFERROR(BU5/BR5,0) -> 0 | BX5: =SUMIFS([2]SD!O:O,[2]SD!A:A,N5,[2]SD!H:H,$P$2)+SUMIFS([2]SD!O:O,[2]SD!A:A,N5,[2]SD!H:H,$T$2) -> 0 | BY5: =IFERROR(BX5/BV5,0) -> 0 | BZ5: =SUMIFS([2]SB!H:H,[2]SB!B:B,N5,[2]SB!A:A,$P$2)+SUMIFS([2]SB!H:H,[2]SB!B:B,N5,[2]SB!A:A,$T$2) -> 0 | CA5: =SUMIFS([2]SB!I:I,[2]SB!B:B,N5,[2]SB!A:A,$P$2)+SUMIFS([2]SB!I:I,[2]SB!B:B,N5,[2]SB!A:A,$T$2) -> 0 | CB5: =IFERROR(CA5/BZ5,0) -> 0 | CC5: =IFERROR(CG5/CA5,0) -> 0 | CD5: =SUMIFS([2]SB!Q:Q,[2]SB!B:B,N5,[2]SB!A:A,$P$2)+SUMIFS([2]SB!Q:Q,[2]SB!B:B,N5,[2]SB!A:A,$T$2) -> 0 | CE5: =SUMIFS([2]SB!O:O,[2]SB!B:B,N5,[2]SB!A:A,$P$2)+SUMIFS([2]SB!O:O,[2]SB!B:B,N5,[2]SB!A:A,$T$2) -> 0 | CF5: =IFERROR(CD5/CA5,0) -> 0 | CG5: =SUMIFS([2]SB!L:L,[2]SB!B:B,N5,[2]SB!A:A,$P$2)+SUMIFS([2]SB!L:L,[2]SB!B:B,N5,[2]SB!A:A,$T$2) -> 0 | CH5: =IFERROR(CG5/CE5,0) -> 0
A6: {=IFERROR(LOOKUP(1,0/(([2]业务报告!$A:$A=$N6)*([2]业务报告!$B:$B=$P$2)),[2]业务报告!AU:AU),"")} -> 0 | B6: {=IFERROR(LOOKUP(1,0/(([2]业务报告!$A:$A=$N6)*([2]业务报告!$B:$B=$P$2)),[2]业务报告!AV:AV),"")} -> 0 | C6: =SUMIFS([2]业务报告!AC:AC,[2]业务报告!$A:$A,$N6,[2]业务报告!$B:$B,$P$2) -> 0 | D6: =SUMIFS([2]业务报告!AD:AD,[2]业务报告!$A:$A,$N6,[2]业务报告!$B:$B,$P$2) -> 0 | E6: {=_xlfn.XLOOKUP($N6&$P$2,[2]业务报告!$A:$A&[2]业务报告!$B:$B,[2]业务报告!AE:AE,"")} -> 0 | F6: {=IFERROR(LOOKUP(1,0/(([2]业务报告!$A:$A=$N6)*([2]业务报告!$B:$B=$P$2)),[2]业务报告!AK:AK),0)} -> WBD | G6: =SUMIFS([2]业务报告!AF:AF,[2]业务报告!$A:$A,$N6,[2]业务报告!$B:$B,$P$2) -> 319.89 | H6: {=IFERROR(LOOKUP(1,0/(([2]业务报告!$A:$A=$N6)*([2]业务报告!B:B=$P$2)),[2]业务报告!AG:AG),0)} -> / | I6: {=IFERROR(LOOKUP(1,0/(([2]业务报告!$A:$A=$N6)*([2]业务报告!$B:$B=$P$2)),[2]业务报告!AH:AH),0)} -> 79.99 | J6: =SUMIFS([2]WT报告!A:A,[2]WT报告!$C:$C,$N6,[2]WT报告!$H:$H,$X$2) -> 0 | K6: {=IFERROR(LOOKUP(1,0/(([2]业务报告!$A:$A=$N6)*([2]业务报告!$B:$B=$P$2)),[2]业务报告!AI:AI),0)} -> 0 | L6: {=IFERROR(LOOKUP(1,0/(([2]业务报告!$A:$A=$N6)*([2]业务报告!$B:$B=$P$2)),[2]业务报告!AJ:AJ),0)} -> 0 | M6: =IFERROR("周"&WEEKDAY(N6,2),"-") -> 周2 | N6: =DATE($O$1,$O$2,DAY(N5)+1) -> 45902 | O6: =SUMIFS([2]业务报告!G:G,[2]业务报告!$A:$A,$N6,[2]业务报告!$B:$B,$P$2)+SUMIFS([2]业务报告!G:G,[2]业务报告!$A:$A,$N6,[2]业务报告!$B:$B,$T$2) -> 0 | P6: =SUMIFS([2]业务报告!H:H,[2]业务报告!$A:$A,$N6,[2]业务报告!$B:$B,$P$2)+SUMIFS([2]业务报告!H:H,[2]业务报告!$A:$A,$N6,[2]业务报告!$B:$B,$T$2) -> 0 | Q6: =SUMIFS([2]业务报告!I:I,[2]业务报告!$A:$A,$N6,[2]业务报告!$B:$B,$P$2)+SUMIFS([2]业务报告!I:I,[2]业务报告!$A:$A,$N6,[2]业务报告!$B:$B,$T$2) -> 0 | R6: =SUMIFS([2]业务报告!T:T,[2]业务报告!$A:$A,$N6,[2]业务报告!$B:$B,$P$2)+SUMIFS([2]业务报告!T:T,[2]业务报告!$A:$A,$N6,[2]业务报告!$B:$B,$T$2) -> 0 | S6: =IFERROR((R6+V6)/Q6,0) -> 0 | T6: =SUMIFS([2]业务报告!X:X,[2]业务报告!$A:$A,$N6,[2]业务报告!$B:$B,$P$2)+SUMIFS([2]业务报告!X:X,[2]业务报告!$A:$A,$N6,[2]业务报告!$B:$B,$T$2) -> 0 | U6: =SUMIFS([2]业务报告!AO:AO,[2]业务报告!$A:$A,$N6,[2]业务报告!$B:$B,$P$2)+SUMIFS([2]业务报告!AP:AP,[2]业务报告!$A:$A,$N6,[2]业务报告!$B:$B,$P$2) -> 0 | V6: =SUMIFS([2]WT报告!I:I,[2]WT报告!$C:$C,$N6,[2]WT报告!$H:$H,$X$2) -> 0 | W6: =SUMIFS([2]WT报告!Z:Z,[2]WT报告!$C:$C,$N6,[2]WT报告!$H:$H,$X$2) -> 0 | X6: =SUMIFS([2]业务报告!AS:AS,[2]业务报告!$A:$A,$N6,[2]业务报告!$B:$B,$P$2)+SUMIFS([2]业务报告!AS:AS,[2]业务报告!$A:$A,$N6,[2]业务报告!$B:$B,$T$2)+V6 -> 0 | Y6: =SUMIFS([2]业务报告!AO:AO,[2]业务报告!$A:$A,$N6,[2]业务报告!$B:$B,$P$2)*SUMIFS([2]业务报告!AM:AM,[2]业务报告!$A:$A,$N6,[2]业务报告!$B:$B,$P$2)/$AC$2+SUMIFS([2]业务报告!AP:AP,[2]业务报告!$A:$A,$N6,[2]业务报告!$B:$B,$P$2)*SUMIFS([2]业务报告!AN:AN,[2]业务报告!$A:$A,$N6,[2]业务报告!$B:$B,$P$2)/$AC$2 -> 0 | Z6: =(I6*(1-$AD$2-4%-10%)-$AD$1-$AC$1/$AC$2)*BB6-BC6 -> 0 | AA6: =(I6*(1-$AD$2-4%-10%)-$AD$1-$AC$1/$AC$2)*(R6-IF(R6>V6,SUMIFS([2]业务报告!AO:AO,[2]业务报告!$A:$A,$N6,[2]业务报告!$B:$B,$P$2),0))-BC6 -> 0 | AB6: =IFERROR(AA6/(I6*R6),0) -> 0 | AC6: =AR6*(J6-$AC$1/$AC$2-J6*4%)-AS6 -> 0 | AD6: =(V6-IF(R6<V6,SUMIFS([2]业务报告!AO:AO,[2]业务报告!$A:$A,$N6,[2]业务报告!$B:$B,$P$2),0))*(J6-$AC$1/$AC$2-J6*4%)-AS6 -> 0 | AE6: {=IFERROR(LOOKUP(1,0/(([2]业务报告!$A:$A=$N6)*([2]业务报告!$B:$B=$P$2)),[2]业务报告!AQ:AQ),0)*$AH$2} -> 0 | AF6: {=IFERROR(LOOKUP(1,0/(([2]业务报告!$A:$A=$N6)*([2]业务报告!$B:$B=$P$2)),[2]业务报告!AR:AR),0)*$AG$2} -> 0 | AG6: =AA6+AD6+AE6+AF6-Y6 -> 0 | AH6: =IFERROR((AG6)/(T6+J6*V6),0) -> 0 | AI6: =IFERROR((AG6)/(X6),0) -> 0 | AJ6: =IFERROR(AS6/(V6*J6),0) -> 0 | AK6: =IFERROR(ROUNDUP(AS6/V6,1),0) -> 0 | AL6: =SUMIFS([2]WT报告!S:S,[2]WT报告!$C:$C,$N6,[2]WT报告!$H:$H,$X$2) -> 0 | AM6: =IFERROR((AR6)/AP6,0) -> 0 | AN6: =SUMIFS([2]WT报告!N:N,[2]WT报告!$C:$C,$N6,[2]WT报告!$H:$H,$X$2) -> 0 | AO6: =IFERROR(AR6/(V6),0) -> 0 | AP6: =SUMIFS([2]WT报告!P:P,[2]WT报告!$C:$C,$N6,[2]WT报告!$H:$H,$X$2) -> 0 | AQ6: =SUMIFS([2]WT报告!Q:Q,[2]WT报告!$C:$C,$N6,[2]WT报告!$H:$H,$X$2) -> 0 | AR6: =SUMIFS([2]WT报告!J:J,[2]WT报告!$C:$C,$N6,[2]WT报告!$H:$H,$X$2) -> 0 | AS6: =SUMIFS([2]WT报告!M:M,[2]WT报告!$C:$C,$N6,[2]WT报告!$H:$H,$X$2) -> 0 | AT6: =IFERROR((BO6+BX6+CG6)/(R6*I6),0) -> 0 | AU6: =IFERROR(ROUNDUP(BC6/R6,1),0) -> 0 | AV6: =IFERROR(ROUNDUP(BC6/BB6,1),0) -> 0 | AW6: =IFERROR((BB6)/AZ6,0) -> 0 | AX6: =IFERROR(BC6/AZ6,0) -> 0 | AY6: =IFERROR((BL6+BU6+CD6)/(R6+V6),0) -> 0 | AZ6: =BI6+BR6+CA6 -> 0 | BA6: =IFERROR((BI6+BR6+CA6)/(BH6+BQ6+BZ6),0) -> 0 | BB6: =BL6+BU6+CD6 -> 0 | BC6: =ROUND(BO6+BX6+CG6,2) -> 0 | BD6: =IFERROR(BC6/(BM6+BV6+CE6),0) -> 0 | BE6: =IFERROR(ROUNDUP((BO6+CG6)/BG6,1),0) -> 0 | BF6: =IFERROR(BG6/(BI6+CA6),0) -> 0 | BG6: =BL6+CD6 -> 0 | BH6: =SUMIFS([2]SP!J:J,[2]SP!A:A,N6,[2]SP!H:H,$P$2)+SUMIFS([2]SP!J:J,[2]SP!A:A,N6,[2]SP!H:H,$T$2) -> 0 | BI6: =SUMIFS([2]SP!K:K,[2]SP!A:A,N6,[2]SP!H:H,$P$2)+SUMIFS([2]SP!K:K,[2]SP!A:A,N6,[2]SP!H:H,$T$2) -> 0 | BJ6: =IFERROR(BI6/BH6,0) -> 0 | BK6: =IFERROR(BO6/BI6,0) -> 0 | BL6: =SUMIFS([2]SP!R:R,[2]SP!A:A,N6,[2]SP!H:H,$P$2)+SUMIFS([2]SP!R:R,[2]SP!A:A,N6,[2]SP!H:H,$T$2) -> 0 | BM6: =SUMIFS([2]SP!O:O,[2]SP!A:A,$N6,[2]SP!H:H,$P$2)+SUMIFS([2]SP!O:O,[2]SP!A:A,$N6,[2]SP!H:H,$T$2) -> 0 | BN6: =IFERROR(BL6/BI6,0) -> 0 | BO6: =SUMIFS([2]SP!N:N,[2]SP!A:A,N6,[2]SP!H:H,$P$2)+SUMIFS([2]SP!N:N,[2]SP!A:A,N6,[2]SP!H:H,$T$2) -> 0 | BP6: =IFERROR(BO6/BM6,0) -> 0 | BQ6: =SUMIFS([2]SD!J:J,[2]SD!A:A,N6,[2]SD!H:H,$P$2)+SUMIFS([2]SD!J:J,[2]SD!A:A,N6,[2]SD!H:H,$T$2) -> 0 | BR6: =SUMIFS([2]SD!L:L,[2]SD!A:A,N6,[2]SD!H:H,$P$2)+SUMIFS([2]SD!L:L,[2]SD!A:A,N6,[2]SD!H:H,$T$2) -> 0 | BS6: =IFERROR(BR6/BQ6,0) -> 0 | BT6: =IFERROR(BX6/BR6,0) -> 0 | BU6: =SUMIFS([2]SD!U:U,[2]SD!A:A,N6,[2]SD!H:H,$P$2)+SUMIFS([2]SD!U:U,[2]SD!A:A,N6,[2]SD!H:H,$T$2) -> 0 | BV6: =SUMIFS([2]SD!V:V,[2]SD!A:A,N6,[2]SD!H:H,$P$2)+SUMIFS([2]SD!V:V,[2]SD!A:A,N6,[2]SD!H:H,$T$2) -> 0 | BW6: =IFERROR(BU6/BR6,0) -> 0 | BX6: =SUMIFS([2]SD!O:O,[2]SD!A:A,N6,[2]SD!H:H,$P$2)+SUMIFS([2]SD!O:O,[2]SD!A:A,N6,[2]SD!H:H,$T$2) -> 0 | BY6: =IFERROR(BX6/BV6,0) -> 0 | BZ6: =SUMIFS([2]SB!H:H,[2]SB!B:B,N6,[2]SB!A:A,$P$2)+SUMIFS([2]SB!H:H,[2]SB!B:B,N6,[2]SB!A:A,$T$2) -> 0 | CA6: =SUMIFS([2]SB!I:I,[2]SB!B:B,N6,[2]SB!A:A,$P$2)+SUMIFS([2]SB!I:I,[2]SB!B:B,N6,[2]SB!A:A,$T$2) -> 0 | CB6: =IFERROR(CA6/BZ6,0) -> 0 | CC6: =IFERROR(CG6/CA6,0) -> 0 | CD6: =SUMIFS([2]SB!Q:Q,[2]SB!B:B,N6,[2]SB!A:A,$P$2)+SUMIFS([2]SB!Q:Q,[2]SB!B:B,N6,[2]SB!A:A,$T$2) -> 0 | CE6: =SUMIFS([2]SB!O:O,[2]SB!B:B,N6,[2]SB!A:A,$P$2)+SUMIFS([2]SB!O:O,[2]SB!B:B,N6,[2]SB!A:A,$T$2) -> 0 | CF6: =IFERROR(CD6/CA6,0) -> 0 | CG6: =SUMIFS([2]SB!L:L,[2]SB!B:B,N6,[2]SB!A:A,$P$2)+SUMIFS([2]SB!L:L,[2]SB!B:B,N6,[2]SB!A:A,$T$2) -> 0 | CH6: =IFERROR(CG6/CE6,0) -> 0
A7: {=IFERROR(LOOKUP(1,0/(([2]业务报告!$A:$A=$N7)*([2]业务报告!$B:$B=$P$2)),[2]业务报告!AU:AU),"")} -> 0 | B7: {=IFERROR(LOOKUP(1,0/(([2]业务报告!$A:$A=$N7)*([2]业务报告!$B:$B=$P$2)),[2]业务报告!AV:AV),"")} -> 3.2.3级词词组，cpc提高到2.35 曝光点击偏少，1070曝光只有5次点击，继续提高cpc到2.45 | C7: =SUMIFS([2]业务报告!AC:AC,[2]业务报告!$A:$A,$N7,[2]业务报告!$B:$B,$P$2) -> 0 | D7: =SUMIFS([2]业务报告!AD:AD,[2]业务报告!$A:$A,$N7,[2]业务报告!$B:$B,$P$2) -> 0 | E7: {=_xlfn.XLOOKUP($N7&$P$2,[2]业务报告!$A:$A&[2]业务报告!$B:$B,[2]业务报告!AE:AE,"")} -> 0 | F7: {=IFERROR(LOOKUP(1,0/(([2]业务报告!$A:$A=$N7)*([2]业务报告!$B:$B=$P$2)),[2]业务报告!AK:AK),0)} -> WBD | G7: =SUMIFS([2]业务报告!AF:AF,[2]业务报告!$A:$A,$N7,[2]业务报告!$B:$B,$P$2) -> 319.89 | H7: {=IFERROR(LOOKUP(1,0/(([2]业务报告!$A:$A=$N7)*([2]业务报告!B:B=$P$2)),[2]业务报告!AG:AG),0)} -> / | I7: {=IFERROR(LOOKUP(1,0/(([2]业务报告!$A:$A=$N7)*([2]业务报告!$B:$B=$P$2)),[2]业务报告!AH:AH),0)} -> 79.99 | J7: =SUMIFS([2]WT报告!A:A,[2]WT报告!$C:$C,$N7,[2]WT报告!$H:$H,$X$2) -> 0 | K7: {=IFERROR(LOOKUP(1,0/(([2]业务报告!$A:$A=$N7)*([2]业务报告!$B:$B=$P$2)),[2]业务报告!AI:AI),0)} -> 0 | L7: {=IFERROR(LOOKUP(1,0/(([2]业务报告!$A:$A=$N7)*([2]业务报告!$B:$B=$P$2)),[2]业务报告!AJ:AJ),0)} -> 0 | M7: =IFERROR("周"&WEEKDAY(N7,2),"-") -> 周3 | N7: =DATE($O$1,$O$2,DAY(N6)+1) -> 45903 | O7: =SUMIFS([2]业务报告!G:G,[2]业务报告!$A:$A,$N7,[2]业务报告!$B:$B,$P$2)+SUMIFS([2]业务报告!G:G,[2]业务报告!$A:$A,$N7,[2]业务报告!$B:$B,$T$2) -> 0 | P7: =SUMIFS([2]业务报告!H:H,[2]业务报告!$A:$A,$N7,[2]业务报告!$B:$B,$P$2)+SUMIFS([2]业务报告!H:H,[2]业务报告!$A:$A,$N7,[2]业务报告!$B:$B,$T$2) -> 0 | Q7: =SUMIFS([2]业务报告!I:I,[2]业务报告!$A:$A,$N7,[2]业务报告!$B:$B,$P$2)+SUMIFS([2]业务报告!I:I,[2]业务报告!$A:$A,$N7,[2]业务报告!$B:$B,$T$2) -> 0 | R7: =SUMIFS([2]业务报告!T:T,[2]业务报告!$A:$A,$N7,[2]业务报告!$B:$B,$P$2)+SUMIFS([2]业务报告!T:T,[2]业务报告!$A:$A,$N7,[2]业务报告!$B:$B,$T$2) -> 0 | S7: =IFERROR((R7+V7)/Q7,0) -> 0 | T7: =SUMIFS([2]业务报告!X:X,[2]业务报告!$A:$A,$N7,[2]业务报告!$B:$B,$P$2)+SUMIFS([2]业务报告!X:X,[2]业务报告!$A:$A,$N7,[2]业务报告!$B:$B,$T$2) -> 0 | U7: =SUMIFS([2]业务报告!AO:AO,[2]业务报告!$A:$A,$N7,[2]业务报告!$B:$B,$P$2)+SUMIFS([2]业务报告!AP:AP,[2]业务报告!$A:$A,$N7,[2]业务报告!$B:$B,$P$2) -> 0 | V7: =SUMIFS([2]WT报告!I:I,[2]WT报告!$C:$C,$N7,[2]WT报告!$H:$H,$X$2) -> 0 | W7: =SUMIFS([2]WT报告!Z:Z,[2]WT报告!$C:$C,$N7,[2]WT报告!$H:$H,$X$2) -> 0 | X7: =SUMIFS([2]业务报告!AS:AS,[2]业务报告!$A:$A,$N7,[2]业务报告!$B:$B,$P$2)+SUMIFS([2]业务报告!AS:AS,[2]业务报告!$A:$A,$N7,[2]业务报告!$B:$B,$T$2)+V7 -> 0 | Y7: =SUMIFS([2]业务报告!AO:AO,[2]业务报告!$A:$A,$N7,[2]业务报告!$B:$B,$P$2)*SUMIFS([2]业务报告!AM:AM,[2]业务报告!$A:$A,$N7,[2]业务报告!$B:$B,$P$2)/$AC$2+SUMIFS([2]业务报告!AP:AP,[2]业务报告!$A:$A,$N7,[2]业务报告!$B:$B,$P$2)*SUMIFS([2]业务报告!AN:AN,[2]业务报告!$A:$A,$N7,[2]业务报告!$B:$B,$P$2)/$AC$2 -> 0 | Z7: =(I7*(1-$AD$2-4%-10%)-$AD$1-$AC$1/$AC$2)*BB7-BC7 -> 0 | AA7: =(I7*(1-$AD$2-4%-10%)-$AD$1-$AC$1/$AC$2)*(R7-IF(R7>V7,SUMIFS([2]业务报告!AO:AO,[2]业务报告!$A:$A,$N7,[2]业务报告!$B:$B,$P$2),0))-BC7 -> 0 | AB7: =IFERROR(AA7/(I7*R7),0) -> 0 | AC7: =AR7*(J7-$AC$1/$AC$2-J7*4%)-AS7 -> 0 | AD7: =(V7-IF(R7<V7,SUMIFS([2]业务报告!AO:AO,[2]业务报告!$A:$A,$N7,[2]业务报告!$B:$B,$P$2),0))*(J7-$AC$1/$AC$2-J7*4%)-AS7 -> 0 | AE7: {=IFERROR(LOOKUP(1,0/(([2]业务报告!$A:$A=$N7)*([2]业务报告!$B:$B=$P$2)),[2]业务报告!AQ:AQ),0)*$AH$2} -> 0 | AF7: {=IFERROR(LOOKUP(1,0/(([2]业务报告!$A:$A=$N7)*([2]业务报告!$B:$B=$P$2)),[2]业务报告!AR:AR),0)*$AG$2} -> 0 | AG7: =AA7+AD7+AE7+AF7-Y7 -> 0 | AH7: =IFERROR((AG7)/(T7+J7*V7),0) -> 0 | AI7: =IFERROR((AG7)/(X7),0) -> 0 | AJ7: =IFERROR(AS7/(V7*J7),0) -> 0 | AK7: =IFERROR(ROUNDUP(AS7/V7,1),0) -> 0 | AL7: =SUMIFS([2]WT报告!S:S,[2]WT报告!$C:$C,$N7,[2]WT报告!$H:$H,$X$2) -> 0 | AM7: =IFERROR((AR7)/AP7,0) -> 0 | AN7: =SUMIFS([2]WT报告!N:N,[2]WT报告!$C:$C,$N7,[2]WT报告!$H:$H,$X$2) -> 0 | AO7: =IFERROR(AR7/(V7),0) -> 0 | AP7: =SUMIFS([2]WT报告!P:P,[2]WT报告!$C:$C,$N7,[2]WT报告!$H:$H,$X$2) -> 0 | AQ7: =SUMIFS([2]WT报告!Q:Q,[2]WT报告!$C:$C,$N7,[2]WT报告!$H:$H,$X$2) -> 0 | AR7: =SUMIFS([2]WT报告!J:J,[2]WT报告!$C:$C,$N7,[2]WT报告!$H:$H,$X$2) -> 0 | AS7: =SUMIFS([2]WT报告!M:M,[2]WT报告!$C:$C,$N7,[2]WT报告!$H:$H,$X$2) -> 0 | AT7: =IFERROR((BO7+BX7+CG7)/(R7*I7),0) -> 0 | AU7: =IFERROR(ROUNDUP(BC7/R7,1),0) -> 0 | AV7: =IFERROR(ROUNDUP(BC7/BB7,1),0) -> 0 | AW7: =IFERROR((BB7)/AZ7,0) -> 0 | AX7: =IFERROR(BC7/AZ7,0) -> 0 | AY7: =IFERROR((BL7+BU7+CD7)/(R7+V7),0) -> 0 | AZ7: =BI7+BR7+CA7 -> 0 | BA7: =IFERROR((BI7+BR7+CA7)/(BH7+BQ7+BZ7),0) -> 0 | BB7: =BL7+BU7+CD7 -> 0 | BC7: =ROUND(BO7+BX7+CG7,2) -> 0 | BD7: =IFERROR(BC7/(BM7+BV7+CE7),0) -> 0 | BE7: =IFERROR(ROUNDUP((BO7+CG7)/BG7,1),0) -> 0 | BF7: =IFERROR(BG7/(BI7+CA7),0) -> 0 | BG7: =BL7+CD7 -> 0 | BH7: =SUMIFS([2]SP!J:J,[2]SP!A:A,N7,[2]SP!H:H,$P$2)+SUMIFS([2]SP!J:J,[2]SP!A:A,N7,[2]SP!H:H,$T$2) -> 0 | BI7: =SUMIFS([2]SP!K:K,[2]SP!A:A,N7,[2]SP!H:H,$P$2)+SUMIFS([2]SP!K:K,[2]SP!A:A,N7,[2]SP!H:H,$T$2) -> 0 | BJ7: =IFERROR(BI7/BH7,0) -> 0 | BK7: =IFERROR(BO7/BI7,0) -> 0 | BL7: =SUMIFS([2]SP!R:R,[2]SP!A:A,N7,[2]SP!H:H,$P$2)+SUMIFS([2]SP!R:R,[2]SP!A:A,N7,[2]SP!H:H,$T$2) -> 0 | BM7: =SUMIFS([2]SP!O:O,[2]SP!A:A,$N7,[2]SP!H:H,$P$2)+SUMIFS([2]SP!O:O,[2]SP!A:A,$N7,[2]SP!H:H,$T$2) -> 0 | BN7: =IFERROR(BL7/BI7,0) -> 0 | BO7: =SUMIFS([2]SP!N:N,[2]SP!A:A,N7,[2]SP!H:H,$P$2)+SUMIFS([2]SP!N:N,[2]SP!A:A,N7,[2]SP!H:H,$T$2) -> 0 | BP7: =IFERROR(BO7/BM7,0) -> 0 | BQ7: =SUMIFS([2]SD!J:J,[2]SD!A:A,N7,[2]SD!H:H,$P$2)+SUMIFS([2]SD!J:J,[2]SD!A:A,N7,[2]SD!H:H,$T$2) -> 0 | BR7: =SUMIFS([2]SD!L:L,[2]SD!A:A,N7,[2]SD!H:H,$P$2)+SUMIFS([2]SD!L:L,[2]SD!A:A,N7,[2]SD!H:H,$T$2) -> 0 | BS7: =IFERROR(BR7/BQ7,0) -> 0 | BT7: =IFERROR(BX7/BR7,0) -> 0 | BU7: =SUMIFS([2]SD!U:U,[2]SD!A:A,N7,[2]SD!H:H,$P$2)+SUMIFS([2]SD!U:U,[2]SD!A:A,N7,[2]SD!H:H,$T$2) -> 0 | BV7: =SUMIFS([2]SD!V:V,[2]SD!A:A,N7,[2]SD!H:H,$P$2)+SUMIFS([2]SD!V:V,[2]SD!A:A,N7,[2]SD!H:H,$T$2) -> 0 | BW7: =IFERROR(BU7/BR7,0) -> 0 | BX7: =SUMIFS([2]SD!O:O,[2]SD!A:A,N7,[2]SD!H:H,$P$2)+SUMIFS([2]SD!O:O,[2]SD!A:A,N7,[2]SD!H:H,$T$2) -> 0 | BY7: =IFERROR(BX7/BV7,0) -> 0 | BZ7: =SUMIFS([2]SB!H:H,[2]SB!B:B,N7,[2]SB!A:A,$P$2)+SUMIFS([2]SB!H:H,[2]SB!B:B,N7,[2]SB!A:A,$T$2) -> 0 | CA7: =SUMIFS([2]SB!I:I,[2]SB!B:B,N7,[2]SB!A:A,$P$2)+SUMIFS([2]SB!I:I,[2]SB!B:B,N7,[2]SB!A:A,$T$2) -> 0 | CB7: =IFERROR(CA7/BZ7,0) -> 0 | CC7: =IFERROR(CG7/CA7,0) -> 0 | CD7: =SUMIFS([2]SB!Q:Q,[2]SB!B:B,N7,[2]SB!A:A,$P$2)+SUMIFS([2]SB!Q:Q,[2]SB!B:B,N7,[2]SB!A:A,$T$2) -> 0 | CE7: =SUMIFS([2]SB!O:O,[2]SB!B:B,N7,[2]SB!A:A,$P$2)+SUMIFS([2]SB!O:O,[2]SB!B:B,N7,[2]SB!A:A,$T$2) -> 0 | CF7: =IFERROR(CD7/CA7,0) -> 0 | CG7: =SUMIFS([2]SB!L:L,[2]SB!B:B,N7,[2]SB!A:A,$P$2)+SUMIFS([2]SB!L:L,[2]SB!B:B,N7,[2]SB!A:A,$T$2) -> 0 | CH7: =IFERROR(CG7/CE7,0) -> 0
A8: {=IFERROR(LOOKUP(1,0/(([2]业务报告!$A:$A=$N8)*([2]业务报告!$B:$B=$P$2)),[2]业务报告!AU:AU),"")} -> 0 | B8: {=IFERROR(LOOKUP(1,0/(([2]业务报告!$A:$A=$N8)*([2]业务报告!$B:$B=$P$2)),[2]业务报告!AV:AV),"")} -> 4.2.3级词精准，cpc提高到2.5 ，曝光点击达到预期，无转化，主要预算花在 laser hair removal for women /ipl laser hair removal 各点击10次无转化，继续观察 | C8: =SUMIFS([2]业务报告!AC:AC,[2]业务报告!$A:$A,$N8,[2]业务报告!$B:$B,$P$2) -> 0 | D8: =SUMIFS([2]业务报告!AD:AD,[2]业务报告!$A:$A,$N8,[2]业务报告!$B:$B,$P$2) -> 0 | E8: {=_xlfn.XLOOKUP($N8&$P$2,[2]业务报告!$A:$A&[2]业务报告!$B:$B,[2]业务报告!AE:AE,"")} -> 0 | F8: {=IFERROR(LOOKUP(1,0/(([2]业务报告!$A:$A=$N8)*([2]业务报告!$B:$B=$P$2)),[2]业务报告!AK:AK),0)} -> WBD | G8: =SUMIFS([2]业务报告!AF:AF,[2]业务报告!$A:$A,$N8,[2]业务报告!$B:$B,$P$2) -> 319.89 | H8: {=IFERROR(LOOKUP(1,0/(([2]业务报告!$A:$A=$N8)*([2]业务报告!B:B=$P$2)),[2]业务报告!AG:AG),0)} -> / | I8: {=IFERROR(LOOKUP(1,0/(([2]业务报告!$A:$A=$N8)*([2]业务报告!$B:$B=$P$2)),[2]业务报告!AH:AH),0)} -> 79.99 | J8: =SUMIFS([2]WT报告!A:A,[2]WT报告!$C:$C,$N8,[2]WT报告!$H:$H,$X$2) -> 0 | K8: {=IFERROR(LOOKUP(1,0/(([2]业务报告!$A:$A=$N8)*([2]业务报告!$B:$B=$P$2)),[2]业务报告!AI:AI),0)} -> 0 | L8: {=IFERROR(LOOKUP(1,0/(([2]业务报告!$A:$A=$N8)*([2]业务报告!$B:$B=$P$2)),[2]业务报告!AJ:AJ),0)} -> 0 | M8: =IFERROR("周"&WEEKDAY(N8,2),"-") -> 周4 | N8: =DATE($O$1,$O$2,DAY(N7)+1) -> 45904 | O8: =SUMIFS([2]业务报告!G:G,[2]业务报告!$A:$A,$N8,[2]业务报告!$B:$B,$P$2)+SUMIFS([2]业务报告!G:G,[2]业务报告!$A:$A,$N8,[2]业务报告!$B:$B,$T$2) -> 0 | P8: =SUMIFS([2]业务报告!H:H,[2]业务报告!$A:$A,$N8,[2]业务报告!$B:$B,$P$2)+SUMIFS([2]业务报告!H:H,[2]业务报告!$A:$A,$N8,[2]业务报告!$B:$B,$T$2) -> 0 | Q8: =SUMIFS([2]业务报告!I:I,[2]业务报告!$A:$A,$N8,[2]业务报告!$B:$B,$P$2)+SUMIFS([2]业务报告!I:I,[2]业务报告!$A:$A,$N8,[2]业务报告!$B:$B,$T$2) -> 0 | R8: =SUMIFS([2]业务报告!T:T,[2]业务报告!$A:$A,$N8,[2]业务报告!$B:$B,$P$2)+SUMIFS([2]业务报告!T:T,[2]业务报告!$A:$A,$N8,[2]业务报告!$B:$B,$T$2) -> 0 | S8: =IFERROR((R8+V8)/Q8,0) -> 0 | T8: =SUMIFS([2]业务报告!X:X,[2]业务报告!$A:$A,$N8,[2]业务报告!$B:$B,$P$2)+SUMIFS([2]业务报告!X:X,[2]业务报告!$A:$A,$N8,[2]业务报告!$B:$B,$T$2) -> 0 | U8: =SUMIFS([2]业务报告!AO:AO,[2]业务报告!$A:$A,$N8,[2]业务报告!$B:$B,$P$2)+SUMIFS([2]业务报告!AP:AP,[2]业务报告!$A:$A,$N8,[2]业务报告!$B:$B,$P$2) -> 0 | V8: =SUMIFS([2]WT报告!I:I,[2]WT报告!$C:$C,$N8,[2]WT报告!$H:$H,$X$2) -> 0 | W8: =SUMIFS([2]WT报告!Z:Z,[2]WT报告!$C:$C,$N8,[2]WT报告!$H:$H,$X$2) -> 0 | X8: =SUMIFS([2]业务报告!AS:AS,[2]业务报告!$A:$A,$N8,[2]业务报告!$B:$B,$P$2)+SUMIFS([2]业务报告!AS:AS,[2]业务报告!$A:$A,$N8,[2]业务报告!$B:$B,$T$2)+V8 -> 0 | Y8: =SUMIFS([2]业务报告!AO:AO,[2]业务报告!$A:$A,$N8,[2]业务报告!$B:$B,$P$2)*SUMIFS([2]业务报告!AM:AM,[2]业务报告!$A:$A,$N8,[2]业务报告!$B:$B,$P$2)/$AC$2+SUMIFS([2]业务报告!AP:AP,[2]业务报告!$A:$A,$N8,[2]业务报告!$B:$B,$P$2)*SUMIFS([2]业务报告!AN:AN,[2]业务报告!$A:$A,$N8,[2]业务报告!$B:$B,$P$2)/$AC$2 -> 0 | Z8: =(I8*(1-$AD$2-4%-10%)-$AD$1-$AC$1/$AC$2)*BB8-BC8 -> 0 | AA8: =(I8*(1-$AD$2-4%-10%)-$AD$1-$AC$1/$AC$2)*(R8-IF(R8>V8,SUMIFS([2]业务报告!AO:AO,[2]业务报告!$A:$A,$N8,[2]业务报告!$B:$B,$P$2),0))-BC8 -> 0 | AB8: =IFERROR(AA8/(I8*R8),0) -> 0 | AC8: =AR8*(J8-$AC$1/$AC$2-J8*4%)-AS8 -> 0 | AD8: =(V8-IF(R8<V8,SUMIFS([2]业务报告!AO:AO,[2]业务报告!$A:$A,$N8,[2]业务报告!$B:$B,$P$2),0))*(J8-$AC$1/$AC$2-J8*4%)-AS8 -> 0 | AE8: {=IFERROR(LOOKUP(1,0/(([2]业务报告!$A:$A=$N8)*([2]业务报告!$B:$B=$P$2)),[2]业务报告!AQ:AQ),0)*$AH$2} -> 0 | AF8: {=IFERROR(LOOKUP(1,0/(([2]业务报告!$A:$A=$N8)*([2]业务报告!$B:$B=$P$2)),[2]业务报告!AR:AR),0)*$AG$2} -> 0 | AG8: =AA8+AD8+AE8+AF8-Y8 -> 0 | AH8: =IFERROR((AG8)/(T8+J8*V8),0) -> 0 | AI8: =IFERROR((AG8)/(X8),0) -> 0 | AJ8: =IFERROR(AS8/(V8*J8),0) -> 0 | AK8: =IFERROR(ROUNDUP(AS8/V8,1),0) -> 0 | AL8: =SUMIFS([2]WT报告!S:S,[2]WT报告!$C:$C,$N8,[2]WT报告!$H:$H,$X$2) -> 0 | AM8: =IFERROR((AR8)/AP8,0) -> 0 | AN8: =SUMIFS([2]WT报告!N:N,[2]WT报告!$C:$C,$N8,[2]WT报告!$H:$H,$X$2) -> 0 | AO8: =IFERROR(AR8/(V8),0) -> 0 | AP8: =SUMIFS([2]WT报告!P:P,[2]WT报告!$C:$C,$N8,[2]WT报告!$H:$H,$X$2) -> 0 | AQ8: =SUMIFS([2]WT报告!Q:Q,[2]WT报告!$C:$C,$N8,[2]WT报告!$H:$H,$X$2) -> 0 | AR8: =SUMIFS([2]WT报告!J:J,[2]WT报告!$C:$C,$N8,[2]WT报告!$H:$H,$X$2) -> 0 | AS8: =SUMIFS([2]WT报告!M:M,[2]WT报告!$C:$C,$N8,[2]WT报告!$H:$H,$X$2) -> 0 | AT8: =IFERROR((BO8+BX8+CG8)/(R8*I8),0) -> 0 | AU8: =IFERROR(ROUNDUP(BC8/R8,1),0) -> 0 | AV8: =IFERROR(ROUNDUP(BC8/BB8,1),0) -> 0 | AW8: =IFERROR((BB8)/AZ8,0) -> 0 | AX8: =IFERROR(BC8/AZ8,0) -> 0 | AY8: =IFERROR((BL8+BU8+CD8)/(R8+V8),0) -> 0 | AZ8: =BI8+BR8+CA8 -> 0 | BA8: =IFERROR((BI8+BR8+CA8)/(BH8+BQ8+BZ8),0) -> 0 | BB8: =BL8+BU8+CD8 -> 0 | BC8: =ROUND(BO8+BX8+CG8,2) -> 0 | BD8: =IFERROR(BC8/(BM8+BV8+CE8),0) -> 0 | BE8: =IFERROR(ROUNDUP((BO8+CG8)/BG8,1),0) -> 0 | BF8: =IFERROR(BG8/(BI8+CA8),0) -> 0 | BG8: =BL8+CD8 -> 0 | BH8: =SUMIFS([2]SP!J:J,[2]SP!A:A,N8,[2]SP!H:H,$P$2)+SUMIFS([2]SP!J:J,[2]SP!A:A,N8,[2]SP!H:H,$T$2) -> 0 | BI8: =SUMIFS([2]SP!K:K,[2]SP!A:A,N8,[2]SP!H:H,$P$2)+SUMIFS([2]SP!K:K,[2]SP!A:A,N8,[2]SP!H:H,$T$2) -> 0 | BJ8: =IFERROR(BI8/BH8,0) -> 0 | BK8: =IFERROR(BO8/BI8,0) -> 0 | BL8: =SUMIFS([2]SP!R:R,[2]SP!A:A,N8,[2]SP!H:H,$P$2)+SUMIFS([2]SP!R:R,[2]SP!A:A,N8,[2]SP!H:H,$T$2) -> 0 | BM8: =SUMIFS([2]SP!O:O,[2]SP!A:A,$N8,[2]SP!H:H,$P$2)+SUMIFS([2]SP!O:O,[2]SP!A:A,$N8,[2]SP!H:H,$T$2) -> 0 | BN8: =IFERROR(BL8/BI8,0) -> 0 | BO8: =SUMIFS([2]SP!N:N,[2]SP!A:A,N8,[2]SP!H:H,$P$2)+SUMIFS([2]SP!N:N,[2]SP!A:A,N8,[2]SP!H:H,$T$2) -> 0 | BP8: =IFERROR(BO8/BM8,0) -> 0 | BQ8: =SUMIFS([2]SD!J:J,[2]SD!A:A,N8,[2]SD!H:H,$P$2)+SUMIFS([2]SD!J:J,[2]SD!A:A,N8,[2]SD!H:H,$T$2) -> 0 | BR8: =SUMIFS([2]SD!L:L,[2]SD!A:A,N8,[2]SD!H:H,$P$2)+SUMIFS([2]SD!L:L,[2]SD!A:A,N8,[2]SD!H:H,$T$2) -> 0 | BS8: =IFERROR(BR8/BQ8,0) -> 0 | BT8: =IFERROR(BX8/BR8,0) -> 0 | BU8: =SUMIFS([2]SD!U:U,[2]SD!A:A,N8,[2]SD!H:H,$P$2)+SUMIFS([2]SD!U:U,[2]SD!A:A,N8,[2]SD!H:H,$T$2) -> 0 | BV8: =SUMIFS([2]SD!V:V,[2]SD!A:A,N8,[2]SD!H:H,$P$2)+SUMIFS([2]SD!V:V,[2]SD!A:A,N8,[2]SD!H:H,$T$2) -> 0 | BW8: =IFERROR(BU8/BR8,0) -> 0 | BX8: =SUMIFS([2]SD!O:O,[2]SD!A:A,N8,[2]SD!H:H,$P$2)+SUMIFS([2]SD!O:O,[2]SD!A:A,N8,[2]SD!H:H,$T$2) -> 0 | BY8: =IFERROR(BX8/BV8,0) -> 0 | BZ8: =SUMIFS([2]SB!H:H,[2]SB!B:B,N8,[2]SB!A:A,$P$2)+SUMIFS([2]SB!H:H,[2]SB!B:B,N8,[2]SB!A:A,$T$2) -> 0 | CA8: =SUMIFS([2]SB!I:I,[2]SB!B:B,N8,[2]SB!A:A,$P$2)+SUMIFS([2]SB!I:I,[2]SB!B:B,N8,[2]SB!A:A,$T$2) -> 0 | CB8: =IFERROR(CA8/BZ8,0) -> 0 | CC8: =IFERROR(CG8/CA8,0) -> 0 | CD8: =SUMIFS([2]SB!Q:Q,[2]SB!B:B,N8,[2]SB!A:A,$P$2)+SUMIFS([2]SB!Q:Q,[2]SB!B:B,N8,[2]SB!A:A,$T$2) -> 0 | CE8: =SUMIFS([2]SB!O:O,[2]SB!B:B,N8,[2]SB!A:A,$P$2)+SUMIFS([2]SB!O:O,[2]SB!B:B,N8,[2]SB!A:A,$T$2) -> 0 | CF8: =IFERROR(CD8/CA8,0) -> 0 | CG8: =SUMIFS([2]SB!L:L,[2]SB!B:B,N8,[2]SB!A:A,$P$2)+SUMIFS([2]SB!L:L,[2]SB!B:B,N8,[2]SB!A:A,$T$2) -> 0 | CH8: =IFERROR(CG8/CE8,0) -> 0
A9: {=IFERROR(LOOKUP(1,0/(([2]业务报告!$A:$A=$N9)*([2]业务报告!$B:$B=$P$2)),[2]业务报告!AU:AU),"")} -> 0 | B9: {=IFERROR(LOOKUP(1,0/(([2]业务报告!$A:$A=$N9)*([2]业务报告!$B:$B=$P$2)),[2]业务报告!AV:AV),"")} -> 5.长尾词精准提高竞价到 2美金，只有3次点击，今晚继续提高cpc到2.3 | C9: =SUMIFS([2]业务报告!AC:AC,[2]业务报告!$A:$A,$N9,[2]业务报告!$B:$B,$P$2) -> 0 | D9: =SUMIFS([2]业务报告!AD:AD,[2]业务报告!$A:$A,$N9,[2]业务报告!$B:$B,$P$2) -> 0 | E9: {=_xlfn.XLOOKUP($N9&$P$2,[2]业务报告!$A:$A&[2]业务报告!$B:$B,[2]业务报告!AE:AE,"")} -> 0 | F9: {=IFERROR(LOOKUP(1,0/(([2]业务报告!$A:$A=$N9)*([2]业务报告!$B:$B=$P$2)),[2]业务报告!AK:AK),0)} -> WBD | G9: =SUMIFS([2]业务报告!AF:AF,[2]业务报告!$A:$A,$N9,[2]业务报告!$B:$B,$P$2) -> 319.89 | H9: {=IFERROR(LOOKUP(1,0/(([2]业务报告!$A:$A=$N9)*([2]业务报告!B:B=$P$2)),[2]业务报告!AG:AG),0)} -> / | I9: {=IFERROR(LOOKUP(1,0/(([2]业务报告!$A:$A=$N9)*([2]业务报告!$B:$B=$P$2)),[2]业务报告!AH:AH),0)} -> 79.99 | J9: =SUMIFS([2]WT报告!A:A,[2]WT报告!$C:$C,$N9,[2]WT报告!$H:$H,$X$2) -> 0 | K9: {=IFERROR(LOOKUP(1,0/(([2]业务报告!$A:$A=$N9)*([2]业务报告!$B:$B=$P$2)),[2]业务报告!AI:AI),0)} -> 0 | L9: {=IFERROR(LOOKUP(1,0/(([2]业务报告!$A:$A=$N9)*([2]业务报告!$B:$B=$P$2)),[2]业务报告!AJ:AJ),0)} -> 0 | M9: =IFERROR("周"&WEEKDAY(N9,2),"-") -> 周5 | N9: =DATE($O$1,$O$2,DAY(N8)+1) -> 45905 | O9: =SUMIFS([2]业务报告!G:G,[2]业务报告!$A:$A,$N9,[2]业务报告!$B:$B,$P$2)+SUMIFS([2]业务报告!G:G,[2]业务报告!$A:$A,$N9,[2]业务报告!$B:$B,$T$2) -> 0 | P9: =SUMIFS([2]业务报告!H:H,[2]业务报告!$A:$A,$N9,[2]业务报告!$B:$B,$P$2)+SUMIFS([2]业务报告!H:H,[2]业务报告!$A:$A,$N9,[2]业务报告!$B:$B,$T$2) -> 0 | Q9: =SUMIFS([2]业务报告!I:I,[2]业务报告!$A:$A,$N9,[2]业务报告!$B:$B,$P$2)+SUMIFS([2]业务报告!I:I,[2]业务报告!$A:$A,$N9,[2]业务报告!$B:$B,$T$2) -> 0 | R9: =SUMIFS([2]业务报告!T:T,[2]业务报告!$A:$A,$N9,[2]业务报告!$B:$B,$P$2)+SUMIFS([2]业务报告!T:T,[2]业务报告!$A:$A,$N9,[2]业务报告!$B:$B,$T$2) -> 0 | S9: =IFERROR((R9+V9)/Q9,0) -> 0 | T9: =SUMIFS([2]业务报告!X:X,[2]业务报告!$A:$A,$N9,[2]业务报告!$B:$B,$P$2)+SUMIFS([2]业务报告!X:X,[2]业务报告!$A:$A,$N9,[2]业务报告!$B:$B,$T$2) -> 0 | U9: =SUMIFS([2]业务报告!AO:AO,[2]业务报告!$A:$A,$N9,[2]业务报告!$B:$B,$P$2)+SUMIFS([2]业务报告!AP:AP,[2]业务报告!$A:$A,$N9,[2]业务报告!$B:$B,$P$2) -> 0 | V9: =SUMIFS([2]WT报告!I:I,[2]WT报告!$C:$C,$N9,[2]WT报告!$H:$H,$X$2) -> 0 | W9: =SUMIFS([2]WT报告!Z:Z,[2]WT报告!$C:$C,$N9,[2]WT报告!$H:$H,$X$2) -> 0 | X9: =SUMIFS([2]业务报告!AS:AS,[2]业务报告!$A:$A,$N9,[2]业务报告!$B:$B,$P$2)+SUMIFS([2]业务报告!AS:AS,[2]业务报告!$A:$A,$N9,[2]业务报告!$B:$B,$T$2)+V9 -> 0 | Y9: =SUMIFS([2]业务报告!AO:AO,[2]业务报告!$A:$A,$N9,[2]业务报告!$B:$B,$P$2)*SUMIFS([2]业务报告!AM:AM,[2]业务报告!$A:$A,$N9,[2]业务报告!$B:$B,$P$2)/$AC$2+SUMIFS([2]业务报告!AP:AP,[2]业务报告!$A:$A,$N9,[2]业务报告!$B:$B,$P$2)*SUMIFS([2]业务报告!AN:AN,[2]业务报告!$A:$A,$N9,[2]业务报告!$B:$B,$P$2)/$AC$2 -> 0 | Z9: =(I9*(1-$AD$2-4%-10%)-$AD$1-$AC$1/$AC$2)*BB9-BC9 -> 0 | AA9: =(I9*(1-$AD$2-4%-10%)-$AD$1-$AC$1/$AC$2)*(R9-IF(R9>V9,SUMIFS([2]业务报告!AO:AO,[2]业务报告!$A:$A,$N9,[2]业务报告!$B:$B,$P$2),0))-BC9 -> 0 | AB9: =IFERROR(AA9/(I9*R9),0) -> 0 | AC9: =AR9*(J9-$AC$1/$AC$2-J9*4%)-AS9 -> 0 | AD9: =(V9-IF(R9<V9,SUMIFS([2]业务报告!AO:AO,[2]业务报告!$A:$A,$N9,[2]业务报告!$B:$B,$P$2),0))*(J9-$AC$1/$AC$2-J9*4%)-AS9 -> 0 | AE9: {=IFERROR(LOOKUP(1,0/(([2]业务报告!$A:$A=$N9)*([2]业务报告!$B:$B=$P$2)),[2]业务报告!AQ:AQ),0)*$AH$2} -> 0 | AF9: {=IFERROR(LOOKUP(1,0/(([2]业务报告!$A:$A=$N9)*([2]业务报告!$B:$B=$P$2)),[2]业务报告!AR:AR),0)*$AG$2} -> 0 | AG9: =AA9+AD9+AE9+AF9-Y9 -> 0 | AH9: =IFERROR((AG9)/(T9+J9*V9),0) -> 0 | AI9: =IFERROR((AG9)/(X9),0) -> 0 | AJ9: =IFERROR(AS9/(V9*J9),0) -> 0 | AK9: =IFERROR(ROUNDUP(AS9/V9,1),0) -> 0 | AL9: =SUMIFS([2]WT报告!S:S,[2]WT报告!$C:$C,$N9,[2]WT报告!$H:$H,$X$2) -> 0 | AM9: =IFERROR((AR9)/AP9,0) -> 0 | AN9: =SUMIFS([2]WT报告!N:N,[2]WT报告!$C:$C,$N9,[2]WT报告!$H:$H,$X$2) -> 0 | AO9: =IFERROR(AR9/(V9),0) -> 0 | AP9: =SUMIFS([2]WT报告!P:P,[2]WT报告!$C:$C,$N9,[2]WT报告!$H:$H,$X$2) -> 0 | AQ9: =SUMIFS([2]WT报告!Q:Q,[2]WT报告!$C:$C,$N9,[2]WT报告!$H:$H,$X$2) -> 0 | AR9: =SUMIFS([2]WT报告!J:J,[2]WT报告!$C:$C,$N9,[2]WT报告!$H:$H,$X$2) -> 0 | AS9: =SUMIFS([2]WT报告!M:M,[2]WT报告!$C:$C,$N9,[2]WT报告!$H:$H,$X$2) -> 0 | AT9: =IFERROR((BO9+BX9+CG9)/(R9*I9),0) -> 0 | AU9: =IFERROR(ROUNDUP(BC9/R9,1),0) -> 0 | AV9: =IFERROR(ROUNDUP(BC9/BB9,1),0) -> 0 | AW9: =IFERROR((BB9)/AZ9,0) -> 0 | AX9: =IFERROR(BC9/AZ9,0) -> 0 | AY9: =IFERROR((BL9+BU9+CD9)/(R9+V9),0) -> 0 | AZ9: =BI9+BR9+CA9 -> 0 | BA9: =IFERROR((BI9+BR9+CA9)/(BH9+BQ9+BZ9),0) -> 0 | BB9: =BL9+BU9+CD9 -> 0 | BC9: =ROUND(BO9+BX9+CG9,2) -> 0 | BD9: =IFERROR(BC9/(BM9+BV9+CE9),0) -> 0 | BE9: =IFERROR(ROUNDUP((BO9+CG9)/BG9,1),0) -> 0 | BF9: =IFERROR(BG9/(BI9+CA9),0) -> 0 | BG9: =BL9+CD9 -> 0 | BH9: =SUMIFS([2]SP!J:J,[2]SP!A:A,N9,[2]SP!H:H,$P$2)+SUMIFS([2]SP!J:J,[2]SP!A:A,N9,[2]SP!H:H,$T$2) -> 0 | BI9: =SUMIFS([2]SP!K:K,[2]SP!A:A,N9,[2]SP!H:H,$P$2)+SUMIFS([2]SP!K:K,[2]SP!A:A,N9,[2]SP!H:H,$T$2) -> 0 | BJ9: =IFERROR(BI9/BH9,0) -> 0 | BK9: =IFERROR(BO9/BI9,0) -> 0 | BL9: =SUMIFS([2]SP!R:R,[2]SP!A:A,N9,[2]SP!H:H,$P$2)+SUMIFS([2]SP!R:R,[2]SP!A:A,N9,[2]SP!H:H,$T$2) -> 0 | BM9: =SUMIFS([2]SP!O:O,[2]SP!A:A,$N9,[2]SP!H:H,$P$2)+SUMIFS([2]SP!O:O,[2]SP!A:A,$N9,[2]SP!H:H,$T$2) -> 0 | BN9: =IFERROR(BL9/BI9,0) -> 0 | BO9: =SUMIFS([2]SP!N:N,[2]SP!A:A,N9,[2]SP!H:H,$P$2)+SUMIFS([2]SP!N:N,[2]SP!A:A,N9,[2]SP!H:H,$T$2) -> 0 | BP9: =IFERROR(BO9/BM9,0) -> 0 | BQ9: =SUMIFS([2]SD!J:J,[2]SD!A:A,N9,[2]SD!H:H,$P$2)+SUMIFS([2]SD!J:J,[2]SD!A:A,N9,[2]SD!H:H,$T$2) -> 0 | BR9: =SUMIFS([2]SD!L:L,[2]SD!A:A,N9,[2]SD!H:H,$P$2)+SUMIFS([2]SD!L:L,[2]SD!A:A,N9,[2]SD!H:H,$T$2) -> 0 | BS9: =IFERROR(BR9/BQ9,0) -> 0 | BT9: =IFERROR(BX9/BR9,0) -> 0 | BU9: =SUMIFS([2]SD!U:U,[2]SD!A:A,N9,[2]SD!H:H,$P$2)+SUMIFS([2]SD!U:U,[2]SD!A:A,N9,[2]SD!H:H,$T$2) -> 0 | BV9: =SUMIFS([2]SD!V:V,[2]SD!A:A,N9,[2]SD!H:H,$P$2)+SUMIFS([2]SD!V:V,[2]SD!A:A,N9,[2]SD!H:H,$T$2) -> 0 | BW9: =IFERROR(BU9/BR9,0) -> 0 | BX9: =SUMIFS([2]SD!O:O,[2]SD!A:A,N9,[2]SD!H:H,$P$2)+SUMIFS([2]SD!O:O,[2]SD!A:A,N9,[2]SD!H:H,$T$2) -> 0 | BY9: =IFERROR(BX9/BV9,0) -> 0 | BZ9: =SUMIFS([2]SB!H:H,[2]SB!B:B,N9,[2]SB!A:A,$P$2)+SUMIFS([2]SB!H:H,[2]SB!B:B,N9,[2]SB!A:A,$T$2) -> 0 | CA9: =SUMIFS([2]SB!I:I,[2]SB!B:B,N9,[2]SB!A:A,$P$2)+SUMIFS([2]SB!I:I,[2]SB!B:B,N9,[2]SB!A:A,$T$2) -> 0 | CB9: =IFERROR(CA9/BZ9,0) -> 0 | CC9: =IFERROR(CG9/CA9,0) -> 0 | CD9: =SUMIFS([2]SB!Q:Q,[2]SB!B:B,N9,[2]SB!A:A,$P$2)+SUMIFS([2]SB!Q:Q,[2]SB!B:B,N9,[2]SB!A:A,$T$2) -> 0 | CE9: =SUMIFS([2]SB!O:O,[2]SB!B:B,N9,[2]SB!A:A,$P$2)+SUMIFS([2]SB!O:O,[2]SB!B:B,N9,[2]SB!A:A,$T$2) -> 0 | CF9: =IFERROR(CD9/CA9,0) -> 0 | CG9: =SUMIFS([2]SB!L:L,[2]SB!B:B,N9,[2]SB!A:A,$P$2)+SUMIFS([2]SB!L:L,[2]SB!B:B,N9,[2]SB!A:A,$T$2) -> 0 | CH9: =IFERROR(CG9/CE9,0) -> 0
A10: {=IFERROR(LOOKUP(1,0/(([2]业务报告!$A:$A=$N10)*([2]业务报告!$B:$B=$P$2)),[2]业务报告!AU:AU),"")} -> 0 | B10: {=IFERROR(LOOKUP(1,0/(([2]业务报告!$A:$A=$N10)*([2]业务报告!$B:$B=$P$2)),[2]业务报告!AV:AV),"")} -> 6.长尾词词组 cpc提高到2.35 曝光点击没达到预期，今晚继续提高cpc到2.45 | C10: =SUMIFS([2]业务报告!AC:AC,[2]业务报告!$A:$A,$N10,[2]业务报告!$B:$B,$P$2) -> 0 | D10: =SUMIFS([2]业务报告!AD:AD,[2]业务报告!$A:$A,$N10,[2]业务报告!$B:$B,$P$2) -> 0 | E10: {=_xlfn.XLOOKUP($N10&$P$2,[2]业务报告!$A:$A&[2]业务报告!$B:$B,[2]业务报告!AE:AE,"")} -> 0 | F10: {=IFERROR(LOOKUP(1,0/(([2]业务报告!$A:$A=$N10)*([2]业务报告!$B:$B=$P$2)),[2]业务报告!AK:AK),0)} -> WBD | G10: =SUMIFS([2]业务报告!AF:AF,[2]业务报告!$A:$A,$N10,[2]业务报告!$B:$B,$P$2) -> 319.89 | H10: {=IFERROR(LOOKUP(1,0/(([2]业务报告!$A:$A=$N10)*([2]业务报告!B:B=$P$2)),[2]业务报告!AG:AG),0)} -> / | I10: {=IFERROR(LOOKUP(1,0/(([2]业务报告!$A:$A=$N10)*([2]业务报告!$B:$B=$P$2)),[2]业务报告!AH:AH),0)} -> 79.99 | J10: =SUMIFS([2]WT报告!A:A,[2]WT报告!$C:$C,$N10,[2]WT报告!$H:$H,$X$2) -> 0 | K10: {=IFERROR(LOOKUP(1,0/(([2]业务报告!$A:$A=$N10)*([2]业务报告!$B:$B=$P$2)),[2]业务报告!AI:AI),0)} -> 0 | L10: {=IFERROR(LOOKUP(1,0/(([2]业务报告!$A:$A=$N10)*([2]业务报告!$B:$B=$P$2)),[2]业务报告!AJ:AJ),0)} -> 0 | M10: =IFERROR("周"&WEEKDAY(N10,2),"-") -> 周6 | N10: =DATE($O$1,$O$2,DAY(N9)+1) -> 45906 | O10: =SUMIFS([2]业务报告!G:G,[2]业务报告!$A:$A,$N10,[2]业务报告!$B:$B,$P$2)+SUMIFS([2]业务报告!G:G,[2]业务报告!$A:$A,$N10,[2]业务报告!$B:$B,$T$2) -> 0 | P10: =SUMIFS([2]业务报告!H:H,[2]业务报告!$A:$A,$N10,[2]业务报告!$B:$B,$P$2)+SUMIFS([2]业务报告!H:H,[2]业务报告!$A:$A,$N10,[2]业务报告!$B:$B,$T$2) -> 0 | Q10: =SUMIFS([2]业务报告!I:I,[2]业务报告!$A:$A,$N10,[2]业务报告!$B:$B,$P$2)+SUMIFS([2]业务报告!I:I,[2]业务报告!$A:$A,$N10,[2]业务报告!$B:$B,$T$2) -> 0 | R10: =SUMIFS([2]业务报告!T:T,[2]业务报告!$A:$A,$N10,[2]业务报告!$B:$B,$P$2)+SUMIFS([2]业务报告!T:T,[2]业务报告!$A:$A,$N10,[2]业务报告!$B:$B,$T$2) -> 0 | S10: =IFERROR((R10+V10)/Q10,0) -> 0 | T10: =SUMIFS([2]业务报告!X:X,[2]业务报告!$A:$A,$N10,[2]业务报告!$B:$B,$P$2)+SUMIFS([2]业务报告!X:X,[2]业务报告!$A:$A,$N10,[2]业务报告!$B:$B,$T$2) -> 0 | U10: =SUMIFS([2]业务报告!AO:AO,[2]业务报告!$A:$A,$N10,[2]业务报告!$B:$B,$P$2)+SUMIFS([2]业务报告!AP:AP,[2]业务报告!$A:$A,$N10,[2]业务报告!$B:$B,$P$2) -> 0 | V10: =SUMIFS([2]WT报告!I:I,[2]WT报告!$C:$C,$N10,[2]WT报告!$H:$H,$X$2) -> 0 | W10: =SUMIFS([2]WT报告!Z:Z,[2]WT报告!$C:$C,$N10,[2]WT报告!$H:$H,$X$2) -> 0 | X10: =SUMIFS([2]业务报告!AS:AS,[2]业务报告!$A:$A,$N10,[2]业务报告!$B:$B,$P$2)+SUMIFS([2]业务报告!AS:AS,[2]业务报告!$A:$A,$N10,[2]业务报告!$B:$B,$T$2)+V10 -> 0 | Y10: =SUMIFS([2]业务报告!AO:AO,[2]业务报告!$A:$A,$N10,[2]业务报告!$B:$B,$P$2)*SUMIFS([2]业务报告!AM:AM,[2]业务报告!$A:$A,$N10,[2]业务报告!$B:$B,$P$2)/$AC$2+SUMIFS([2]业务报告!AP:AP,[2]业务报告!$A:$A,$N10,[2]业务报告!$B:$B,$P$2)*SUMIFS([2]业务报告!AN:AN,[2]业务报告!$A:$A,$N10,[2]业务报告!$B:$B,$P$2)/$AC$2 -> 0 | Z10: =(I10*(1-$AD$2-4%-10%)-$AD$1-$AC$1/$AC$2)*BB10-BC10 -> 0 | AA10: =(I10*(1-$AD$2-4%-10%)-$AD$1-$AC$1/$AC$2)*(R10-IF(R10>V10,SUMIFS([2]业务报告!AO:AO,[2]业务报告!$A:$A,$N10,[2]业务报告!$B:$B,$P$2),0))-BC10 -> 0 | AB10: =IFERROR(AA10/(I10*R10),0) -> 0 | AC10: =AR10*(J10-$AC$1/$AC$2-J10*4%)-AS10 -> 0 | AD10: =(V10-IF(R10<V10,SUMIFS([2]业务报告!AO:AO,[2]业务报告!$A:$A,$N10,[2]业务报告!$B:$B,$P$2),0))*(J10-$AC$1/$AC$2-J10*4%)-AS10 -> 0 | AE10: {=IFERROR(LOOKUP(1,0/(([2]业务报告!$A:$A=$N10)*([2]业务报告!$B:$B=$P$2)),[2]业务报告!AQ:AQ),0)*$AH$2} -> 0 | AF10: {=IFERROR(LOOKUP(1,0/(([2]业务报告!$A:$A=$N10)*([2]业务报告!$B:$B=$P$2)),[2]业务报告!AR:AR),0)*$AG$2} -> 0 | AG10: =AA10+AD10+AE10+AF10-Y10 -> 0 | AH10: =IFERROR((AG10)/(T10+J10*V10),0) -> 0 | AI10: =IFERROR((AG10)/(X10),0) -> 0 | AJ10: =IFERROR(AS10/(V10*J10),0) -> 0 | AK10: =IFERROR(ROUNDUP(AS10/V10,1),0) -> 0 | AL10: =SUMIFS([2]WT报告!S:S,[2]WT报告!$C:$C,$N10,[2]WT报告!$H:$H,$X$2) -> 0 | AM10: =IFERROR((AR10)/AP10,0) -> 0 | AN10: =SUMIFS([2]WT报告!N:N,[2]WT报告!$C:$C,$N10,[2]WT报告!$H:$H,$X$2) -> 0 | AO10: =IFERROR(AR10/(V10),0) -> 0 | AP10: =SUMIFS([2]WT报告!P:P,[2]WT报告!$C:$C,$N10,[2]WT报告!$H:$H,$X$2) -> 0 | AQ10: =SUMIFS([2]WT报告!Q:Q,[2]WT报告!$C:$C,$N10,[2]WT报告!$H:$H,$X$2) -> 0 | AR10: =SUMIFS([2]WT报告!J:J,[2]WT报告!$C:$C,$N10,[2]WT报告!$H:$H,$X$2) -> 0 | AS10: =SUMIFS([2]WT报告!M:M,[2]WT报告!$C:$C,$N10,[2]WT报告!$H:$H,$X$2) -> 0 | AT10: =IFERROR((BO10+BX10+CG10)/(R10*I10),0) -> 0 | AU10: =IFERROR(ROUNDUP(BC10/R10,1),0) -> 0 | AV10: =IFERROR(ROUNDUP(BC10/BB10,1),0) -> 0 | AW10: =IFERROR((BB10)/AZ10,0) -> 0 | AX10: =IFERROR(BC10/AZ10,0) -> 0 | AY10: =IFERROR((BL10+BU10+CD10)/(R10+V10),0) -> 0 | AZ10: =BI10+BR10+CA10 -> 0 | BA10: =IFERROR((BI10+BR10+CA10)/(BH10+BQ10+BZ10),0) -> 0 | BB10: =BL10+BU10+CD10 -> 0 | BC10: =ROUND(BO10+BX10+CG10,2) -> 0 | BD10: =IFERROR(BC10/(BM10+BV10+CE10),0) -> 0 | BE10: =IFERROR(ROUNDUP((BO10+CG10)/BG10,1),0) -> 0 | BF10: =IFERROR(BG10/(BI10+CA10),0) -> 0 | BG10: =BL10+CD10 -> 0 | BH10: =SUMIFS([2]SP!J:J,[2]SP!A:A,N10,[2]SP!H:H,$P$2)+SUMIFS([2]SP!J:J,[2]SP!A:A,N10,[2]SP!H:H,$T$2) -> 0 | BI10: =SUMIFS([2]SP!K:K,[2]SP!A:A,N10,[2]SP!H:H,$P$2)+SUMIFS([2]SP!K:K,[2]SP!A:A,N10,[2]SP!H:H,$T$2) -> 0 | BJ10: =IFERROR(BI10/BH10,0) -> 0 | BK10: =IFERROR(BO10/BI10,0) -> 0 | BL10: =SUMIFS([2]SP!R:R,[2]SP!A:A,N10,[2]SP!H:H,$P$2)+SUMIFS([2]SP!R:R,[2]SP!A:A,N10,[2]SP!H:H,$T$2) -> 0 | BM10: =SUMIFS([2]SP!O:O,[2]SP!A:A,$N10,[2]SP!H:H,$P$2)+SUMIFS([2]SP!O:O,[2]SP!A:A,$N10,[2]SP!H:H,$T$2) -> 0 | BN10: =IFERROR(BL10/BI10,0) -> 0 | BO10: =SUMIFS([2]SP!N:N,[2]SP!A:A,N10,[2]SP!H:H,$P$2)+SUMIFS([2]SP!N:N,[2]SP!A:A,N10,[2]SP!H:H,$T$2) -> 0 | BP10: =IFERROR(BO10/BM10,0) -> 0 | BQ10: =SUMIFS([2]SD!J:J,[2]SD!A:A,N10,[2]SD!H:H,$P$2)+SUMIFS([2]SD!J:J,[2]SD!A:A,N10,[2]SD!H:H,$T$2) -> 0 | BR10: =SUMIFS([2]SD!L:L,[2]SD!A:A,N10,[2]SD!H:H,$P$2)+SUMIFS([2]SD!L:L,[2]SD!A:A,N10,[2]SD!H:H,$T$2) -> 0 | BS10: =IFERROR(BR10/BQ10,0) -> 0 | BT10: =IFERROR(BX10/BR10,0) -> 0 | BU10: =SUMIFS([2]SD!U:U,[2]SD!A:A,N10,[2]SD!H:H,$P$2)+SUMIFS([2]SD!U:U,[2]SD!A:A,N10,[2]SD!H:H,$T$2) -> 0 | BV10: =SUMIFS([2]SD!V:V,[2]SD!A:A,N10,[2]SD!H:H,$P$2)+SUMIFS([2]SD!V:V,[2]SD!A:A,N10,[2]SD!H:H,$T$2) -> 0 | BW10: =IFERROR(BU10/BR10,0) -> 0 | BX10: =SUMIFS([2]SD!O:O,[2]SD!A:A,N10,[2]SD!H:H,$P$2)+SUMIFS([2]SD!O:O,[2]SD!A:A,N10,[2]SD!H:H,$T$2) -> 0 | BY10: =IFERROR(BX10/BV10,0) -> 0 | BZ10: =SUMIFS([2]SB!H:H,[2]SB!B:B,N10,[2]SB!A:A,$P$2)+SUMIFS([2]SB!H:H,[2]SB!B:B,N10,[2]SB!A:A,$T$2) -> 0 | CA10: =SUMIFS([2]SB!I:I,[2]SB!B:B,N10,[2]SB!A:A,$P$2)+SUMIFS([2]SB!I:I,[2]SB!B:B,N10,[2]SB!A:A,$T$2) -> 0 | CB10: =IFERROR(CA10/BZ10,0) -> 0 | CC10: =IFERROR(CG10/CA10,0) -> 0 | CD10: =SUMIFS([2]SB!Q:Q,[2]SB!B:B,N10,[2]SB!A:A,$P$2)+SUMIFS([2]SB!Q:Q,[2]SB!B:B,N10,[2]SB!A:A,$T$2) -> 0 | CE10: =SUMIFS([2]SB!O:O,[2]SB!B:B,N10,[2]SB!A:A,$P$2)+SUMIFS([2]SB!O:O,[2]SB!B:B,N10,[2]SB!A:A,$T$2) -> 0 | CF10: =IFERROR(CD10/CA10,0) -> 0 | CG10: =SUMIFS([2]SB!L:L,[2]SB!B:B,N10,[2]SB!A:A,$P$2)+SUMIFS([2]SB!L:L,[2]SB!B:B,N10,[2]SB!A:A,$T$2) -> 0 | CH10: =IFERROR(CG10/CE10,0) -> 0
A11: {=IFERROR(LOOKUP(1,0/(([2]业务报告!$A:$A=$N11)*([2]业务报告!$B:$B=$P$2)),[2]业务报告!AU:AU),"")} -> 0 | B11: {=IFERROR(LOOKUP(1,0/(([2]业务报告!$A:$A=$N11)*([2]业务报告!$B:$B=$P$2)),[2]业务报告!AV:AV),"")} -> 0 | C11: =SUMIFS([2]业务报告!AC:AC,[2]业务报告!$A:$A,$N11,[2]业务报告!$B:$B,$P$2) -> 0 | D11: =SUMIFS([2]业务报告!AD:AD,[2]业务报告!$A:$A,$N11,[2]业务报告!$B:$B,$P$2) -> 0 | E11: {=_xlfn.XLOOKUP($N11&$P$2,[2]业务报告!$A:$A&[2]业务报告!$B:$B,[2]业务报告!AE:AE,"")} -> 0 | F11: {=IFERROR(LOOKUP(1,0/(([2]业务报告!$A:$A=$N11)*([2]业务报告!$B:$B=$P$2)),[2]业务报告!AK:AK),0)} -> WBD | G11: =SUMIFS([2]业务报告!AF:AF,[2]业务报告!$A:$A,$N11,[2]业务报告!$B:$B,$P$2) -> 319.89 | H11: {=IFERROR(LOOKUP(1,0/(([2]业务报告!$A:$A=$N11)*([2]业务报告!B:B=$P$2)),[2]业务报告!AG:AG),0)} -> / | I11: {=IFERROR(LOOKUP(1,0/(([2]业务报告!$A:$A=$N11)*([2]业务报告!$B:$B=$P$2)),[2]业务报告!AH:AH),0)} -> 79.99 | J11: =SUMIFS([2]WT报告!A:A,[2]WT报告!$C:$C,$N11,[2]WT报告!$H:$H,$X$2) -> 0 | K11: {=IFERROR(LOOKUP(1,0/(([2]业务报告!$A:$A=$N11)*([2]业务报告!$B:$B=$P$2)),[2]业务报告!AI:AI),0)} -> 0 | L11: {=IFERROR(LOOKUP(1,0/(([2]业务报告!$A:$A=$N11)*([2]业务报告!$B:$B=$P$2)),[2]业务报告!AJ:AJ),0)} -> 0 | M11: =IFERROR("周"&WEEKDAY(N11,2),"-") -> 周7 | N11: =DATE($O$1,$O$2,DAY(N10)+1) -> 45907 | O11: =SUMIFS([2]业务报告!G:G,[2]业务报告!$A:$A,$N11,[2]业务报告!$B:$B,$P$2)+SUMIFS([2]业务报告!G:G,[2]业务报告!$A:$A,$N11,[2]业务报告!$B:$B,$T$2) -> 0 | P11: =SUMIFS([2]业务报告!H:H,[2]业务报告!$A:$A,$N11,[2]业务报告!$B:$B,$P$2)+SUMIFS([2]业务报告!H:H,[2]业务报告!$A:$A,$N11,[2]业务报告!$B:$B,$T$2) -> 0 | Q11: =SUMIFS([2]业务报告!I:I,[2]业务报告!$A:$A,$N11,[2]业务报告!$B:$B,$P$2)+SUMIFS([2]业务报告!I:I,[2]业务报告!$A:$A,$N11,[2]业务报告!$B:$B,$T$2) -> 0 | R11: =SUMIFS([2]业务报告!T:T,[2]业务报告!$A:$A,$N11,[2]业务报告!$B:$B,$P$2)+SUMIFS([2]业务报告!T:T,[2]业务报告!$A:$A,$N11,[2]业务报告!$B:$B,$T$2) -> 0 | S11: =IFERROR((R11+V11)/Q11,0) -> 0 | T11: =SUMIFS([2]业务报告!X:X,[2]业务报告!$A:$A,$N11,[2]业务报告!$B:$B,$P$2)+SUMIFS([2]业务报告!X:X,[2]业务报告!$A:$A,$N11,[2]业务报告!$B:$B,$T$2) -> 0 | U11: =SUMIFS([2]业务报告!AO:AO,[2]业务报告!$A:$A,$N11,[2]业务报告!$B:$B,$P$2)+SUMIFS([2]业务报告!AP:AP,[2]业务报告!$A:$A,$N11,[2]业务报告!$B:$B,$P$2) -> 0 | V11: =SUMIFS([2]WT报告!I:I,[2]WT报告!$C:$C,$N11,[2]WT报告!$H:$H,$X$2) -> 0 | W11: =SUMIFS([2]WT报告!Z:Z,[2]WT报告!$C:$C,$N11,[2]WT报告!$H:$H,$X$2) -> 0 | X11: =SUMIFS([2]业务报告!AS:AS,[2]业务报告!$A:$A,$N11,[2]业务报告!$B:$B,$P$2)+SUMIFS([2]业务报告!AS:AS,[2]业务报告!$A:$A,$N11,[2]业务报告!$B:$B,$T$2)+V11 -> 0 | Y11: =SUMIFS([2]业务报告!AO:AO,[2]业务报告!$A:$A,$N11,[2]业务报告!$B:$B,$P$2)*SUMIFS([2]业务报告!AM:AM,[2]业务报告!$A:$A,$N11,[2]业务报告!$B:$B,$P$2)/$AC$2+SUMIFS([2]业务报告!AP:AP,[2]业务报告!$A:$A,$N11,[2]业务报告!$B:$B,$P$2)*SUMIFS([2]业务报告!AN:AN,[2]业务报告!$A:$A,$N11,[2]业务报告!$B:$B,$P$2)/$AC$2 -> 0 | Z11: =(I11*(1-$AD$2-4%-10%)-$AD$1-$AC$1/$AC$2)*BB11-BC11 -> 0 | AA11: =(I11*(1-$AD$2-4%-10%)-$AD$1-$AC$1/$AC$2)*(R11-IF(R11>V11,SUMIFS([2]业务报告!AO:AO,[2]业务报告!$A:$A,$N11,[2]业务报告!$B:$B,$P$2),0))-BC11 -> 0 | AB11: =IFERROR(AA11/(I11*R11),0) -> 0 | AC11: =AR11*(J11-$AC$1/$AC$2-J11*4%)-AS11 -> 0 | AD11: =(V11-IF(R11<V11,SUMIFS([2]业务报告!AO:AO,[2]业务报告!$A:$A,$N11,[2]业务报告!$B:$B,$P$2),0))*(J11-$AC$1/$AC$2-J11*4%)-AS11 -> 0 | AE11: {=IFERROR(LOOKUP(1,0/(([2]业务报告!$A:$A=$N11)*([2]业务报告!$B:$B=$P$2)),[2]业务报告!AQ:AQ),0)*$AH$2} -> 0 | AF11: {=IFERROR(LOOKUP(1,0/(([2]业务报告!$A:$A=$N11)*([2]业务报告!$B:$B=$P$2)),[2]业务报告!AR:AR),0)*$AG$2} -> 0 | AG11: =AA11+AD11+AE11+AF11-Y11 -> 0 | AH11: =IFERROR((AG11)/(T11+J11*V11),0) -> 0 | AI11: =IFERROR((AG11)/(X11),0) -> 0 | AJ11: =IFERROR(AS11/(V11*J11),0) -> 0 | AK11: =IFERROR(ROUNDUP(AS11/V11,1),0) -> 0 | AL11: =SUMIFS([2]WT报告!S:S,[2]WT报告!$C:$C,$N11,[2]WT报告!$H:$H,$X$2) -> 0 | AM11: =IFERROR((AR11)/AP11,0) -> 0 | AN11: =SUMIFS([2]WT报告!N:N,[2]WT报告!$C:$C,$N11,[2]WT报告!$H:$H,$X$2) -> 0 | AO11: =IFERROR(AR11/(V11),0) -> 0 | AP11: =SUMIFS([2]WT报告!P:P,[2]WT报告!$C:$C,$N11,[2]WT报告!$H:$H,$X$2) -> 0 | AQ11: =SUMIFS([2]WT报告!Q:Q,[2]WT报告!$C:$C,$N11,[2]WT报告!$H:$H,$X$2) -> 0 | AR11: =SUMIFS([2]WT报告!J:J,[2]WT报告!$C:$C,$N11,[2]WT报告!$H:$H,$X$2) -> 0 | AS11: =SUMIFS([2]WT报告!M:M,[2]WT报告!$C:$C,$N11,[2]WT报告!$H:$H,$X$2) -> 0 | AT11: =IFERROR((BO11+BX11+CG11)/(R11*I11),0) -> 0 | AU11: =IFERROR(ROUNDUP(BC11/R11,1),0) -> 0 | AV11: =IFERROR(ROUNDUP(BC11/BB11,1),0) -> 0 | AW11: =IFERROR((BB11)/AZ11,0) -> 0 | AX11: =IFERROR(BC11/AZ11,0) -> 0 | AY11: =IFERROR((BL11+BU11+CD11)/(R11+V11),0) -> 0 | AZ11: =BI11+BR11+CA11 -> 0 | BA11: =IFERROR((BI11+BR11+CA11)/(BH11+BQ11+BZ11),0) -> 0 | BB11: =BL11+BU11+CD11 -> 0 | BC11: =ROUND(BO11+BX11+CG11,2) -> 0 | BD11: =IFERROR(BC11/(BM11+BV11+CE11),0) -> 0 | BE11: =IFERROR(ROUNDUP((BO11+CG11)/BG11,1),0) -> 0 | BF11: =IFERROR(BG11/(BI11+CA11),0) -> 0 | BG11: =BL11+CD11 -> 0 | BH11: =SUMIFS([2]SP!J:J,[2]SP!A:A,N11,[2]SP!H:H,$P$2)+SUMIFS([2]SP!J:J,[2]SP!A:A,N11,[2]SP!H:H,$T$2) -> 0 | BI11: =SUMIFS([2]SP!K:K,[2]SP!A:A,N11,[2]SP!H:H,$P$2)+SUMIFS([2]SP!K:K,[2]SP!A:A,N11,[2]SP!H:H,$T$2) -> 0 | BJ11: =IFERROR(BI11/BH11,0) -> 0 | BK11: =IFERROR(BO11/BI11,0) -> 0 | BL11: =SUMIFS([2]SP!R:R,[2]SP!A:A,N11,[2]SP!H:H,$P$2)+SUMIFS([2]SP!R:R,[2]SP!A:A,N11,[2]SP!H:H,$T$2) -> 0 | BM11: =SUMIFS([2]SP!O:O,[2]SP!A:A,$N11,[2]SP!H:H,$P$2)+SUMIFS([2]SP!O:O,[2]SP!A:A,$N11,[2]SP!H:H,$T$2) -> 0 | BN11: =IFERROR(BL11/BI11,0) -> 0 | BO11: =SUMIFS([2]SP!N:N,[2]SP!A:A,N11,[2]SP!H:H,$P$2)+SUMIFS([2]SP!N:N,[2]SP!A:A,N11,[2]SP!H:H,$T$2) -> 0 | BP11: =IFERROR(BO11/BM11,0) -> 0 | BQ11: =SUMIFS([2]SD!J:J,[2]SD!A:A,N11,[2]SD!H:H,$P$2)+SUMIFS([2]SD!J:J,[2]SD!A:A,N11,[2]SD!H:H,$T$2) -> 0 | BR11: =SUMIFS([2]SD!L:L,[2]SD!A:A,N11,[2]SD!H:H,$P$2)+SUMIFS([2]SD!L:L,[2]SD!A:A,N11,[2]SD!H:H,$T$2) -> 0 | BS11: =IFERROR(BR11/BQ11,0) -> 0 | BT11: =IFERROR(BX11/BR11,0) -> 0 | BU11: =SUMIFS([2]SD!U:U,[2]SD!A:A,N11,[2]SD!H:H,$P$2)+SUMIFS([2]SD!U:U,[2]SD!A:A,N11,[2]SD!H:H,$T$2) -> 0 | BV11: =SUMIFS([2]SD!V:V,[2]SD!A:A,N11,[2]SD!H:H,$P$2)+SUMIFS([2]SD!V:V,[2]SD!A:A,N11,[2]SD!H:H,$T$2) -> 0 | BW11: =IFERROR(BU11/BR11,0) -> 0 | BX11: =SUMIFS([2]SD!O:O,[2]SD!A:A,N11,[2]SD!H:H,$P$2)+SUMIFS([2]SD!O:O,[2]SD!A:A,N11,[2]SD!H:H,$T$2) -> 0 | BY11: =IFERROR(BX11/BV11,0) -> 0 | BZ11: =SUMIFS([2]SB!H:H,[2]SB!B:B,N11,[2]SB!A:A,$P$2)+SUMIFS([2]SB!H:H,[2]SB!B:B,N11,[2]SB!A:A,$T$2) -> 0 | CA11: =SUMIFS([2]SB!I:I,[2]SB!B:B,N11,[2]SB!A:A,$P$2)+SUMIFS([2]SB!I:I,[2]SB!B:B,N11,[2]SB!A:A,$T$2) -> 0 | CB11: =IFERROR(CA11/BZ11,0) -> 0 | CC11: =IFERROR(CG11/CA11,0) -> 0 | CD11: =SUMIFS([2]SB!Q:Q,[2]SB!B:B,N11,[2]SB!A:A,$P$2)+SUMIFS([2]SB!Q:Q,[2]SB!B:B,N11,[2]SB!A:A,$T$2) -> 0 | CE11: =SUMIFS([2]SB!O:O,[2]SB!B:B,N11,[2]SB!A:A,$P$2)+SUMIFS([2]SB!O:O,[2]SB!B:B,N11,[2]SB!A:A,$T$2) -> 0 | CF11: =IFERROR(CD11/CA11,0) -> 0 | CG11: =SUMIFS([2]SB!L:L,[2]SB!B:B,N11,[2]SB!A:A,$P$2)+SUMIFS([2]SB!L:L,[2]SB!B:B,N11,[2]SB!A:A,$T$2) -> 0 | CH11: =IFERROR(CG11/CE11,0) -> 0
A12: {=IFERROR(LOOKUP(1,0/(([2]业务报告!$A:$A=$N12)*([2]业务报告!$B:$B=$P$2)),[2]业务报告!AU:AU),"")} -> 0 | B12: {=IFERROR(LOOKUP(1,0/(([2]业务报告!$A:$A=$N12)*([2]业务报告!$B:$B=$P$2)),[2]业务报告!AV:AV),"")} -> 0 | C12: =SUMIFS([2]业务报告!AC:AC,[2]业务报告!$A:$A,$N12,[2]业务报告!$B:$B,$P$2) -> 0 | D12: =SUMIFS([2]业务报告!AD:AD,[2]业务报告!$A:$A,$N12,[2]业务报告!$B:$B,$P$2) -> 0 | E12: {=_xlfn.XLOOKUP($N12&$P$2,[2]业务报告!$A:$A&[2]业务报告!$B:$B,[2]业务报告!AE:AE,"")} -> 0 | F12: {=IFERROR(LOOKUP(1,0/(([2]业务报告!$A:$A=$N12)*([2]业务报告!$B:$B=$P$2)),[2]业务报告!AK:AK),0)} -> WBD | G12: =SUMIFS([2]业务报告!AF:AF,[2]业务报告!$A:$A,$N12,[2]业务报告!$B:$B,$P$2) -> 319.89 | H12: {=IFERROR(LOOKUP(1,0/(([2]业务报告!$A:$A=$N12)*([2]业务报告!B:B=$P$2)),[2]业务报告!AG:AG),0)} -> / | I12: {=IFERROR(LOOKUP(1,0/(([2]业务报告!$A:$A=$N12)*([2]业务报告!$B:$B=$P$2)),[2]业务报告!AH:AH),0)} -> 79.99 | J12: =SUMIFS([2]WT报告!A:A,[2]WT报告!$C:$C,$N12,[2]WT报告!$H:$H,$X$2) -> 0 | K12: {=IFERROR(LOOKUP(1,0/(([2]业务报告!$A:$A=$N12)*([2]业务报告!$B:$B=$P$2)),[2]业务报告!AI:AI),0)} -> 0 | L12: {=IFERROR(LOOKUP(1,0/(([2]业务报告!$A:$A=$N12)*([2]业务报告!$B:$B=$P$2)),[2]业务报告!AJ:AJ),0)} -> 0 | M12: =IFERROR("周"&WEEKDAY(N12,2),"-") -> 周1 | N12: =DATE($O$1,$O$2,DAY(N11)+1) -> 45908 | O12: =SUMIFS([2]业务报告!G:G,[2]业务报告!$A:$A,$N12,[2]业务报告!$B:$B,$P$2)+SUMIFS([2]业务报告!G:G,[2]业务报告!$A:$A,$N12,[2]业务报告!$B:$B,$T$2) -> 0 | P12: =SUMIFS([2]业务报告!H:H,[2]业务报告!$A:$A,$N12,[2]业务报告!$B:$B,$P$2)+SUMIFS([2]业务报告!H:H,[2]业务报告!$A:$A,$N12,[2]业务报告!$B:$B,$T$2) -> 0 | Q12: =SUMIFS([2]业务报告!I:I,[2]业务报告!$A:$A,$N12,[2]业务报告!$B:$B,$P$2)+SUMIFS([2]业务报告!I:I,[2]业务报告!$A:$A,$N12,[2]业务报告!$B:$B,$T$2) -> 0 | R12: =SUMIFS([2]业务报告!T:T,[2]业务报告!$A:$A,$N12,[2]业务报告!$B:$B,$P$2)+SUMIFS([2]业务报告!T:T,[2]业务报告!$A:$A,$N12,[2]业务报告!$B:$B,$T$2) -> 0 | S12: =IFERROR((R12+V12)/Q12,0) -> 0 | T12: =SUMIFS([2]业务报告!X:X,[2]业务报告!$A:$A,$N12,[2]业务报告!$B:$B,$P$2)+SUMIFS([2]业务报告!X:X,[2]业务报告!$A:$A,$N12,[2]业务报告!$B:$B,$T$2) -> 0 | U12: =SUMIFS([2]业务报告!AO:AO,[2]业务报告!$A:$A,$N12,[2]业务报告!$B:$B,$P$2)+SUMIFS([2]业务报告!AP:AP,[2]业务报告!$A:$A,$N12,[2]业务报告!$B:$B,$P$2) -> 0 | V12: =SUMIFS([2]WT报告!I:I,[2]WT报告!$C:$C,$N12,[2]WT报告!$H:$H,$X$2) -> 0 | W12: =SUMIFS([2]WT报告!Z:Z,[2]WT报告!$C:$C,$N12,[2]WT报告!$H:$H,$X$2) -> 0 | X12: =SUMIFS([2]业务报告!AS:AS,[2]业务报告!$A:$A,$N12,[2]业务报告!$B:$B,$P$2)+SUMIFS([2]业务报告!AS:AS,[2]业务报告!$A:$A,$N12,[2]业务报告!$B:$B,$T$2)+V12 -> 0 | Y12: =SUMIFS([2]业务报告!AO:AO,[2]业务报告!$A:$A,$N12,[2]业务报告!$B:$B,$P$2)*SUMIFS([2]业务报告!AM:AM,[2]业务报告!$A:$A,$N12,[2]业务报告!$B:$B,$P$2)/$AC$2+SUMIFS([2]业务报告!AP:AP,[2]业务报告!$A:$A,$N12,[2]业务报告!$B:$B,$P$2)*SUMIFS([2]业务报告!AN:AN,[2]业务报告!$A:$A,$N12,[2]业务报告!$B:$B,$P$2)/$AC$2 -> 0 | Z12: =(I12*(1-$AD$2-4%-10%)-$AD$1-$AC$1/$AC$2)*BB12-BC12 -> 0 | AA12: =(I12*(1-$AD$2-4%-10%)-$AD$1-$AC$1/$AC$2)*(R12-IF(R12>V12,SUMIFS([2]业务报告!AO:AO,[2]业务报告!$A:$A,$N12,[2]业务报告!$B:$B,$P$2),0))-BC12 -> 0 | AB12: =IFERROR(AA12/(I12*R12),0) -> 0 | AC12: =AR12*(J12-$AC$1/$AC$2-J12*4%)-AS12 -> 0 | AD12: =(V12-IF(R12<V12,SUMIFS([2]业务报告!AO:AO,[2]业务报告!$A:$A,$N12,[2]业务报告!$B:$B,$P$2),0))*(J12-$AC$1/$AC$2-J12*4%)-AS12 -> 0 | AE12: {=IFERROR(LOOKUP(1,0/(([2]业务报告!$A:$A=$N12)*([2]业务报告!$B:$B=$P$2)),[2]业务报告!AQ:AQ),0)*$AH$2} -> 0 | AF12: {=IFERROR(LOOKUP(1,0/(([2]业务报告!$A:$A=$N12)*([2]业务报告!$B:$B=$P$2)),[2]业务报告!AR:AR),0)*$AG$2} -> 0 | AG12: =AA12+AD12+AE12+AF12-Y12 -> 0 | AH12: =IFERROR((AG12)/(T12+J12*V12),0) -> 0 | AI12: =IFERROR((AG12)/(X12),0) -> 0 | AJ12: =IFERROR(AS12/(V12*J12),0) -> 0 | AK12: =IFERROR(ROUNDUP(AS12/V12,1),0) -> 0 | AL12: =SUMIFS([2]WT报告!S:S,[2]WT报告!$C:$C,$N12,[2]WT报告!$H:$H,$X$2) -> 0 | AM12: =IFERROR((AR12)/AP12,0) -> 0 | AN12: =SUMIFS([2]WT报告!N:N,[2]WT报告!$C:$C,$N12,[2]WT报告!$H:$H,$X$2) -> 0 | AO12: =IFERROR(AR12/(V12),0) -> 0 | AP12: =SUMIFS([2]WT报告!P:P,[2]WT报告!$C:$C,$N12,[2]WT报告!$H:$H,$X$2) -> 0 | AQ12: =SUMIFS([2]WT报告!Q:Q,[2]WT报告!$C:$C,$N12,[2]WT报告!$H:$H,$X$2) -> 0 | AR12: =SUMIFS([2]WT报告!J:J,[2]WT报告!$C:$C,$N12,[2]WT报告!$H:$H,$X$2) -> 0 | AS12: =SUMIFS([2]WT报告!M:M,[2]WT报告!$C:$C,$N12,[2]WT报告!$H:$H,$X$2) -> 0 | AT12: =IFERROR((BO12+BX12+CG12)/(R12*I12),0) -> 0 | AU12: =IFERROR(ROUNDUP(BC12/R12,1),0) -> 0 | AV12: =IFERROR(ROUNDUP(BC12/BB12,1),0) -> 0 | AW12: =IFERROR((BB12)/AZ12,0) -> 0 | AX12: =IFERROR(BC12/AZ12,0) -> 0 | AY12: =IFERROR((BL12+BU12+CD12)/(R12+V12),0) -> 0 | AZ12: =BI12+BR12+CA12 -> 0 | BA12: =IFERROR((BI12+BR12+CA12)/(BH12+BQ12+BZ12),0) -> 0 | BB12: =BL12+BU12+CD12 -> 0 | BC12: =ROUND(BO12+BX12+CG12,2) -> 0 | BD12: =IFERROR(BC12/(BM12+BV12+CE12),0) -> 0 | BE12: =IFERROR(ROUNDUP((BO12+CG12)/BG12,1),0) -> 0 | BF12: =IFERROR(BG12/(BI12+CA12),0) -> 0 | BG12: =BL12+CD12 -> 0 | BH12: =SUMIFS([2]SP!J:J,[2]SP!A:A,N12,[2]SP!H:H,$P$2)+SUMIFS([2]SP!J:J,[2]SP!A:A,N12,[2]SP!H:H,$T$2) -> 0 | BI12: =SUMIFS([2]SP!K:K,[2]SP!A:A,N12,[2]SP!H:H,$P$2)+SUMIFS([2]SP!K:K,[2]SP!A:A,N12,[2]SP!H:H,$T$2) -> 0 | BJ12: =IFERROR(BI12/BH12,0) -> 0 | BK12: =IFERROR(BO12/BI12,0) -> 0 | BL12: =SUMIFS([2]SP!R:R,[2]SP!A:A,N12,[2]SP!H:H,$P$2)+SUMIFS([2]SP!R:R,[2]SP!A:A,N12,[2]SP!H:H,$T$2) -> 0 | BM12: =SUMIFS([2]SP!O:O,[2]SP!A:A,$N12,[2]SP!H:H,$P$2)+SUMIFS([2]SP!O:O,[2]SP!A:A,$N12,[2]SP!H:H,$T$2) -> 0 | BN12: =IFERROR(BL12/BI12,0) -> 0 | BO12: =SUMIFS([2]SP!N:N,[2]SP!A:A,N12,[2]SP!H:H,$P$2)+SUMIFS([2]SP!N:N,[2]SP!A:A,N12,[2]SP!H:H,$T$2) -> 0 | BP12: =IFERROR(BO12/BM12,0) -> 0 | BQ12: =SUMIFS([2]SD!J:J,[2]SD!A:A,N12,[2]SD!H:H,$P$2)+SUMIFS([2]SD!J:J,[2]SD!A:A,N12,[2]SD!H:H,$T$2) -> 0 | BR12: =SUMIFS([2]SD!L:L,[2]SD!A:A,N12,[2]SD!H:H,$P$2)+SUMIFS([2]SD!L:L,[2]SD!A:A,N12,[2]SD!H:H,$T$2) -> 0 | BS12: =IFERROR(BR12/BQ12,0) -> 0 | BT12: =IFERROR(BX12/BR12,0) -> 0 | BU12: =SUMIFS([2]SD!U:U,[2]SD!A:A,N12,[2]SD!H:H,$P$2)+SUMIFS([2]SD!U:U,[2]SD!A:A,N12,[2]SD!H:H,$T$2) -> 0 | BV12: =SUMIFS([2]SD!V:V,[2]SD!A:A,N12,[2]SD!H:H,$P$2)+SUMIFS([2]SD!V:V,[2]SD!A:A,N12,[2]SD!H:H,$T$2) -> 0 | BW12: =IFERROR(BU12/BR12,0) -> 0 | BX12: =SUMIFS([2]SD!O:O,[2]SD!A:A,N12,[2]SD!H:H,$P$2)+SUMIFS([2]SD!O:O,[2]SD!A:A,N12,[2]SD!H:H,$T$2) -> 0 | BY12: =IFERROR(BX12/BV12,0) -> 0 | BZ12: =SUMIFS([2]SB!H:H,[2]SB!B:B,N12,[2]SB!A:A,$P$2)+SUMIFS([2]SB!H:H,[2]SB!B:B,N12,[2]SB!A:A,$T$2) -> 0 | CA12: =SUMIFS([2]SB!I:I,[2]SB!B:B,N12,[2]SB!A:A,$P$2)+SUMIFS([2]SB!I:I,[2]SB!B:B,N12,[2]SB!A:A,$T$2) -> 0 | CB12: =IFERROR(CA12/BZ12,0) -> 0 | CC12: =IFERROR(CG12/CA12,0) -> 0 | CD12: =SUMIFS([2]SB!Q:Q,[2]SB!B:B,N12,[2]SB!A:A,$P$2)+SUMIFS([2]SB!Q:Q,[2]SB!B:B,N12,[2]SB!A:A,$T$2) -> 0 | CE12: =SUMIFS([2]SB!O:O,[2]SB!B:B,N12,[2]SB!A:A,$P$2)+SUMIFS([2]SB!O:O,[2]SB!B:B,N12,[2]SB!A:A,$T$2) -> 0 | CF12: =IFERROR(CD12/CA12,0) -> 0 | CG12: =SUMIFS([2]SB!L:L,[2]SB!B:B,N12,[2]SB!A:A,$P$2)+SUMIFS([2]SB!L:L,[2]SB!B:B,N12,[2]SB!A:A,$T$2) -> 0 | CH12: =IFERROR(CG12/CE12,0) -> 0
A13: {=IFERROR(LOOKUP(1,0/(([2]业务报告!$A:$A=$N13)*([2]业务报告!$B:$B=$P$2)),[2]业务报告!AU:AU),"")} -> 0 | B13: {=IFERROR(LOOKUP(1,0/(([2]业务报告!$A:$A=$N13)*([2]业务报告!$B:$B=$P$2)),[2]业务报告!AV:AV),"")} -> 0 | C13: =SUMIFS([2]业务报告!AC:AC,[2]业务报告!$A:$A,$N13,[2]业务报告!$B:$B,$P$2) -> 0 | D13: =SUMIFS([2]业务报告!AD:AD,[2]业务报告!$A:$A,$N13,[2]业务报告!$B:$B,$P$2) -> 0 | E13: {=_xlfn.XLOOKUP($N13&$P$2,[2]业务报告!$A:$A&[2]业务报告!$B:$B,[2]业务报告!AE:AE,"")} -> 0 | F13: {=IFERROR(LOOKUP(1,0/(([2]业务报告!$A:$A=$N13)*([2]业务报告!$B:$B=$P$2)),[2]业务报告!AK:AK),0)} -> WBD | G13: =SUMIFS([2]业务报告!AF:AF,[2]业务报告!$A:$A,$N13,[2]业务报告!$B:$B,$P$2) -> 319.89 | H13: {=IFERROR(LOOKUP(1,0/(([2]业务报告!$A:$A=$N13)*([2]业务报告!B:B=$P$2)),[2]业务报告!AG:AG),0)} -> / | I13: {=IFERROR(LOOKUP(1,0/(([2]业务报告!$A:$A=$N13)*([2]业务报告!$B:$B=$P$2)),[2]业务报告!AH:AH),0)} -> 79.99 | J13: =SUMIFS([2]WT报告!A:A,[2]WT报告!$C:$C,$N13,[2]WT报告!$H:$H,$X$2) -> 0 | K13: {=IFERROR(LOOKUP(1,0/(([2]业务报告!$A:$A=$N13)*([2]业务报告!$B:$B=$P$2)),[2]业务报告!AI:AI),0)} -> 0 | L13: {=IFERROR(LOOKUP(1,0/(([2]业务报告!$A:$A=$N13)*([2]业务报告!$B:$B=$P$2)),[2]业务报告!AJ:AJ),0)} -> 0 | M13: =IFERROR("周"&WEEKDAY(N13,2),"-") -> 周2 | N13: =DATE($O$1,$O$2,DAY(N12)+1) -> 45909 | O13: =SUMIFS([2]业务报告!G:G,[2]业务报告!$A:$A,$N13,[2]业务报告!$B:$B,$P$2)+SUMIFS([2]业务报告!G:G,[2]业务报告!$A:$A,$N13,[2]业务报告!$B:$B,$T$2) -> 0 | P13: =SUMIFS([2]业务报告!H:H,[2]业务报告!$A:$A,$N13,[2]业务报告!$B:$B,$P$2)+SUMIFS([2]业务报告!H:H,[2]业务报告!$A:$A,$N13,[2]业务报告!$B:$B,$T$2) -> 0 | Q13: =SUMIFS([2]业务报告!I:I,[2]业务报告!$A:$A,$N13,[2]业务报告!$B:$B,$P$2)+SUMIFS([2]业务报告!I:I,[2]业务报告!$A:$A,$N13,[2]业务报告!$B:$B,$T$2) -> 0 | R13: =SUMIFS([2]业务报告!T:T,[2]业务报告!$A:$A,$N13,[2]业务报告!$B:$B,$P$2)+SUMIFS([2]业务报告!T:T,[2]业务报告!$A:$A,$N13,[2]业务报告!$B:$B,$T$2) -> 0 | S13: =IFERROR((R13+V13)/Q13,0) -> 0 | T13: =SUMIFS([2]业务报告!X:X,[2]业务报告!$A:$A,$N13,[2]业务报告!$B:$B,$P$2)+SUMIFS([2]业务报告!X:X,[2]业务报告!$A:$A,$N13,[2]业务报告!$B:$B,$T$2) -> 0 | U13: =SUMIFS([2]业务报告!AO:AO,[2]业务报告!$A:$A,$N13,[2]业务报告!$B:$B,$P$2)+SUMIFS([2]业务报告!AP:AP,[2]业务报告!$A:$A,$N13,[2]业务报告!$B:$B,$P$2) -> 0 | V13: =SUMIFS([2]WT报告!I:I,[2]WT报告!$C:$C,$N13,[2]WT报告!$H:$H,$X$2) -> 0 | W13: =SUMIFS([2]WT报告!Z:Z,[2]WT报告!$C:$C,$N13,[2]WT报告!$H:$H,$X$2) -> 0 | X13: =SUMIFS([2]业务报告!AS:AS,[2]业务报告!$A:$A,$N13,[2]业务报告!$B:$B,$P$2)+SUMIFS([2]业务报告!AS:AS,[2]业务报告!$A:$A,$N13,[2]业务报告!$B:$B,$T$2)+V13 -> 0 | Y13: =SUMIFS([2]业务报告!AO:AO,[2]业务报告!$A:$A,$N13,[2]业务报告!$B:$B,$P$2)*SUMIFS([2]业务报告!AM:AM,[2]业务报告!$A:$A,$N13,[2]业务报告!$B:$B,$P$2)/$AC$2+SUMIFS([2]业务报告!AP:AP,[2]业务报告!$A:$A,$N13,[2]业务报告!$B:$B,$P$2)*SUMIFS([2]业务报告!AN:AN,[2]业务报告!$A:$A,$N13,[2]业务报告!$B:$B,$P$2)/$AC$2 -> 0 | Z13: =(I13*(1-$AD$2-4%-10%)-$AD$1-$AC$1/$AC$2)*BB13-BC13 -> 0 | AA13: =(I13*(1-$AD$2-4%-10%)-$AD$1-$AC$1/$AC$2)*(R13-IF(R13>V13,SUMIFS([2]业务报告!AO:AO,[2]业务报告!$A:$A,$N13,[2]业务报告!$B:$B,$P$2),0))-BC13 -> 0 | AB13: =IFERROR(AA13/(I13*R13),0) -> 0 | AC13: =AR13*(J13-$AC$1/$AC$2-J13*4%)-AS13 -> 0 | AD13: =(V13-IF(R13<V13,SUMIFS([2]业务报告!AO:AO,[2]业务报告!$A:$A,$N13,[2]业务报告!$B:$B,$P$2),0))*(J13-$AC$1/$AC$2-J13*4%)-AS13 -> 0 | AE13: {=IFERROR(LOOKUP(1,0/(([2]业务报告!$A:$A=$N13)*([2]业务报告!$B:$B=$P$2)),[2]业务报告!AQ:AQ),0)*$AH$2} -> 0 | AF13: {=IFERROR(LOOKUP(1,0/(([2]业务报告!$A:$A=$N13)*([2]业务报告!$B:$B=$P$2)),[2]业务报告!AR:AR),0)*$AG$2} -> 0 | AG13: =AA13+AD13+AE13+AF13-Y13 -> 0 | AH13: =IFERROR((AG13)/(T13+J13*V13),0) -> 0 | AI13: =IFERROR((AG13)/(X13),0) -> 0 | AJ13: =IFERROR(AS13/(V13*J13),0) -> 0 | AK13: =IFERROR(ROUNDUP(AS13/V13,1),0) -> 0 | AL13: =SUMIFS([2]WT报告!S:S,[2]WT报告!$C:$C,$N13,[2]WT报告!$H:$H,$X$2) -> 0 | AM13: =IFERROR((AR13)/AP13,0) -> 0 | AN13: =SUMIFS([2]WT报告!N:N,[2]WT报告!$C:$C,$N13,[2]WT报告!$H:$H,$X$2) -> 0 | AO13: =IFERROR(AR13/(V13),0) -> 0 | AP13: =SUMIFS([2]WT报告!P:P,[2]WT报告!$C:$C,$N13,[2]WT报告!$H:$H,$X$2) -> 0 | AQ13: =SUMIFS([2]WT报告!Q:Q,[2]WT报告!$C:$C,$N13,[2]WT报告!$H:$H,$X$2) -> 0 | AR13: =SUMIFS([2]WT报告!J:J,[2]WT报告!$C:$C,$N13,[2]WT报告!$H:$H,$X$2) -> 0 | AS13: =SUMIFS([2]WT报告!M:M,[2]WT报告!$C:$C,$N13,[2]WT报告!$H:$H,$X$2) -> 0 | AT13: =IFERROR((BO13+BX13+CG13)/(R13*I13),0) -> 0 | AU13: =IFERROR(ROUNDUP(BC13/R13,1),0) -> 0 | AV13: =IFERROR(ROUNDUP(BC13/BB13,1),0) -> 0 | AW13: =IFERROR((BB13)/AZ13,0) -> 0 | AX13: =IFERROR(BC13/AZ13,0) -> 0 | AY13: =IFERROR((BL13+BU13+CD13)/(R13+V13),0) -> 0 | AZ13: =BI13+BR13+CA13 -> 0 | BA13: =IFERROR((BI13+BR13+CA13)/(BH13+BQ13+BZ13),0) -> 0 | BB13: =BL13+BU13+CD13 -> 0 | BC13: =ROUND(BO13+BX13+CG13,2) -> 0 | BD13: =IFERROR(BC13/(BM13+BV13+CE13),0) -> 0 | BE13: =IFERROR(ROUNDUP((BO13+CG13)/BG13,1),0) -> 0 | BF13: =IFERROR(BG13/(BI13+CA13),0) -> 0 | BG13: =BL13+CD13 -> 0 | BH13: =SUMIFS([2]SP!J:J,[2]SP!A:A,N13,[2]SP!H:H,$P$2)+SUMIFS([2]SP!J:J,[2]SP!A:A,N13,[2]SP!H:H,$T$2) -> 0 | BI13: =SUMIFS([2]SP!K:K,[2]SP!A:A,N13,[2]SP!H:H,$P$2)+SUMIFS([2]SP!K:K,[2]SP!A:A,N13,[2]SP!H:H,$T$2) -> 0 | BJ13: =IFERROR(BI13/BH13,0) -> 0 | BK13: =IFERROR(BO13/BI13,0) -> 0 | BL13: =SUMIFS([2]SP!R:R,[2]SP!A:A,N13,[2]SP!H:H,$P$2)+SUMIFS([2]SP!R:R,[2]SP!A:A,N13,[2]SP!H:H,$T$2) -> 0 | BM13: =SUMIFS([2]SP!O:O,[2]SP!A:A,$N13,[2]SP!H:H,$P$2)+SUMIFS([2]SP!O:O,[2]SP!A:A,$N13,[2]SP!H:H,$T$2) -> 0 | BN13: =IFERROR(BL13/BI13,0) -> 0 | BO13: =SUMIFS([2]SP!N:N,[2]SP!A:A,N13,[2]SP!H:H,$P$2)+SUMIFS([2]SP!N:N,[2]SP!A:A,N13,[2]SP!H:H,$T$2) -> 0 | BP13: =IFERROR(BO13/BM13,0) -> 0 | BQ13: =SUMIFS([2]SD!J:J,[2]SD!A:A,N13,[2]SD!H:H,$P$2)+SUMIFS([2]SD!J:J,[2]SD!A:A,N13,[2]SD!H:H,$T$2) -> 0 | BR13: =SUMIFS([2]SD!L:L,[2]SD!A:A,N13,[2]SD!H:H,$P$2)+SUMIFS([2]SD!L:L,[2]SD!A:A,N13,[2]SD!H:H,$T$2) -> 0 | BS13: =IFERROR(BR13/BQ13,0) -> 0 | BT13: =IFERROR(BX13/BR13,0) -> 0 | BU13: =SUMIFS([2]SD!U:U,[2]SD!A:A,N13,[2]SD!H:H,$P$2)+SUMIFS([2]SD!U:U,[2]SD!A:A,N13,[2]SD!H:H,$T$2) -> 0 | BV13: =SUMIFS([2]SD!V:V,[2]SD!A:A,N13,[2]SD!H:H,$P$2)+SUMIFS([2]SD!V:V,[2]SD!A:A,N13,[2]SD!H:H,$T$2) -> 0 | BW13: =IFERROR(BU13/BR13,0) -> 0 | BX13: =SUMIFS([2]SD!O:O,[2]SD!A:A,N13,[2]SD!H:H,$P$2)+SUMIFS([2]SD!O:O,[2]SD!A:A,N13,[2]SD!H:H,$T$2) -> 0 | BY13: =IFERROR(BX13/BV13,0) -> 0 | BZ13: =SUMIFS([2]SB!H:H,[2]SB!B:B,N13,[2]SB!A:A,$P$2)+SUMIFS([2]SB!H:H,[2]SB!B:B,N13,[2]SB!A:A,$T$2) -> 0 | CA13: =SUMIFS([2]SB!I:I,[2]SB!B:B,N13,[2]SB!A:A,$P$2)+SUMIFS([2]SB!I:I,[2]SB!B:B,N13,[2]SB!A:A,$T$2) -> 0 | CB13: =IFERROR(CA13/BZ13,0) -> 0 | CC13: =IFERROR(CG13/CA13,0) -> 0 | CD13: =SUMIFS([2]SB!Q:Q,[2]SB!B:B,N13,[2]SB!A:A,$P$2)+SUMIFS([2]SB!Q:Q,[2]SB!B:B,N13,[2]SB!A:A,$T$2) -> 0 | CE13: =SUMIFS([2]SB!O:O,[2]SB!B:B,N13,[2]SB!A:A,$P$2)+SUMIFS([2]SB!O:O,[2]SB!B:B,N13,[2]SB!A:A,$T$2) -> 0 | CF13: =IFERROR(CD13/CA13,0) -> 0 | CG13: =SUMIFS([2]SB!L:L,[2]SB!B:B,N13,[2]SB!A:A,$P$2)+SUMIFS([2]SB!L:L,[2]SB!B:B,N13,[2]SB!A:A,$T$2) -> 0 | CH13: =IFERROR(CG13/CE13,0) -> 0
A14: {=IFERROR(LOOKUP(1,0/(([2]业务报告!$A:$A=$N14)*([2]业务报告!$B:$B=$P$2)),[2]业务报告!AU:AU),"")} -> 0 | B14: {=IFERROR(LOOKUP(1,0/(([2]业务报告!$A:$A=$N14)*([2]业务报告!$B:$B=$P$2)),[2]业务报告!AV:AV),"")} -> 0 | C14: =SUMIFS([2]业务报告!AC:AC,[2]业务报告!$A:$A,$N14,[2]业务报告!$B:$B,$P$2) -> 0 | D14: =SUMIFS([2]业务报告!AD:AD,[2]业务报告!$A:$A,$N14,[2]业务报告!$B:$B,$P$2) -> 0 | E14: {=_xlfn.XLOOKUP($N14&$P$2,[2]业务报告!$A:$A&[2]业务报告!$B:$B,[2]业务报告!AE:AE,"")} -> 0 | F14: {=IFERROR(LOOKUP(1,0/(([2]业务报告!$A:$A=$N14)*([2]业务报告!$B:$B=$P$2)),[2]业务报告!AK:AK),0)} -> WBD | G14: =SUMIFS([2]业务报告!AF:AF,[2]业务报告!$A:$A,$N14,[2]业务报告!$B:$B,$P$2) -> 319.89 | H14: {=IFERROR(LOOKUP(1,0/(([2]业务报告!$A:$A=$N14)*([2]业务报告!B:B=$P$2)),[2]业务报告!AG:AG),0)} -> / | I14: {=IFERROR(LOOKUP(1,0/(([2]业务报告!$A:$A=$N14)*([2]业务报告!$B:$B=$P$2)),[2]业务报告!AH:AH),0)} -> 79.99 | J14: =SUMIFS([2]WT报告!A:A,[2]WT报告!$C:$C,$N14,[2]WT报告!$H:$H,$X$2) -> 0 | K14: {=IFERROR(LOOKUP(1,0/(([2]业务报告!$A:$A=$N14)*([2]业务报告!$B:$B=$P$2)),[2]业务报告!AI:AI),0)} -> 0 | L14: {=IFERROR(LOOKUP(1,0/(([2]业务报告!$A:$A=$N14)*([2]业务报告!$B:$B=$P$2)),[2]业务报告!AJ:AJ),0)} -> 0 | M14: =IFERROR("周"&WEEKDAY(N14,2),"-") -> 周3 | N14: =DATE($O$1,$O$2,DAY(N13)+1) -> 45910 | O14: =SUMIFS([2]业务报告!G:G,[2]业务报告!$A:$A,$N14,[2]业务报告!$B:$B,$P$2)+SUMIFS([2]业务报告!G:G,[2]业务报告!$A:$A,$N14,[2]业务报告!$B:$B,$T$2) -> 0 | P14: =SUMIFS([2]业务报告!H:H,[2]业务报告!$A:$A,$N14,[2]业务报告!$B:$B,$P$2)+SUMIFS([2]业务报告!H:H,[2]业务报告!$A:$A,$N14,[2]业务报告!$B:$B,$T$2) -> 0 | Q14: =SUMIFS([2]业务报告!I:I,[2]业务报告!$A:$A,$N14,[2]业务报告!$B:$B,$P$2)+SUMIFS([2]业务报告!I:I,[2]业务报告!$A:$A,$N14,[2]业务报告!$B:$B,$T$2) -> 0 | R14: =SUMIFS([2]业务报告!T:T,[2]业务报告!$A:$A,$N14,[2]业务报告!$B:$B,$P$2)+SUMIFS([2]业务报告!T:T,[2]业务报告!$A:$A,$N14,[2]业务报告!$B:$B,$T$2) -> 0 | S14: =IFERROR((R14+V14)/Q14,0) -> 0 | T14: =SUMIFS([2]业务报告!X:X,[2]业务报告!$A:$A,$N14,[2]业务报告!$B:$B,$P$2)+SUMIFS([2]业务报告!X:X,[2]业务报告!$A:$A,$N14,[2]业务报告!$B:$B,$T$2) -> 0 | U14: =SUMIFS([2]业务报告!AO:AO,[2]业务报告!$A:$A,$N14,[2]业务报告!$B:$B,$P$2)+SUMIFS([2]业务报告!AP:AP,[2]业务报告!$A:$A,$N14,[2]业务报告!$B:$B,$P$2) -> 0 | V14: =SUMIFS([2]WT报告!I:I,[2]WT报告!$C:$C,$N14,[2]WT报告!$H:$H,$X$2) -> 0 | W14: =SUMIFS([2]WT报告!Z:Z,[2]WT报告!$C:$C,$N14,[2]WT报告!$H:$H,$X$2) -> 0 | X14: =SUMIFS([2]业务报告!AS:AS,[2]业务报告!$A:$A,$N14,[2]业务报告!$B:$B,$P$2)+SUMIFS([2]业务报告!AS:AS,[2]业务报告!$A:$A,$N14,[2]业务报告!$B:$B,$T$2)+V14 -> 0 | Y14: =SUMIFS([2]业务报告!AO:AO,[2]业务报告!$A:$A,$N14,[2]业务报告!$B:$B,$P$2)*SUMIFS([2]业务报告!AM:AM,[2]业务报告!$A:$A,$N14,[2]业务报告!$B:$B,$P$2)/$AC$2+SUMIFS([2]业务报告!AP:AP,[2]业务报告!$A:$A,$N14,[2]业务报告!$B:$B,$P$2)*SUMIFS([2]业务报告!AN:AN,[2]业务报告!$A:$A,$N14,[2]业务报告!$B:$B,$P$2)/$AC$2 -> 0 | Z14: =(I14*(1-$AD$2-4%-10%)-$AD$1-$AC$1/$AC$2)*BB14-BC14 -> 0 | AA14: =(I14*(1-$AD$2-4%-10%)-$AD$1-$AC$1/$AC$2)*(R14-IF(R14>V14,SUMIFS([2]业务报告!AO:AO,[2]业务报告!$A:$A,$N14,[2]业务报告!$B:$B,$P$2),0))-BC14 -> 0 | AB14: =IFERROR(AA14/(I14*R14),0) -> 0 | AC14: =AR14*(J14-$AC$1/$AC$2-J14*4%)-AS14 -> 0 | AD14: =(V14-IF(R14<V14,SUMIFS([2]业务报告!AO:AO,[2]业务报告!$A:$A,$N14,[2]业务报告!$B:$B,$P$2),0))*(J14-$AC$1/$AC$2-J14*4%)-AS14 -> 0 | AE14: {=IFERROR(LOOKUP(1,0/(([2]业务报告!$A:$A=$N14)*([2]业务报告!$B:$B=$P$2)),[2]业务报告!AQ:AQ),0)*$AH$2} -> 0 | AF14: {=IFERROR(LOOKUP(1,0/(([2]业务报告!$A:$A=$N14)*([2]业务报告!$B:$B=$P$2)),[2]业务报告!AR:AR),0)*$AG$2} -> 0 | AG14: =AA14+AD14+AE14+AF14-Y14 -> 0 | AH14: =IFERROR((AG14)/(T14+J14*V14),0) -> 0 | AI14: =IFERROR((AG14)/(X14),0) -> 0 | AJ14: =IFERROR(AS14/(V14*J14),0) -> 0 | AK14: =IFERROR(ROUNDUP(AS14/V14,1),0) -> 0 | AL14: =SUMIFS([2]WT报告!S:S,[2]WT报告!$C:$C,$N14,[2]WT报告!$H:$H,$X$2) -> 0 | AM14: =IFERROR((AR14)/AP14,0) -> 0 | AN14: =SUMIFS([2]WT报告!N:N,[2]WT报告!$C:$C,$N14,[2]WT报告!$H:$H,$X$2) -> 0 | AO14: =IFERROR(AR14/(V14),0) -> 0 | AP14: =SUMIFS([2]WT报告!P:P,[2]WT报告!$C:$C,$N14,[2]WT报告!$H:$H,$X$2) -> 0 | AQ14: =SUMIFS([2]WT报告!Q:Q,[2]WT报告!$C:$C,$N14,[2]WT报告!$H:$H,$X$2) -> 0 | AR14: =SUMIFS([2]WT报告!J:J,[2]WT报告!$C:$C,$N14,[2]WT报告!$H:$H,$X$2) -> 0 | AS14: =SUMIFS([2]WT报告!M:M,[2]WT报告!$C:$C,$N14,[2]WT报告!$H:$H,$X$2) -> 0 | AT14: =IFERROR((BO14+BX14+CG14)/(R14*I14),0) -> 0 | AU14: =IFERROR(ROUNDUP(BC14/R14,1),0) -> 0 | AV14: =IFERROR(ROUNDUP(BC14/BB14,1),0) -> 0 | AW14: =IFERROR((BB14)/AZ14,0) -> 0 | AX14: =IFERROR(BC14/AZ14,0) -> 0 | AY14: =IFERROR((BL14+BU14+CD14)/(R14+V14),0) -> 0 | AZ14: =BI14+BR14+CA14 -> 0 | BA14: =IFERROR((BI14+BR14+CA14)/(BH14+BQ14+BZ14),0) -> 0 | BB14: =BL14+BU14+CD14 -> 0 | BC14: =ROUND(BO14+BX14+CG14,2) -> 0 | BD14: =IFERROR(BC14/(BM14+BV14+CE14),0) -> 0 | BE14: =IFERROR(ROUNDUP((BO14+CG14)/BG14,1),0) -> 0 | BF14: =IFERROR(BG14/(BI14+CA14),0) -> 0 | BG14: =BL14+CD14 -> 0 | BH14: =SUMIFS([2]SP!J:J,[2]SP!A:A,N14,[2]SP!H:H,$P$2)+SUMIFS([2]SP!J:J,[2]SP!A:A,N14,[2]SP!H:H,$T$2) -> 0 | BI14: =SUMIFS([2]SP!K:K,[2]SP!A:A,N14,[2]SP!H:H,$P$2)+SUMIFS([2]SP!K:K,[2]SP!A:A,N14,[2]SP!H:H,$T$2) -> 0 | BJ14: =IFERROR(BI14/BH14,0) -> 0 | BK14: =IFERROR(BO14/BI14,0) -> 0 | BL14: =SUMIFS([2]SP!R:R,[2]SP!A:A,N14,[2]SP!H:H,$P$2)+SUMIFS([2]SP!R:R,[2]SP!A:A,N14,[2]SP!H:H,$T$2) -> 0 | BM14: =SUMIFS([2]SP!O:O,[2]SP!A:A,$N14,[2]SP!H:H,$P$2)+SUMIFS([2]SP!O:O,[2]SP!A:A,$N14,[2]SP!H:H,$T$2) -> 0 | BN14: =IFERROR(BL14/BI14,0) -> 0 | BO14: =SUMIFS([2]SP!N:N,[2]SP!A:A,N14,[2]SP!H:H,$P$2)+SUMIFS([2]SP!N:N,[2]SP!A:A,N14,[2]SP!H:H,$T$2) -> 0 | BP14: =IFERROR(BO14/BM14,0) -> 0 | BQ14: =SUMIFS([2]SD!J:J,[2]SD!A:A,N14,[2]SD!H:H,$P$2)+SUMIFS([2]SD!J:J,[2]SD!A:A,N14,[2]SD!H:H,$T$2) -> 0 | BR14: =SUMIFS([2]SD!L:L,[2]SD!A:A,N14,[2]SD!H:H,$P$2)+SUMIFS([2]SD!L:L,[2]SD!A:A,N14,[2]SD!H:H,$T$2) -> 0 | BS14: =IFERROR(BR14/BQ14,0) -> 0 | BT14: =IFERROR(BX14/BR14,0) -> 0 | BU14: =SUMIFS([2]SD!U:U,[2]SD!A:A,N14,[2]SD!H:H,$P$2)+SUMIFS([2]SD!U:U,[2]SD!A:A,N14,[2]SD!H:H,$T$2) -> 0 | BV14: =SUMIFS([2]SD!V:V,[2]SD!A:A,N14,[2]SD!H:H,$P$2)+SUMIFS([2]SD!V:V,[2]SD!A:A,N14,[2]SD!H:H,$T$2) -> 0 | BW14: =IFERROR(BU14/BR14,0) -> 0 | BX14: =SUMIFS([2]SD!O:O,[2]SD!A:A,N14,[2]SD!H:H,$P$2)+SUMIFS([2]SD!O:O,[2]SD!A:A,N14,[2]SD!H:H,$T$2) -> 0 | BY14: =IFERROR(BX14/BV14,0) -> 0 | BZ14: =SUMIFS([2]SB!H:H,[2]SB!B:B,N14,[2]SB!A:A,$P$2)+SUMIFS([2]SB!H:H,[2]SB!B:B,N14,[2]SB!A:A,$T$2) -> 0 | CA14: =SUMIFS([2]SB!I:I,[2]SB!B:B,N14,[2]SB!A:A,$P$2)+SUMIFS([2]SB!I:I,[2]SB!B:B,N14,[2]SB!A:A,$T$2) -> 0 | CB14: =IFERROR(CA14/BZ14,0) -> 0 | CC14: =IFERROR(CG14/CA14,0) -> 0 | CD14: =SUMIFS([2]SB!Q:Q,[2]SB!B:B,N14,[2]SB!A:A,$P$2)+SUMIFS([2]SB!Q:Q,[2]SB!B:B,N14,[2]SB!A:A,$T$2) -> 0 | CE14: =SUMIFS([2]SB!O:O,[2]SB!B:B,N14,[2]SB!A:A,$P$2)+SUMIFS([2]SB!O:O,[2]SB!B:B,N14,[2]SB!A:A,$T$2) -> 0 | CF14: =IFERROR(CD14/CA14,0) -> 0 | CG14: =SUMIFS([2]SB!L:L,[2]SB!B:B,N14,[2]SB!A:A,$P$2)+SUMIFS([2]SB!L:L,[2]SB!B:B,N14,[2]SB!A:A,$T$2) -> 0 | CH14: =IFERROR(CG14/CE14,0) -> 0
A15: {=IFERROR(LOOKUP(1,0/(([2]业务报告!$A:$A=$N15)*([2]业务报告!$B:$B=$P$2)),[2]业务报告!AU:AU),"")} | B15: {=IFERROR(LOOKUP(1,0/(([2]业务报告!$A:$A=$N15)*([2]业务报告!$B:$B=$P$2)),[2]业务报告!AV:AV),"")} | C15: =SUMIFS([2]业务报告!AC:AC,[2]业务报告!$A:$A,$N15,[2]业务报告!$B:$B,$P$2) -> 0 | D15: =SUMIFS([2]业务报告!AD:AD,[2]业务报告!$A:$A,$N15,[2]业务报告!$B:$B,$P$2) -> 0 | E15: {=_xlfn.XLOOKUP($N15&$P$2,[2]业务报告!$A:$A&[2]业务报告!$B:$B,[2]业务报告!AE:AE,"")} | F15: {=IFERROR(LOOKUP(1,0/(([2]业务报告!$A:$A=$N15)*([2]业务报告!$B:$B=$P$2)),[2]业务报告!AK:AK),0)} -> 0 | G15: =SUMIFS([2]业务报告!AF:AF,[2]业务报告!$A:$A,$N15,[2]业务报告!$B:$B,$P$2) -> 0 | H15: {=IFERROR(LOOKUP(1,0/(([2]业务报告!$A:$A=$N15)*([2]业务报告!B:B=$P$2)),[2]业务报告!AG:AG),0)} -> 0 | I15: {=IFERROR(LOOKUP(1,0/(([2]业务报告!$A:$A=$N15)*([2]业务报告!$B:$B=$P$2)),[2]业务报告!AH:AH),0)} -> 0 | J15: =SUMIFS([2]WT报告!A:A,[2]WT报告!$C:$C,$N15,[2]WT报告!$H:$H,$X$2) -> 0 | K15: {=IFERROR(LOOKUP(1,0/(([2]业务报告!$A:$A=$N15)*([2]业务报告!$B:$B=$P$2)),[2]业务报告!AI:AI),0)} -> 0 | L15: {=IFERROR(LOOKUP(1,0/(([2]业务报告!$A:$A=$N15)*([2]业务报告!$B:$B=$P$2)),[2]业务报告!AJ:AJ),0)} -> 0 | M15: =IFERROR("周"&WEEKDAY(N15,2),"-") -> 周4 | N15: =DATE($O$1,$O$2,DAY(N14)+1) -> 45911 | O15: =SUMIFS([2]业务报告!G:G,[2]业务报告!$A:$A,$N15,[2]业务报告!$B:$B,$P$2)+SUMIFS([2]业务报告!G:G,[2]业务报告!$A:$A,$N15,[2]业务报告!$B:$B,$T$2) -> 0 | P15: =SUMIFS([2]业务报告!H:H,[2]业务报告!$A:$A,$N15,[2]业务报告!$B:$B,$P$2)+SUMIFS([2]业务报告!H:H,[2]业务报告!$A:$A,$N15,[2]业务报告!$B:$B,$T$2) -> 0 | Q15: =SUMIFS([2]业务报告!I:I,[2]业务报告!$A:$A,$N15,[2]业务报告!$B:$B,$P$2)+SUMIFS([2]业务报告!I:I,[2]业务报告!$A:$A,$N15,[2]业务报告!$B:$B,$T$2) -> 0 | R15: =SUMIFS([2]业务报告!T:T,[2]业务报告!$A:$A,$N15,[2]业务报告!$B:$B,$P$2)+SUMIFS([2]业务报告!T:T,[2]业务报告!$A:$A,$N15,[2]业务报告!$B:$B,$T$2) -> 0 | S15: =IFERROR((R15+V15)/Q15,0) -> 0 | T15: =SUMIFS([2]业务报告!X:X,[2]业务报告!$A:$A,$N15,[2]业务报告!$B:$B,$P$2)+SUMIFS([2]业务报告!X:X,[2]业务报告!$A:$A,$N15,[2]业务报告!$B:$B,$T$2) -> 0 | U15: =SUMIFS([2]业务报告!AO:AO,[2]业务报告!$A:$A,$N15,[2]业务报告!$B:$B,$P$2)+SUMIFS([2]业务报告!AP:AP,[2]业务报告!$A:$A,$N15,[2]业务报告!$B:$B,$P$2) -> 0 | V15: =SUMIFS([2]WT报告!I:I,[2]WT报告!$C:$C,$N15,[2]WT报告!$H:$H,$X$2) -> 0 | W15: =SUMIFS([2]WT报告!Z:Z,[2]WT报告!$C:$C,$N15,[2]WT报告!$H:$H,$X$2) -> 0 | X15: =SUMIFS([2]业务报告!AS:AS,[2]业务报告!$A:$A,$N15,[2]业务报告!$B:$B,$P$2)+SUMIFS([2]业务报告!AS:AS,[2]业务报告!$A:$A,$N15,[2]业务报告!$B:$B,$T$2)+V15 -> 0 | Y15: =SUMIFS([2]业务报告!AO:AO,[2]业务报告!$A:$A,$N15,[2]业务报告!$B:$B,$P$2)*SUMIFS([2]业务报告!AM:AM,[2]业务报告!$A:$A,$N15,[2]业务报告!$B:$B,$P$2)/$AC$2+SUMIFS([2]业务报告!AP:AP,[2]业务报告!$A:$A,$N15,[2]业务报告!$B:$B,$P$2)*SUMIFS([2]业务报告!AN:AN,[2]业务报告!$A:$A,$N15,[2]业务报告!$B:$B,$P$2)/$AC$2 -> 0 | Z15: =(I15*(1-$AD$2-4%-10%)-$AD$1-$AC$1/$AC$2)*BB15-BC15 -> 0 | AA15: =(I15*(1-$AD$2-4%-10%)-$AD$1-$AC$1/$AC$2)*(R15-IF(R15>V15,SUMIFS([2]业务报告!AO:AO,[2]业务报告!$A:$A,$N15,[2]业务报告!$B:$B,$P$2),0))-BC15 -> 0 | AB15: =IFERROR(AA15/(I15*R15),0) -> 0 | AC15: =AR15*(J15-$AC$1/$AC$2-J15*4%)-AS15 -> 0 | AD15: =(V15-IF(R15<V15,SUMIFS([2]业务报告!AO:AO,[2]业务报告!$A:$A,$N15,[2]业务报告!$B:$B,$P$2),0))*(J15-$AC$1/$AC$2-J15*4%)-AS15 -> 0 | AE15: {=IFERROR(LOOKUP(1,0/(([2]业务报告!$A:$A=$N15)*([2]业务报告!$B:$B=$P$2)),[2]业务报告!AQ:AQ),0)*$AH$2} -> 0 | AF15: {=IFERROR(LOOKUP(1,0/(([2]业务报告!$A:$A=$N15)*([2]业务报告!$B:$B=$P$2)),[2]业务报告!AR:AR),0)*$AG$2} -> 0 | AG15: =AA15+AD15+AE15+AF15-Y15 -> 0 | AH15: =IFERROR((AG15)/(T15+J15*V15),0) -> 0 | AI15: =IFERROR((AG15)/(X15),0) -> 0 | AJ15: =IFERROR(AS15/(V15*J15),0) -> 0 | AK15: =IFERROR(ROUNDUP(AS15/V15,1),0) -> 0 | AL15: =SUMIFS([2]WT报告!S:S,[2]WT报告!$C:$C,$N15,[2]WT报告!$H:$H,$X$2) -> 0 | AM15: =IFERROR((AR15)/AP15,0) -> 0 | AN15: =SUMIFS([2]WT报告!N:N,[2]WT报告!$C:$C,$N15,[2]WT报告!$H:$H,$X$2) -> 0 | AO15: =IFERROR(AR15/(V15),0) -> 0 | AP15: =SUMIFS([2]WT报告!P:P,[2]WT报告!$C:$C,$N15,[2]WT报告!$H:$H,$X$2) -> 0 | AQ15: =SUMIFS([2]WT报告!Q:Q,[2]WT报告!$C:$C,$N15,[2]WT报告!$H:$H,$X$2) -> 0 | AR15: =SUMIFS([2]WT报告!J:J,[2]WT报告!$C:$C,$N15,[2]WT报告!$H:$H,$X$2) -> 0 | AS15: =SUMIFS([2]WT报告!M:M,[2]WT报告!$C:$C,$N15,[2]WT报告!$H:$H,$X$2) -> 0 | AT15: =IFERROR((BO15+BX15+CG15)/(R15*I15),0) -> 0 | AU15: =IFERROR(ROUNDUP(BC15/R15,1),0) -> 0 | AV15: =IFERROR(ROUNDUP(BC15/BB15,1),0) -> 0 | AW15: =IFERROR((BB15)/AZ15,0) -> 0 | AX15: =IFERROR(BC15/AZ15,0) -> 0 | AY15: =IFERROR((BL15+BU15+CD15)/(R15+V15),0) -> 0 | AZ15: =BI15+BR15+CA15 -> 0 | BA15: =IFERROR((BI15+BR15+CA15)/(BH15+BQ15+BZ15),0) -> 0 | BB15: =BL15+BU15+CD15 -> 0 | BC15: =ROUND(BO15+BX15+CG15,2) -> 0 | BD15: =IFERROR(BC15/(BM15+BV15+CE15),0) -> 0 | BE15: =IFERROR(ROUNDUP((BO15+CG15)/BG15,1),0) -> 0 | BF15: =IFERROR(BG15/(BI15+CA15),0) -> 0 | BG15: =BL15+CD15 -> 0 | BH15: =SUMIFS([2]SP!J:J,[2]SP!A:A,N15,[2]SP!H:H,$P$2)+SUMIFS([2]SP!J:J,[2]SP!A:A,N15,[2]SP!H:H,$T$2) -> 0 | BI15: =SUMIFS([2]SP!K:K,[2]SP!A:A,N15,[2]SP!H:H,$P$2)+SUMIFS([2]SP!K:K,[2]SP!A:A,N15,[2]SP!H:H,$T$2) -> 0 | BJ15: =IFERROR(BI15/BH15,0) -> 0 | BK15: =IFERROR(BO15/BI15,0) -> 0 | BL15: =SUMIFS([2]SP!R:R,[2]SP!A:A,N15,[2]SP!H:H,$P$2)+SUMIFS([2]SP!R:R,[2]SP!A:A,N15,[2]SP!H:H,$T$2) -> 0 | BM15: =SUMIFS([2]SP!O:O,[2]SP!A:A,$N15,[2]SP!H:H,$P$2)+SUMIFS([2]SP!O:O,[2]SP!A:A,$N15,[2]SP!H:H,$T$2) -> 0 | BN15: =IFERROR(BL15/BI15,0) -> 0 | BO15: =SUMIFS([2]SP!N:N,[2]SP!A:A,N15,[2]SP!H:H,$P$2)+SUMIFS([2]SP!N:N,[2]SP!A:A,N15,[2]SP!H:H,$T$2) -> 0 | BP15: =IFERROR(BO15/BM15,0) -> 0 | BQ15: =SUMIFS([2]SD!J:J,[2]SD!A:A,N15,[2]SD!H:H,$P$2)+SUMIFS([2]SD!J:J,[2]SD!A:A,N15,[2]SD!H:H,$T$2) -> 0 | BR15: =SUMIFS([2]SD!L:L,[2]SD!A:A,N15,[2]SD!H:H,$P$2)+SUMIFS([2]SD!L:L,[2]SD!A:A,N15,[2]SD!H:H,$T$2) -> 0 | BS15: =IFERROR(BR15/BQ15,0) -> 0 | BT15: =IFERROR(BX15/BR15,0) -> 0 | BU15: =SUMIFS([2]SD!U:U,[2]SD!A:A,N15,[2]SD!H:H,$P$2)+SUMIFS([2]SD!U:U,[2]SD!A:A,N15,[2]SD!H:H,$T$2) -> 0 | BV15: =SUMIFS([2]SD!V:V,[2]SD!A:A,N15,[2]SD!H:H,$P$2)+SUMIFS([2]SD!V:V,[2]SD!A:A,N15,[2]SD!H:H,$T$2) -> 0 | BW15: =IFERROR(BU15/BR15,0) -> 0 | BX15: =SUMIFS([2]SD!O:O,[2]SD!A:A,N15,[2]SD!H:H,$P$2)+SUMIFS([2]SD!O:O,[2]SD!A:A,N15,[2]SD!H:H,$T$2) -> 0 | BY15: =IFERROR(BX15/BV15,0) -> 0 | BZ15: =SUMIFS([2]SB!H:H,[2]SB!B:B,N15,[2]SB!A:A,$P$2)+SUMIFS([2]SB!H:H,[2]SB!B:B,N15,[2]SB!A:A,$T$2) -> 0 | CA15: =SUMIFS([2]SB!I:I,[2]SB!B:B,N15,[2]SB!A:A,$P$2)+SUMIFS([2]SB!I:I,[2]SB!B:B,N15,[2]SB!A:A,$T$2) -> 0 | CB15: =IFERROR(CA15/BZ15,0) -> 0 | CC15: =IFERROR(CG15/CA15,0) -> 0 | CD15: =SUMIFS([2]SB!Q:Q,[2]SB!B:B,N15,[2]SB!A:A,$P$2)+SUMIFS([2]SB!Q:Q,[2]SB!B:B,N15,[2]SB!A:A,$T$2) -> 0 | CE15: =SUMIFS([2]SB!O:O,[2]SB!B:B,N15,[2]SB!A:A,$P$2)+SUMIFS([2]SB!O:O,[2]SB!B:B,N15,[2]SB!A:A,$T$2) -> 0 | CF15: =IFERROR(CD15/CA15,0) -> 0 | CG15: =SUMIFS([2]SB!L:L,[2]SB!B:B,N15,[2]SB!A:A,$P$2)+SUMIFS([2]SB!L:L,[2]SB!B:B,N15,[2]SB!A:A,$T$2) -> 0 | CH15: =IFERROR(CG15/CE15,0) -> 0
A16: {=IFERROR(LOOKUP(1,0/(([2]业务报告!$A:$A=$N16)*([2]业务报告!$B:$B=$P$2)),[2]业务报告!AU:AU),"")} | B16: {=IFERROR(LOOKUP(1,0/(([2]业务报告!$A:$A=$N16)*([2]业务报告!$B:$B=$P$2)),[2]业务报告!AV:AV),"")} | C16: =SUMIFS([2]业务报告!AC:AC,[2]业务报告!$A:$A,$N16,[2]业务报告!$B:$B,$P$2) -> 0 | D16: =SUMIFS([2]业务报告!AD:AD,[2]业务报告!$A:$A,$N16,[2]业务报告!$B:$B,$P$2) -> 0 | E16: {=_xlfn.XLOOKUP($N16&$P$2,[2]业务报告!$A:$A&[2]业务报告!$B:$B,[2]业务报告!AE:AE,"")} | F16: {=IFERROR(LOOKUP(1,0/(([2]业务报告!$A:$A=$N16)*([2]业务报告!$B:$B=$P$2)),[2]业务报告!AK:AK),0)} -> 0 | G16: =SUMIFS([2]业务报告!AF:AF,[2]业务报告!$A:$A,$N16,[2]业务报告!$B:$B,$P$2) -> 0 | H16: {=IFERROR(LOOKUP(1,0/(([2]业务报告!$A:$A=$N16)*([2]业务报告!B:B=$P$2)),[2]业务报告!AG:AG),0)} -> 0 | I16: {=IFERROR(LOOKUP(1,0/(([2]业务报告!$A:$A=$N16)*([2]业务报告!$B:$B=$P$2)),[2]业务报告!AH:AH),0)} -> 0 | J16: =SUMIFS([2]WT报告!A:A,[2]WT报告!$C:$C,$N16,[2]WT报告!$H:$H,$X$2) -> 0 | K16: {=IFERROR(LOOKUP(1,0/(([2]业务报告!$A:$A=$N16)*([2]业务报告!$B:$B=$P$2)),[2]业务报告!AI:AI),0)} -> 0 | L16: {=IFERROR(LOOKUP(1,0/(([2]业务报告!$A:$A=$N16)*([2]业务报告!$B:$B=$P$2)),[2]业务报告!AJ:AJ),0)} -> 0 | M16: =IFERROR("周"&WEEKDAY(N16,2),"-") -> 周5 | N16: =DATE($O$1,$O$2,DAY(N15)+1) -> 45912 | O16: =SUMIFS([2]业务报告!G:G,[2]业务报告!$A:$A,$N16,[2]业务报告!$B:$B,$P$2)+SUMIFS([2]业务报告!G:G,[2]业务报告!$A:$A,$N16,[2]业务报告!$B:$B,$T$2) -> 0 | P16: =SUMIFS([2]业务报告!H:H,[2]业务报告!$A:$A,$N16,[2]业务报告!$B:$B,$P$2)+SUMIFS([2]业务报告!H:H,[2]业务报告!$A:$A,$N16,[2]业务报告!$B:$B,$T$2) -> 0 | Q16: =SUMIFS([2]业务报告!I:I,[2]业务报告!$A:$A,$N16,[2]业务报告!$B:$B,$P$2)+SUMIFS([2]业务报告!I:I,[2]业务报告!$A:$A,$N16,[2]业务报告!$B:$B,$T$2) -> 0 | R16: =SUMIFS([2]业务报告!T:T,[2]业务报告!$A:$A,$N16,[2]业务报告!$B:$B,$P$2)+SUMIFS([2]业务报告!T:T,[2]业务报告!$A:$A,$N16,[2]业务报告!$B:$B,$T$2) -> 0 | S16: =IFERROR((R16+V16)/Q16,0) -> 0 | T16: =SUMIFS([2]业务报告!X:X,[2]业务报告!$A:$A,$N16,[2]业务报告!$B:$B,$P$2)+SUMIFS([2]业务报告!X:X,[2]业务报告!$A:$A,$N16,[2]业务报告!$B:$B,$T$2) -> 0 | U16: =SUMIFS([2]业务报告!AO:AO,[2]业务报告!$A:$A,$N16,[2]业务报告!$B:$B,$P$2)+SUMIFS([2]业务报告!AP:AP,[2]业务报告!$A:$A,$N16,[2]业务报告!$B:$B,$P$2) -> 0 | V16: =SUMIFS([2]WT报告!I:I,[2]WT报告!$C:$C,$N16,[2]WT报告!$H:$H,$X$2) -> 0 | W16: =SUMIFS([2]WT报告!Z:Z,[2]WT报告!$C:$C,$N16,[2]WT报告!$H:$H,$X$2) -> 0 | X16: =SUMIFS([2]业务报告!AS:AS,[2]业务报告!$A:$A,$N16,[2]业务报告!$B:$B,$P$2)+SUMIFS([2]业务报告!AS:AS,[2]业务报告!$A:$A,$N16,[2]业务报告!$B:$B,$T$2)+V16 -> 0 | Y16: =SUMIFS([2]业务报告!AO:AO,[2]业务报告!$A:$A,$N16,[2]业务报告!$B:$B,$P$2)*SUMIFS([2]业务报告!AM:AM,[2]业务报告!$A:$A,$N16,[2]业务报告!$B:$B,$P$2)/$AC$2+SUMIFS([2]业务报告!AP:AP,[2]业务报告!$A:$A,$N16,[2]业务报告!$B:$B,$P$2)*SUMIFS([2]业务报告!AN:AN,[2]业务报告!$A:$A,$N16,[2]业务报告!$B:$B,$P$2)/$AC$2 -> 0 | Z16: =(I16*(1-$AD$2-4%-10%)-$AD$1-$AC$1/$AC$2)*BB16-BC16 -> 0 | AA16: =(I16*(1-$AD$2-4%-10%)-$AD$1-$AC$1/$AC$2)*(R16-IF(R16>V16,SUMIFS([2]业务报告!AO:AO,[2]业务报告!$A:$A,$N16,[2]业务报告!$B:$B,$P$2),0))-BC16 -> 0 | AB16: =IFERROR(AA16/(I16*R16),0) -> 0 | AC16: =AR16*(J16-$AC$1/$AC$2-J16*4%)-AS16 -> 0 | AD16: =(V16-IF(R16<V16,SUMIFS([2]业务报告!AO:AO,[2]业务报告!$A:$A,$N16,[2]业务报告!$B:$B,$P$2),0))*(J16-$AC$1/$AC$2-J16*4%)-AS16 -> 0 | AE16: {=IFERROR(LOOKUP(1,0/(([2]业务报告!$A:$A=$N16)*([2]业务报告!$B:$B=$P$2)),[2]业务报告!AQ:AQ),0)*$AH$2} -> 0 | AF16: {=IFERROR(LOOKUP(1,0/(([2]业务报告!$A:$A=$N16)*([2]业务报告!$B:$B=$P$2)),[2]业务报告!AR:AR),0)*$AG$2} -> 0 | AG16: =AA16+AD16+AE16+AF16-Y16 -> 0 | AH16: =IFERROR((AG16)/(T16+J16*V16),0) -> 0 | AI16: =IFERROR((AG16)/(X16),0) -> 0 | AJ16: =IFERROR(AS16/(V16*J16),0) -> 0 | AK16: =IFERROR(ROUNDUP(AS16/V16,1),0) -> 0 | AL16: =SUMIFS([2]WT报告!S:S,[2]WT报告!$C:$C,$N16,[2]WT报告!$H:$H,$X$2) -> 0 | AM16: =IFERROR((AR16)/AP16,0) -> 0 | AN16: =SUMIFS([2]WT报告!N:N,[2]WT报告!$C:$C,$N16,[2]WT报告!$H:$H,$X$2) -> 0 | AO16: =IFERROR(AR16/(V16),0) -> 0 | AP16: =SUMIFS([2]WT报告!P:P,[2]WT报告!$C:$C,$N16,[2]WT报告!$H:$H,$X$2) -> 0 | AQ16: =SUMIFS([2]WT报告!Q:Q,[2]WT报告!$C:$C,$N16,[2]WT报告!$H:$H,$X$2) -> 0 | AR16: =SUMIFS([2]WT报告!J:J,[2]WT报告!$C:$C,$N16,[2]WT报告!$H:$H,$X$2) -> 0 | AS16: =SUMIFS([2]WT报告!M:M,[2]WT报告!$C:$C,$N16,[2]WT报告!$H:$H,$X$2) -> 0 | AT16: =IFERROR((BO16+BX16+CG16)/(R16*I16),0) -> 0 | AU16: =IFERROR(ROUNDUP(BC16/R16,1),0) -> 0 | AV16: =IFERROR(ROUNDUP(BC16/BB16,1),0) -> 0 | AW16: =IFERROR((BB16)/AZ16,0) -> 0 | AX16: =IFERROR(BC16/AZ16,0) -> 0 | AY16: =IFERROR((BL16+BU16+CD16)/(R16+V16),0) -> 0 | AZ16: =BI16+BR16+CA16 -> 0 | BA16: =IFERROR((BI16+BR16+CA16)/(BH16+BQ16+BZ16),0) -> 0 | BB16: =BL16+BU16+CD16 -> 0 | BC16: =ROUND(BO16+BX16+CG16,2) -> 0 | BD16: =IFERROR(BC16/(BM16+BV16+CE16),0) -> 0 | BE16: =IFERROR(ROUNDUP((BO16+CG16)/BG16,1),0) -> 0 | BF16: =IFERROR(BG16/(BI16+CA16),0) -> 0 | BG16: =BL16+CD16 -> 0 | BH16: =SUMIFS([2]SP!J:J,[2]SP!A:A,N16,[2]SP!H:H,$P$2)+SUMIFS([2]SP!J:J,[2]SP!A:A,N16,[2]SP!H:H,$T$2) -> 0 | BI16: =SUMIFS([2]SP!K:K,[2]SP!A:A,N16,[2]SP!H:H,$P$2)+SUMIFS([2]SP!K:K,[2]SP!A:A,N16,[2]SP!H:H,$T$2) -> 0 | BJ16: =IFERROR(BI16/BH16,0) -> 0 | BK16: =IFERROR(BO16/BI16,0) -> 0 | BL16: =SUMIFS([2]SP!R:R,[2]SP!A:A,N16,[2]SP!H:H,$P$2)+SUMIFS([2]SP!R:R,[2]SP!A:A,N16,[2]SP!H:H,$T$2) -> 0 | BM16: =SUMIFS([2]SP!O:O,[2]SP!A:A,$N16,[2]SP!H:H,$P$2)+SUMIFS([2]SP!O:O,[2]SP!A:A,$N16,[2]SP!H:H,$T$2) -> 0 | BN16: =IFERROR(BL16/BI16,0) -> 0 | BO16: =SUMIFS([2]SP!N:N,[2]SP!A:A,N16,[2]SP!H:H,$P$2)+SUMIFS([2]SP!N:N,[2]SP!A:A,N16,[2]SP!H:H,$T$2) -> 0 | BP16: =IFERROR(BO16/BM16,0) -> 0 | BQ16: =SUMIFS([2]SD!J:J,[2]SD!A:A,N16,[2]SD!H:H,$P$2)+SUMIFS([2]SD!J:J,[2]SD!A:A,N16,[2]SD!H:H,$T$2) -> 0 | BR16: =SUMIFS([2]SD!L:L,[2]SD!A:A,N16,[2]SD!H:H,$P$2)+SUMIFS([2]SD!L:L,[2]SD!A:A,N16,[2]SD!H:H,$T$2) -> 0 | BS16: =IFERROR(BR16/BQ16,0) -> 0 | BT16: =IFERROR(BX16/BR16,0) -> 0 | BU16: =SUMIFS([2]SD!U:U,[2]SD!A:A,N16,[2]SD!H:H,$P$2)+SUMIFS([2]SD!U:U,[2]SD!A:A,N16,[2]SD!H:H,$T$2) -> 0 | BV16: =SUMIFS([2]SD!V:V,[2]SD!A:A,N16,[2]SD!H:H,$P$2)+SUMIFS([2]SD!V:V,[2]SD!A:A,N16,[2]SD!H:H,$T$2) -> 0 | BW16: =IFERROR(BU16/BR16,0) -> 0 | BX16: =SUMIFS([2]SD!O:O,[2]SD!A:A,N16,[2]SD!H:H,$P$2)+SUMIFS([2]SD!O:O,[2]SD!A:A,N16,[2]SD!H:H,$T$2) -> 0 | BY16: =IFERROR(BX16/BV16,0) -> 0 | BZ16: =SUMIFS([2]SB!H:H,[2]SB!B:B,N16,[2]SB!A:A,$P$2)+SUMIFS([2]SB!H:H,[2]SB!B:B,N16,[2]SB!A:A,$T$2) -> 0 | CA16: =SUMIFS([2]SB!I:I,[2]SB!B:B,N16,[2]SB!A:A,$P$2)+SUMIFS([2]SB!I:I,[2]SB!B:B,N16,[2]SB!A:A,$T$2) -> 0 | CB16: =IFERROR(CA16/BZ16,0) -> 0 | CC16: =IFERROR(CG16/CA16,0) -> 0 | CD16: =SUMIFS([2]SB!Q:Q,[2]SB!B:B,N16,[2]SB!A:A,$P$2)+SUMIFS([2]SB!Q:Q,[2]SB!B:B,N16,[2]SB!A:A,$T$2) -> 0 | CE16: =SUMIFS([2]SB!O:O,[2]SB!B:B,N16,[2]SB!A:A,$P$2)+SUMIFS([2]SB!O:O,[2]SB!B:B,N16,[2]SB!A:A,$T$2) -> 0 | CF16: =IFERROR(CD16/CA16,0) -> 0 | CG16: =SUMIFS([2]SB!L:L,[2]SB!B:B,N16,[2]SB!A:A,$P$2)+SUMIFS([2]SB!L:L,[2]SB!B:B,N16,[2]SB!A:A,$T$2) -> 0 | CH16: =IFERROR(CG16/CE16,0) -> 0
A17: {=IFERROR(LOOKUP(1,0/(([2]业务报告!$A:$A=$N17)*([2]业务报告!$B:$B=$P$2)),[2]业务报告!AU:AU),"")} | B17: {=IFERROR(LOOKUP(1,0/(([2]业务报告!$A:$A=$N17)*([2]业务报告!$B:$B=$P$2)),[2]业务报告!AV:AV),"")} | C17: =SUMIFS([2]业务报告!AC:AC,[2]业务报告!$A:$A,$N17,[2]业务报告!$B:$B,$P$2) -> 0 | D17: =SUMIFS([2]业务报告!AD:AD,[2]业务报告!$A:$A,$N17,[2]业务报告!$B:$B,$P$2) -> 0 | E17: {=_xlfn.XLOOKUP($N17&$P$2,[2]业务报告!$A:$A&[2]业务报告!$B:$B,[2]业务报告!AE:AE,"")} | F17: {=IFERROR(LOOKUP(1,0/(([2]业务报告!$A:$A=$N17)*([2]业务报告!$B:$B=$P$2)),[2]业务报告!AK:AK),0)} -> 0 | G17: =SUMIFS([2]业务报告!AF:AF,[2]业务报告!$A:$A,$N17,[2]业务报告!$B:$B,$P$2) -> 0 | H17: {=IFERROR(LOOKUP(1,0/(([2]业务报告!$A:$A=$N17)*([2]业务报告!B:B=$P$2)),[2]业务报告!AG:AG),0)} -> 0 | I17: {=IFERROR(LOOKUP(1,0/(([2]业务报告!$A:$A=$N17)*([2]业务报告!$B:$B=$P$2)),[2]业务报告!AH:AH),0)} -> 0 | J17: =SUMIFS([2]WT报告!A:A,[2]WT报告!$C:$C,$N17,[2]WT报告!$H:$H,$X$2) -> 0 | K17: {=IFERROR(LOOKUP(1,0/(([2]业务报告!$A:$A=$N17)*([2]业务报告!$B:$B=$P$2)),[2]业务报告!AI:AI),0)} -> 0 | L17: {=IFERROR(LOOKUP(1,0/(([2]业务报告!$A:$A=$N17)*([2]业务报告!$B:$B=$P$2)),[2]业务报告!AJ:AJ),0)} -> 0 | M17: =IFERROR("周"&WEEKDAY(N17,2),"-") -> 周6 | N17: =DATE($O$1,$O$2,DAY(N16)+1) -> 45913 | O17: =SUMIFS([2]业务报告!G:G,[2]业务报告!$A:$A,$N17,[2]业务报告!$B:$B,$P$2)+SUMIFS([2]业务报告!G:G,[2]业务报告!$A:$A,$N17,[2]业务报告!$B:$B,$T$2) -> 0 | P17: =SUMIFS([2]业务报告!H:H,[2]业务报告!$A:$A,$N17,[2]业务报告!$B:$B,$P$2)+SUMIFS([2]业务报告!H:H,[2]业务报告!$A:$A,$N17,[2]业务报告!$B:$B,$T$2) -> 0 | Q17: =SUMIFS([2]业务报告!I:I,[2]业务报告!$A:$A,$N17,[2]业务报告!$B:$B,$P$2)+SUMIFS([2]业务报告!I:I,[2]业务报告!$A:$A,$N17,[2]业务报告!$B:$B,$T$2) -> 0 | R17: =SUMIFS([2]业务报告!T:T,[2]业务报告!$A:$A,$N17,[2]业务报告!$B:$B,$P$2)+SUMIFS([2]业务报告!T:T,[2]业务报告!$A:$A,$N17,[2]业务报告!$B:$B,$T$2) -> 0 | S17: =IFERROR((R17+V17)/Q17,0) -> 0 | T17: =SUMIFS([2]业务报告!X:X,[2]业务报告!$A:$A,$N17,[2]业务报告!$B:$B,$P$2)+SUMIFS([2]业务报告!X:X,[2]业务报告!$A:$A,$N17,[2]业务报告!$B:$B,$T$2) -> 0 | U17: =SUMIFS([2]业务报告!AO:AO,[2]业务报告!$A:$A,$N17,[2]业务报告!$B:$B,$P$2)+SUMIFS([2]业务报告!AP:AP,[2]业务报告!$A:$A,$N17,[2]业务报告!$B:$B,$P$2) -> 0 | V17: =SUMIFS([2]WT报告!I:I,[2]WT报告!$C:$C,$N17,[2]WT报告!$H:$H,$X$2) -> 0 | W17: =SUMIFS([2]WT报告!Z:Z,[2]WT报告!$C:$C,$N17,[2]WT报告!$H:$H,$X$2) -> 0 | X17: =SUMIFS([2]业务报告!AS:AS,[2]业务报告!$A:$A,$N17,[2]业务报告!$B:$B,$P$2)+SUMIFS([2]业务报告!AS:AS,[2]业务报告!$A:$A,$N17,[2]业务报告!$B:$B,$T$2)+V17 -> 0 | Y17: =SUMIFS([2]业务报告!AO:AO,[2]业务报告!$A:$A,$N17,[2]业务报告!$B:$B,$P$2)*SUMIFS([2]业务报告!AM:AM,[2]业务报告!$A:$A,$N17,[2]业务报告!$B:$B,$P$2)/$AC$2+SUMIFS([2]业务报告!AP:AP,[2]业务报告!$A:$A,$N17,[2]业务报告!$B:$B,$P$2)*SUMIFS([2]业务报告!AN:AN,[2]业务报告!$A:$A,$N17,[2]业务报告!$B:$B,$P$2)/$AC$2 -> 0 | Z17: =(I17*(1-$AD$2-4%-10%)-$AD$1-$AC$1/$AC$2)*BB17-BC17 -> 0 | AA17: =(I17*(1-$AD$2-4%-10%)-$AD$1-$AC$1/$AC$2)*(R17-IF(R17>V17,SUMIFS([2]业务报告!AO:AO,[2]业务报告!$A:$A,$N17,[2]业务报告!$B:$B,$P$2),0))-BC17 -> 0 | AB17: =IFERROR(AA17/(I17*R17),0) -> 0 | AC17: =AR17*(J17-$AC$1/$AC$2-J17*4%)-AS17 -> 0 | AD17: =(V17-IF(R17<V17,SUMIFS([2]业务报告!AO:AO,[2]业务报告!$A:$A,$N17,[2]业务报告!$B:$B,$P$2),0))*(J17-$AC$1/$AC$2-J17*4%)-AS17 -> 0 | AE17: {=IFERROR(LOOKUP(1,0/(([2]业务报告!$A:$A=$N17)*([2]业务报告!$B:$B=$P$2)),[2]业务报告!AQ:AQ),0)*$AH$2} -> 0 | AF17: {=IFERROR(LOOKUP(1,0/(([2]业务报告!$A:$A=$N17)*([2]业务报告!$B:$B=$P$2)),[2]业务报告!AR:AR),0)*$AG$2} -> 0 | AG17: =AA17+AD17+AE17+AF17-Y17 -> 0 | AH17: =IFERROR((AG17)/(T17+J17*V17),0) -> 0 | AI17: =IFERROR((AG17)/(X17),0) -> 0 | AJ17: =IFERROR(AS17/(V17*J17),0) -> 0 | AK17: =IFERROR(ROUNDUP(AS17/V17,1),0) -> 0 | AL17: =SUMIFS([2]WT报告!S:S,[2]WT报告!$C:$C,$N17,[2]WT报告!$H:$H,$X$2) -> 0 | AM17: =IFERROR((AR17)/AP17,0) -> 0 | AN17: =SUMIFS([2]WT报告!N:N,[2]WT报告!$C:$C,$N17,[2]WT报告!$H:$H,$X$2) -> 0 | AO17: =IFERROR(AR17/(V17),0) -> 0 | AP17: =SUMIFS([2]WT报告!P:P,[2]WT报告!$C:$C,$N17,[2]WT报告!$H:$H,$X$2) -> 0 | AQ17: =SUMIFS([2]WT报告!Q:Q,[2]WT报告!$C:$C,$N17,[2]WT报告!$H:$H,$X$2) -> 0 | AR17: =SUMIFS([2]WT报告!J:J,[2]WT报告!$C:$C,$N17,[2]WT报告!$H:$H,$X$2) -> 0 | AS17: =SUMIFS([2]WT报告!M:M,[2]WT报告!$C:$C,$N17,[2]WT报告!$H:$H,$X$2) -> 0 | AT17: =IFERROR((BO17+BX17+CG17)/(R17*I17),0) -> 0 | AU17: =IFERROR(ROUNDUP(BC17/R17,1),0) -> 0 | AV17: =IFERROR(ROUNDUP(BC17/BB17,1),0) -> 0 | AW17: =IFERROR((BB17)/AZ17,0) -> 0 | AX17: =IFERROR(BC17/AZ17,0) -> 0 | AY17: =IFERROR((BL17+BU17+CD17)/(R17+V17),0) -> 0 | AZ17: =BI17+BR17+CA17 -> 0 | BA17: =IFERROR((BI17+BR17+CA17)/(BH17+BQ17+BZ17),0) -> 0 | BB17: =BL17+BU17+CD17 -> 0 | BC17: =ROUND(BO17+BX17+CG17,2) -> 0 | BD17: =IFERROR(BC17/(BM17+BV17+CE17),0) -> 0 | BE17: =IFERROR(ROUNDUP((BO17+CG17)/BG17,1),0) -> 0 | BF17: =IFERROR(BG17/(BI17+CA17),0) -> 0 | BG17: =BL17+CD17 -> 0 | BH17: =SUMIFS([2]SP!J:J,[2]SP!A:A,N17,[2]SP!H:H,$P$2)+SUMIFS([2]SP!J:J,[2]SP!A:A,N17,[2]SP!H:H,$T$2) -> 0 | BI17: =SUMIFS([2]SP!K:K,[2]SP!A:A,N17,[2]SP!H:H,$P$2)+SUMIFS([2]SP!K:K,[2]SP!A:A,N17,[2]SP!H:H,$T$2) -> 0 | BJ17: =IFERROR(BI17/BH17,0) -> 0 | BK17: =IFERROR(BO17/BI17,0) -> 0 | BL17: =SUMIFS([2]SP!R:R,[2]SP!A:A,N17,[2]SP!H:H,$P$2)+SUMIFS([2]SP!R:R,[2]SP!A:A,N17,[2]SP!H:H,$T$2) -> 0 | BM17: =SUMIFS([2]SP!O:O,[2]SP!A:A,$N17,[2]SP!H:H,$P$2)+SUMIFS([2]SP!O:O,[2]SP!A:A,$N17,[2]SP!H:H,$T$2) -> 0 | BN17: =IFERROR(BL17/BI17,0) -> 0 | BO17: =SUMIFS([2]SP!N:N,[2]SP!A:A,N17,[2]SP!H:H,$P$2)+SUMIFS([2]SP!N:N,[2]SP!A:A,N17,[2]SP!H:H,$T$2) -> 0 | BP17: =IFERROR(BO17/BM17,0) -> 0 | BQ17: =SUMIFS([2]SD!J:J,[2]SD!A:A,N17,[2]SD!H:H,$P$2)+SUMIFS([2]SD!J:J,[2]SD!A:A,N17,[2]SD!H:H,$T$2) -> 0 | BR17: =SUMIFS([2]SD!L:L,[2]SD!A:A,N17,[2]SD!H:H,$P$2)+SUMIFS([2]SD!L:L,[2]SD!A:A,N17,[2]SD!H:H,$T$2) -> 0 | BS17: =IFERROR(BR17/BQ17,0) -> 0 | BT17: =IFERROR(BX17/BR17,0) -> 0 | BU17: =SUMIFS([2]SD!U:U,[2]SD!A:A,N17,[2]SD!H:H,$P$2)+SUMIFS([2]SD!U:U,[2]SD!A:A,N17,[2]SD!H:H,$T$2) -> 0 | BV17: =SUMIFS([2]SD!V:V,[2]SD!A:A,N17,[2]SD!H:H,$P$2)+SUMIFS([2]SD!V:V,[2]SD!A:A,N17,[2]SD!H:H,$T$2) -> 0 | BW17: =IFERROR(BU17/BR17,0) -> 0 | BX17: =SUMIFS([2]SD!O:O,[2]SD!A:A,N17,[2]SD!H:H,$P$2)+SUMIFS([2]SD!O:O,[2]SD!A:A,N17,[2]SD!H:H,$T$2) -> 0 | BY17: =IFERROR(BX17/BV17,0) -> 0 | BZ17: =SUMIFS([2]SB!H:H,[2]SB!B:B,N17,[2]SB!A:A,$P$2)+SUMIFS([2]SB!H:H,[2]SB!B:B,N17,[2]SB!A:A,$T$2) -> 0 | CA17: =SUMIFS([2]SB!I:I,[2]SB!B:B,N17,[2]SB!A:A,$P$2)+SUMIFS([2]SB!I:I,[2]SB!B:B,N17,[2]SB!A:A,$T$2) -> 0 | CB17: =IFERROR(CA17/BZ17,0) -> 0 | CC17: =IFERROR(CG17/CA17,0) -> 0 | CD17: =SUMIFS([2]SB!Q:Q,[2]SB!B:B,N17,[2]SB!A:A,$P$2)+SUMIFS([2]SB!Q:Q,[2]SB!B:B,N17,[2]SB!A:A,$T$2) -> 0 | CE17: =SUMIFS([2]SB!O:O,[2]SB!B:B,N17,[2]SB!A:A,$P$2)+SUMIFS([2]SB!O:O,[2]SB!B:B,N17,[2]SB!A:A,$T$2) -> 0 | CF17: =IFERROR(CD17/CA17,0) -> 0 | CG17: =SUMIFS([2]SB!L:L,[2]SB!B:B,N17,[2]SB!A:A,$P$2)+SUMIFS([2]SB!L:L,[2]SB!B:B,N17,[2]SB!A:A,$T$2) -> 0 | CH17: =IFERROR(CG17/CE17,0) -> 0
... A32: {=IFERROR(LOOKUP(1,0/(([2]业务报告!$A:$A=$N32)*([2]业务报告!$B:$B=$P$2)),[2]业务报告!AU:AU),"")} | B32: {=IFERROR(LOOKUP(1,0/(([2]业务报告!$A:$A=$N32)*([2]业务报告!$B:$B=$P$2)),[2]业务报告!AV:AV),"")} | C32: =SUMIFS([2]业务报告!AC:AC,[2]业务报告!$A:$A,$N32,[2]业务报告!$B:$B,$P$2) -> 0 | D32: =SUMIFS([2]业务报告!AD:AD,[2]业务报告!$A:$A,$N32,[2]业务报告!$B:$B,$P$2) -> 0 | E32: {=_xlfn.XLOOKUP($N32&$P$2,[2]业务报告!$A:$A&[2]业务报告!$B:$B,[2]业务报告!AE:AE,"")} | F32: {=IFERROR(LOOKUP(1,0/(([2]业务报告!$A:$A=$N32)*([2]业务报告!$B:$B=$P$2)),[2]业务报告!AK:AK),0)} -> 0 | G32: =SUMIFS([2]业务报告!AF:AF,[2]业务报告!$A:$A,$N32,[2]业务报告!$B:$B,$P$2) -> 0 | H32: {=IFERROR(LOOKUP(1,0/(([2]业务报告!$A:$A=$N32)*([2]业务报告!B:B=$P$2)),[2]业务报告!AG:AG),0)} -> 0 | I32: {=IFERROR(LOOKUP(1,0/(([2]业务报告!$A:$A=$N32)*([2]业务报告!$B:$B=$P$2)),[2]业务报告!AH:AH),0)} -> 0 | J32: =SUMIFS([2]WT报告!A:A,[2]WT报告!$C:$C,$N32,[2]WT报告!$H:$H,$X$2) -> 0 | K32: {=IFERROR(LOOKUP(1,0/(([2]业务报告!$A:$A=$N32)*([2]业务报告!$B:$B=$P$2)),[2]业务报告!AI:AI),0)} -> 0 | L32: {=IFERROR(LOOKUP(1,0/(([2]业务报告!$A:$A=$N32)*([2]业务报告!$B:$B=$P$2)),[2]业务报告!AJ:AJ),0)} -> 0 | M32: =IFERROR("周"&WEEKDAY(N32,2),"-") -> 周7 | N32: =DATE($O$1,$O$2,DAY(N31)+1) -> 45928 | O32: =SUMIFS([2]业务报告!G:G,[2]业务报告!$A:$A,$N32,[2]业务报告!$B:$B,$P$2)+SUMIFS([2]业务报告!G:G,[2]业务报告!$A:$A,$N32,[2]业务报告!$B:$B,$T$2) -> 0 | P32: =SUMIFS([2]业务报告!H:H,[2]业务报告!$A:$A,$N32,[2]业务报告!$B:$B,$P$2)+SUMIFS([2]业务报告!H:H,[2]业务报告!$A:$A,$N32,[2]业务报告!$B:$B,$T$2) -> 0 | Q32: =SUMIFS([2]业务报告!I:I,[2]业务报告!$A:$A,$N32,[2]业务报告!$B:$B,$P$2)+SUMIFS([2]业务报告!I:I,[2]业务报告!$A:$A,$N32,[2]业务报告!$B:$B,$T$2) -> 0 | R32: =SUMIFS([2]业务报告!T:T,[2]业务报告!$A:$A,$N32,[2]业务报告!$B:$B,$P$2)+SUMIFS([2]业务报告!T:T,[2]业务报告!$A:$A,$N32,[2]业务报告!$B:$B,$T$2) -> 0 | S32: =IFERROR((R32+V32)/Q32,0) -> 0 | T32: =SUMIFS([2]业务报告!X:X,[2]业务报告!$A:$A,$N32,[2]业务报告!$B:$B,$P$2)+SUMIFS([2]业务报告!X:X,[2]业务报告!$A:$A,$N32,[2]业务报告!$B:$B,$T$2) -> 0 | U32: =SUMIFS([2]业务报告!AO:AO,[2]业务报告!$A:$A,$N32,[2]业务报告!$B:$B,$P$2)+SUMIFS([2]业务报告!AP:AP,[2]业务报告!$A:$A,$N32,[2]业务报告!$B:$B,$P$2) -> 0 | V32: =SUMIFS([2]WT报告!I:I,[2]WT报告!$C:$C,$N32,[2]WT报告!$H:$H,$X$2) -> 0 | W32: =SUMIFS([2]WT报告!Z:Z,[2]WT报告!$C:$C,$N32,[2]WT报告!$H:$H,$X$2) -> 0 | X32: =SUMIFS([2]业务报告!AS:AS,[2]业务报告!$A:$A,$N32,[2]业务报告!$B:$B,$P$2)+SUMIFS([2]业务报告!AS:AS,[2]业务报告!$A:$A,$N32,[2]业务报告!$B:$B,$T$2)+V32 -> 0 | Y32: =SUMIFS([2]业务报告!AO:AO,[2]业务报告!$A:$A,$N32,[2]业务报告!$B:$B,$P$2)*SUMIFS([2]业务报告!AM:AM,[2]业务报告!$A:$A,$N32,[2]业务报告!$B:$B,$P$2)/$AC$2+SUMIFS([2]业务报告!AP:AP,[2]业务报告!$A:$A,$N32,[2]业务报告!$B:$B,$P$2)*SUMIFS([2]业务报告!AN:AN,[2]业务报告!$A:$A,$N32,[2]业务报告!$B:$B,$P$2)/$AC$2 -> 0 | Z32: =(I32*(1-$AD$2-4%-10%)-$AD$1-$AC$1/$AC$2)*BB32-BC32 -> 0 | AA32: =(I32*(1-$AD$2-4%-10%)-$AD$1-$AC$1/$AC$2)*(R32-IF(R32>V32,SUMIFS([2]业务报告!AO:AO,[2]业务报告!$A:$A,$N32,[2]业务报告!$B:$B,$P$2),0))-BC32 -> 0 | AB32: =IFERROR(AA32/(I32*R32),0) -> 0 | AC32: =AR32*(J32-$AC$1/$AC$2-J32*4%)-AS32 -> 0 | AD32: =(V32-IF(R32<V32,SUMIFS([2]业务报告!AO:AO,[2]业务报告!$A:$A,$N32,[2]业务报告!$B:$B,$P$2),0))*(J32-$AC$1/$AC$2-J32*4%)-AS32 -> 0 | AE32: {=IFERROR(LOOKUP(1,0/(([2]业务报告!$A:$A=$N32)*([2]业务报告!$B:$B=$P$2)),[2]业务报告!AQ:AQ),0)*$AH$2} -> 0 | AF32: {=IFERROR(LOOKUP(1,0/(([2]业务报告!$A:$A=$N32)*([2]业务报告!$B:$B=$P$2)),[2]业务报告!AR:AR),0)*$AG$2} -> 0 | AG32: =AA32+AD32+AE32+AF32-Y32 -> 0 | AH32: =IFERROR((AG32)/(T32+J32*V32),0) -> 0 | AI32: =IFERROR((AG32)/(X32),0) -> 0 | AJ32: =IFERROR(AS32/(V32*J32),0) -> 0 | AK32: =IFERROR(ROUNDUP(AS32/V32,1),0) -> 0 | AL32: =SUMIFS([2]WT报告!S:S,[2]WT报告!$C:$C,$N32,[2]WT报告!$H:$H,$X$2) -> 0 | AM32: =IFERROR((AR32)/AP32,0) -> 0 | AN32: =SUMIFS([2]WT报告!N:N,[2]WT报告!$C:$C,$N32,[2]WT报告!$H:$H,$X$2) -> 0 | AO32: =IFERROR(AR32/(V32),0) -> 0 | AP32: =SUMIFS([2]WT报告!P:P,[2]WT报告!$C:$C,$N32,[2]WT报告!$H:$H,$X$2) -> 0 | AQ32: =SUMIFS([2]WT报告!Q:Q,[2]WT报告!$C:$C,$N32,[2]WT报告!$H:$H,$X$2) -> 0 | AR32: =SUMIFS([2]WT报告!J:J,[2]WT报告!$C:$C,$N32,[2]WT报告!$H:$H,$X$2) -> 0 | AS32: =SUMIFS([2]WT报告!M:M,[2]WT报告!$C:$C,$N32,[2]WT报告!$H:$H,$X$2) -> 0 | AT32: =IFERROR((BO32+BX32+CG32)/(R32*I32),0) -> 0 | AU32: =IFERROR(ROUNDUP(BC32/R32,1),0) -> 0 | AV32: =IFERROR(ROUNDUP(BC32/BB32,1),0) -> 0 | AW32: =IFERROR((BB32)/AZ32,0) -> 0 | AX32: =IFERROR(BC32/AZ32,0) -> 0 | AY32: =IFERROR((BL32+BU32+CD32)/(R32+V32),0) -> 0 | AZ32: =BI32+BR32+CA32 -> 0 | BA32: =IFERROR((BI32+BR32+CA32)/(BH32+BQ32+BZ32),0) -> 0 | BB32: =BL32+BU32+CD32 -> 0 | BC32: =ROUND(BO32+BX32+CG32,2) -> 0 | BD32: =IFERROR(BC32/(BM32+BV32+CE32),0) -> 0 | BE32: =IFERROR(ROUNDUP((BO32+CG32)/BG32,1),0) -> 0 | BF32: =IFERROR(BG32/(BI32+CA32),0) -> 0 | BG32: =BL32+CD32 -> 0 | BH32: =SUMIFS([2]SP!J:J,[2]SP!A:A,N32,[2]SP!H:H,$P$2)+SUMIFS([2]SP!J:J,[2]SP!A:A,N32,[2]SP!H:H,$T$2) -> 0 | BI32: =SUMIFS([2]SP!K:K,[2]SP!A:A,N32,[2]SP!H:H,$P$2)+SUMIFS([2]SP!K:K,[2]SP!A:A,N32,[2]SP!H:H,$T$2) -> 0 | BJ32: =IFERROR(BI32/BH32,0) -> 0 | BK32: =IFERROR(BO32/BI32,0) -> 0 | BL32: =SUMIFS([2]SP!R:R,[2]SP!A:A,N32,[2]SP!H:H,$P$2)+SUMIFS([2]SP!R:R,[2]SP!A:A,N32,[2]SP!H:H,$T$2) -> 0 | BM32: =SUMIFS([2]SP!O:O,[2]SP!A:A,$N32,[2]SP!H:H,$P$2)+SUMIFS([2]SP!O:O,[2]SP!A:A,$N32,[2]SP!H:H,$T$2) -> 0 | BN32: =IFERROR(BL32/BI32,0) -> 0 | BO32: =SUMIFS([2]SP!N:N,[2]SP!A:A,N32,[2]SP!H:H,$P$2)+SUMIFS([2]SP!N:N,[2]SP!A:A,N32,[2]SP!H:H,$T$2) -> 0 | BP32: =IFERROR(BO32/BM32,0) -> 0 | BQ32: =SUMIFS([2]SD!J:J,[2]SD!A:A,N32,[2]SD!H:H,$P$2)+SUMIFS([2]SD!J:J,[2]SD!A:A,N32,[2]SD!H:H,$T$2) -> 0 | BR32: =SUMIFS([2]SD!L:L,[2]SD!A:A,N32,[2]SD!H:H,$P$2)+SUMIFS([2]SD!L:L,[2]SD!A:A,N32,[2]SD!H:H,$T$2) -> 0 | BS32: =IFERROR(BR32/BQ32,0) -> 0 | BT32: =IFERROR(BX32/BR32,0) -> 0 | BU32: =SUMIFS([2]SD!U:U,[2]SD!A:A,N32,[2]SD!H:H,$P$2)+SUMIFS([2]SD!U:U,[2]SD!A:A,N32,[2]SD!H:H,$T$2) -> 0 | BV32: =SUMIFS([2]SD!V:V,[2]SD!A:A,N32,[2]SD!H:H,$P$2)+SUMIFS([2]SD!V:V,[2]SD!A:A,N32,[2]SD!H:H,$T$2) -> 0 | BW32: =IFERROR(BU32/BR32,0) -> 0 | BX32: =SUMIFS([2]SD!O:O,[2]SD!A:A,N32,[2]SD!H:H,$P$2)+SUMIFS([2]SD!O:O,[2]SD!A:A,N32,[2]SD!H:H,$T$2) -> 0 | BY32: =IFERROR(BX32/BV32,0) -> 0 | BZ32: =SUMIFS([2]SB!H:H,[2]SB!B:B,N32,[2]SB!A:A,$P$2)+SUMIFS([2]SB!H:H,[2]SB!B:B,N32,[2]SB!A:A,$T$2) -> 0 | CA32: =SUMIFS([2]SB!I:I,[2]SB!B:B,N32,[2]SB!A:A,$P$2)+SUMIFS([2]SB!I:I,[2]SB!B:B,N32,[2]SB!A:A,$T$2) -> 0 | CB32: =IFERROR(CA32/BZ32,0) -> 0 | CC32: =IFERROR(CG32/CA32,0) -> 0 | CD32: =SUMIFS([2]SB!Q:Q,[2]SB!B:B,N32,[2]SB!A:A,$P$2)+SUMIFS([2]SB!Q:Q,[2]SB!B:B,N32,[2]SB!A:A,$T$2) -> 0 | CE32: =SUMIFS([2]SB!O:O,[2]SB!B:B,N32,[2]SB!A:A,$P$2)+SUMIFS([2]SB!O:O,[2]SB!B:B,N32,[2]SB!A:A,$T$2) -> 0 | CF32: =IFERROR(CD32/CA32,0) -> 0 | CG32: =SUMIFS([2]SB!L:L,[2]SB!B:B,N32,[2]SB!A:A,$P$2)+SUMIFS([2]SB!L:L,[2]SB!B:B,N32,[2]SB!A:A,$T$2) -> 0 | CH32: =IFERROR(CG32/CE32,0) -> 0
A33: {=IFERROR(LOOKUP(1,0/(([2]业务报告!$A:$A=$N33)*([2]业务报告!$B:$B=$P$2)),[2]业务报告!AU:AU),"")} | B33: {=IFERROR(LOOKUP(1,0/(([2]业务报告!$A:$A=$N33)*([2]业务报告!$B:$B=$P$2)),[2]业务报告!AV:AV),"")} | C33: =SUMIFS([2]业务报告!AC:AC,[2]业务报告!$A:$A,$N33,[2]业务报告!$B:$B,$P$2) -> 0 | D33: =SUMIFS([2]业务报告!AD:AD,[2]业务报告!$A:$A,$N33,[2]业务报告!$B:$B,$P$2) -> 0 | E33: {=_xlfn.XLOOKUP($N33&$P$2,[2]业务报告!$A:$A&[2]业务报告!$B:$B,[2]业务报告!AE:AE,"")} | F33: {=IFERROR(LOOKUP(1,0/(([2]业务报告!$A:$A=$N33)*([2]业务报告!$B:$B=$P$2)),[2]业务报告!AK:AK),0)} -> 0 | G33: =SUMIFS([2]业务报告!AF:AF,[2]业务报告!$A:$A,$N33,[2]业务报告!$B:$B,$P$2) -> 0 | H33: {=IFERROR(LOOKUP(1,0/(([2]业务报告!$A:$A=$N33)*([2]业务报告!B:B=$P$2)),[2]业务报告!AG:AG),0)} -> 0 | I33: {=IFERROR(LOOKUP(1,0/(([2]业务报告!$A:$A=$N33)*([2]业务报告!$B:$B=$P$2)),[2]业务报告!AH:AH),0)} -> 0 | J33: =SUMIFS([2]WT报告!A:A,[2]WT报告!$C:$C,$N33,[2]WT报告!$H:$H,$X$2) -> 0 | K33: {=IFERROR(LOOKUP(1,0/(([2]业务报告!$A:$A=$N33)*([2]业务报告!$B:$B=$P$2)),[2]业务报告!AI:AI),0)} -> 0 | L33: {=IFERROR(LOOKUP(1,0/(([2]业务报告!$A:$A=$N33)*([2]业务报告!$B:$B=$P$2)),[2]业务报告!AJ:AJ),0)} -> 0 | M33: =IFERROR("周"&WEEKDAY(N33,2),"-") -> 周1 | N33: =IFERROR(IF(MONTH(DATE($O$1,$O$2,DAY(N32)+1))=$O$2,DATE($O$1,$O$2,DAY(N32)+1),"-"),IFERROR(IF(FIND("-",N32,1)>0,"-",0),"其他")) -> 45929 | O33: =SUMIFS([2]业务报告!G:G,[2]业务报告!$A:$A,$N33,[2]业务报告!$B:$B,$P$2)+SUMIFS([2]业务报告!G:G,[2]业务报告!$A:$A,$N33,[2]业务报告!$B:$B,$T$2) -> 0 | P33: =SUMIFS([2]业务报告!H:H,[2]业务报告!$A:$A,$N33,[2]业务报告!$B:$B,$P$2)+SUMIFS([2]业务报告!H:H,[2]业务报告!$A:$A,$N33,[2]业务报告!$B:$B,$T$2) -> 0 | Q33: =SUMIFS([2]业务报告!I:I,[2]业务报告!$A:$A,$N33,[2]业务报告!$B:$B,$P$2)+SUMIFS([2]业务报告!I:I,[2]业务报告!$A:$A,$N33,[2]业务报告!$B:$B,$T$2) -> 0 | R33: =SUMIFS([2]业务报告!T:T,[2]业务报告!$A:$A,$N33,[2]业务报告!$B:$B,$P$2)+SUMIFS([2]业务报告!T:T,[2]业务报告!$A:$A,$N33,[2]业务报告!$B:$B,$T$2) -> 0 | S33: =IFERROR((R33+V33)/Q33,0) -> 0 | T33: =SUMIFS([2]业务报告!X:X,[2]业务报告!$A:$A,$N33,[2]业务报告!$B:$B,$P$2)+SUMIFS([2]业务报告!X:X,[2]业务报告!$A:$A,$N33,[2]业务报告!$B:$B,$T$2) -> 0 | U33: =SUMIFS([2]业务报告!AO:AO,[2]业务报告!$A:$A,$N33,[2]业务报告!$B:$B,$P$2)+SUMIFS([2]业务报告!AP:AP,[2]业务报告!$A:$A,$N33,[2]业务报告!$B:$B,$P$2) -> 0 | V33: =SUMIFS([2]WT报告!I:I,[2]WT报告!$C:$C,$N33,[2]WT报告!$H:$H,$X$2) -> 0 | W33: =SUMIFS([2]WT报告!Z:Z,[2]WT报告!$C:$C,$N33,[2]WT报告!$H:$H,$X$2) -> 0 | X33: =SUMIFS([2]业务报告!AS:AS,[2]业务报告!$A:$A,$N33,[2]业务报告!$B:$B,$P$2)+SUMIFS([2]业务报告!AS:AS,[2]业务报告!$A:$A,$N33,[2]业务报告!$B:$B,$T$2)+V33 -> 0 | Y33: =SUMIFS([2]业务报告!AO:AO,[2]业务报告!$A:$A,$N33,[2]业务报告!$B:$B,$P$2)*SUMIFS([2]业务报告!AM:AM,[2]业务报告!$A:$A,$N33,[2]业务报告!$B:$B,$P$2)/$AC$2+SUMIFS([2]业务报告!AP:AP,[2]业务报告!$A:$A,$N33,[2]业务报告!$B:$B,$P$2)*SUMIFS([2]业务报告!AN:AN,[2]业务报告!$A:$A,$N33,[2]业务报告!$B:$B,$P$2)/$AC$2 -> 0 | Z33: =(I33*(1-$AD$2-4%-10%)-$AD$1-$AC$1/$AC$2)*BB33-BC33 -> 0 | AA33: =(I33*(1-$AD$2-4%-10%)-$AD$1-$AC$1/$AC$2)*(R33-IF(R33>V33,SUMIFS([2]业务报告!AO:AO,[2]业务报告!$A:$A,$N33,[2]业务报告!$B:$B,$P$2),0))-BC33 -> 0 | AB33: =IFERROR(AA33/(I33*R33),0) -> 0 | AC33: =AR33*(J33-$AC$1/$AC$2-J33*4%)-AS33 -> 0 | AD33: =(V33-IF(R33<V33,SUMIFS([2]业务报告!AO:AO,[2]业务报告!$A:$A,$N33,[2]业务报告!$B:$B,$P$2),0))*(J33-$AC$1/$AC$2-J33*4%)-AS33 -> 0 | AE33: {=IFERROR(LOOKUP(1,0/(([2]业务报告!$A:$A=$N33)*([2]业务报告!$B:$B=$P$2)),[2]业务报告!AQ:AQ),0)*$AH$2} -> 0 | AF33: {=IFERROR(LOOKUP(1,0/(([2]业务报告!$A:$A=$N33)*([2]业务报告!$B:$B=$P$2)),[2]业务报告!AR:AR),0)*$AG$2} -> 0 | AG33: =AA33+AD33+AE33+AF33-Y33 -> 0 | AH33: =IFERROR((AG33)/(T33+J33*V33),0) -> 0 | AI33: =IFERROR((AG33)/(X33),0) -> 0 | AJ33: =IFERROR(AS33/(V33*J33),0) -> 0 | AK33: =IFERROR(ROUNDUP(AS33/V33,1),0) -> 0 | AL33: =SUMIFS([2]WT报告!S:S,[2]WT报告!$C:$C,$N33,[2]WT报告!$H:$H,$X$2) -> 0 | AM33: =IFERROR((AR33)/AP33,0) -> 0 | AN33: =SUMIFS([2]WT报告!N:N,[2]WT报告!$C:$C,$N33,[2]WT报告!$H:$H,$X$2) -> 0 | AO33: =IFERROR(AR33/(V33),0) -> 0 | AP33: =SUMIFS([2]WT报告!P:P,[2]WT报告!$C:$C,$N33,[2]WT报告!$H:$H,$X$2) -> 0 | AQ33: =SUMIFS([2]WT报告!Q:Q,[2]WT报告!$C:$C,$N33,[2]WT报告!$H:$H,$X$2) -> 0 | AR33: =SUMIFS([2]WT报告!J:J,[2]WT报告!$C:$C,$N33,[2]WT报告!$H:$H,$X$2) -> 0 | AS33: =SUMIFS([2]WT报告!M:M,[2]WT报告!$C:$C,$N33,[2]WT报告!$H:$H,$X$2) -> 0 | AT33: =IFERROR((BO33+BX33+CG33)/(R33*I33),0) -> 0 | AU33: =IFERROR(ROUNDUP(BC33/R33,1),0) -> 0 | AV33: =IFERROR(ROUNDUP(BC33/BB33,1),0) -> 0 | AW33: =IFERROR((BB33)/AZ33,0) -> 0 | AX33: =IFERROR(BC33/AZ33,0) -> 0 | AY33: =IFERROR((BL33+BU33+CD33)/(R33+V33),0) -> 0 | AZ33: =BI33+BR33+CA33 -> 0 | BA33: =IFERROR((BI33+BR33+CA33)/(BH33+BQ33+BZ33),0) -> 0 | BB33: =BL33+BU33+CD33 -> 0 | BC33: =ROUND(BO33+BX33+CG33,2) -> 0 | BD33: =IFERROR(BC33/(BM33+BV33+CE33),0) -> 0 | BE33: =IFERROR(ROUNDUP((BO33+CG33)/BG33,1),0) -> 0 | BF33: =IFERROR(BG33/(BI33+CA33),0) -> 0 | BG33: =BL33+CD33 -> 0 | BH33: =SUMIFS([2]SP!J:J,[2]SP!A:A,N33,[2]SP!H:H,$P$2)+SUMIFS([2]SP!J:J,[2]SP!A:A,N33,[2]SP!H:H,$T$2) -> 0 | BI33: =SUMIFS([2]SP!K:K,[2]SP!A:A,N33,[2]SP!H:H,$P$2)+SUMIFS([2]SP!K:K,[2]SP!A:A,N33,[2]SP!H:H,$T$2) -> 0 | BJ33: =IFERROR(BI33/BH33,0) -> 0 | BK33: =IFERROR(BO33/BI33,0) -> 0 | BL33: =SUMIFS([2]SP!R:R,[2]SP!A:A,N33,[2]SP!H:H,$P$2)+SUMIFS([2]SP!R:R,[2]SP!A:A,N33,[2]SP!H:H,$T$2) -> 0 | BM33: =SUMIFS([2]SP!O:O,[2]SP!A:A,$N33,[2]SP!H:H,$P$2)+SUMIFS([2]SP!O:O,[2]SP!A:A,$N33,[2]SP!H:H,$T$2) -> 0 | BN33: =IFERROR(BL33/BI33,0) -> 0 | BO33: =SUMIFS([2]SP!N:N,[2]SP!A:A,N33,[2]SP!H:H,$P$2)+SUMIFS([2]SP!N:N,[2]SP!A:A,N33,[2]SP!H:H,$T$2) -> 0 | BP33: =IFERROR(BO33/BM33,0) -> 0 | BQ33: =SUMIFS([2]SD!J:J,[2]SD!A:A,N33,[2]SD!H:H,$P$2)+SUMIFS([2]SD!J:J,[2]SD!A:A,N33,[2]SD!H:H,$T$2) -> 0 | BR33: =SUMIFS([2]SD!L:L,[2]SD!A:A,N33,[2]SD!H:H,$P$2)+SUMIFS([2]SD!L:L,[2]SD!A:A,N33,[2]SD!H:H,$T$2) -> 0 | BS33: =IFERROR(BR33/BQ33,0) -> 0 | BT33: =IFERROR(BX33/BR33,0) -> 0 | BU33: =SUMIFS([2]SD!U:U,[2]SD!A:A,N33,[2]SD!H:H,$P$2)+SUMIFS([2]SD!U:U,[2]SD!A:A,N33,[2]SD!H:H,$T$2) -> 0 | BV33: =SUMIFS([2]SD!V:V,[2]SD!A:A,N33,[2]SD!H:H,$P$2)+SUMIFS([2]SD!V:V,[2]SD!A:A,N33,[2]SD!H:H,$T$2) -> 0 | BW33: =IFERROR(BU33/BR33,0) -> 0 | BX33: =SUMIFS([2]SD!O:O,[2]SD!A:A,N33,[2]SD!H:H,$P$2)+SUMIFS([2]SD!O:O,[2]SD!A:A,N33,[2]SD!H:H,$T$2) -> 0 | BY33: =IFERROR(BX33/BV33,0) -> 0 | BZ33: =SUMIFS([2]SB!H:H,[2]SB!B:B,N33,[2]SB!A:A,$P$2)+SUMIFS([2]SB!H:H,[2]SB!B:B,N33,[2]SB!A:A,$T$2) -> 0 | CA33: =SUMIFS([2]SB!I:I,[2]SB!B:B,N33,[2]SB!A:A,$P$2)+SUMIFS([2]SB!I:I,[2]SB!B:B,N33,[2]SB!A:A,$T$2) -> 0 | CB33: =IFERROR(CA33/BZ33,0) -> 0 | CC33: =IFERROR(CG33/CA33,0) -> 0 | CD33: =SUMIFS([2]SB!Q:Q,[2]SB!B:B,N33,[2]SB!A:A,$P$2)+SUMIFS([2]SB!Q:Q,[2]SB!B:B,N33,[2]SB!A:A,$T$2) -> 0 | CE33: =SUMIFS([2]SB!O:O,[2]SB!B:B,N33,[2]SB!A:A,$P$2)+SUMIFS([2]SB!O:O,[2]SB!B:B,N33,[2]SB!A:A,$T$2) -> 0 | CF33: =IFERROR(CD33/CA33,0) -> 0 | CG33: =SUMIFS([2]SB!L:L,[2]SB!B:B,N33,[2]SB!A:A,$P$2)+SUMIFS([2]SB!L:L,[2]SB!B:B,N33,[2]SB!A:A,$T$2) -> 0 | CH33: =IFERROR(CG33/CE33,0) -> 0
A34: {=IFERROR(LOOKUP(1,0/(([2]业务报告!$A:$A=$N34)*([2]业务报告!$B:$B=$P$2)),[2]业务报告!AU:AU),"")} | B34: {=IFERROR(LOOKUP(1,0/(([2]业务报告!$A:$A=$N34)*([2]业务报告!$B:$B=$P$2)),[2]业务报告!AV:AV),"")} | C34: =SUMIFS([2]业务报告!AC:AC,[2]业务报告!$A:$A,$N34,[2]业务报告!$B:$B,$P$2) -> 0 | D34: =SUMIFS([2]业务报告!AD:AD,[2]业务报告!$A:$A,$N34,[2]业务报告!$B:$B,$P$2) -> 0 | E34: {=_xlfn.XLOOKUP($N34&$P$2,[2]业务报告!$A:$A&[2]业务报告!$B:$B,[2]业务报告!AE:AE,"")} | F34: {=IFERROR(LOOKUP(1,0/(([2]业务报告!$A:$A=$N34)*([2]业务报告!$B:$B=$P$2)),[2]业务报告!AK:AK),0)} -> 0 | G34: =SUMIFS([2]业务报告!AF:AF,[2]业务报告!$A:$A,$N34,[2]业务报告!$B:$B,$P$2) -> 0 | H34: {=IFERROR(LOOKUP(1,0/(([2]业务报告!$A:$A=$N34)*([2]业务报告!B:B=$P$2)),[2]业务报告!AG:AG),0)} -> 0 | I34: {=IFERROR(LOOKUP(1,0/(([2]业务报告!$A:$A=$N34)*([2]业务报告!$B:$B=$P$2)),[2]业务报告!AH:AH),0)} -> 0 | J34: =SUMIFS([2]WT报告!A:A,[2]WT报告!$C:$C,$N34,[2]WT报告!$H:$H,$X$2) -> 0 | K34: {=IFERROR(LOOKUP(1,0/(([2]业务报告!$A:$A=$N34)*([2]业务报告!$B:$B=$P$2)),[2]业务报告!AI:AI),0)} -> 0 | L34: {=IFERROR(LOOKUP(1,0/(([2]业务报告!$A:$A=$N34)*([2]业务报告!$B:$B=$P$2)),[2]业务报告!AJ:AJ),0)} -> 0 | M34: =IFERROR("周"&WEEKDAY(N34,2),"-") -> 周2 | N34: =IFERROR(IF(MONTH(DATE($O$1,$O$2,DAY(N33)+1))=$O$2,DATE($O$1,$O$2,DAY(N33)+1),"-"),IFERROR(IF(FIND("-",N33,1)>0,"-",0),"其他")) -> 45930 | O34: =SUMIFS([2]业务报告!G:G,[2]业务报告!$A:$A,$N34,[2]业务报告!$B:$B,$P$2)+SUMIFS([2]业务报告!G:G,[2]业务报告!$A:$A,$N34,[2]业务报告!$B:$B,$T$2) -> 0 | P34: =SUMIFS([2]业务报告!H:H,[2]业务报告!$A:$A,$N34,[2]业务报告!$B:$B,$P$2)+SUMIFS([2]业务报告!H:H,[2]业务报告!$A:$A,$N34,[2]业务报告!$B:$B,$T$2) -> 0 | Q34: =SUMIFS([2]业务报告!I:I,[2]业务报告!$A:$A,$N34,[2]业务报告!$B:$B,$P$2)+SUMIFS([2]业务报告!I:I,[2]业务报告!$A:$A,$N34,[2]业务报告!$B:$B,$T$2) -> 0 | R34: =SUMIFS([2]业务报告!T:T,[2]业务报告!$A:$A,$N34,[2]业务报告!$B:$B,$P$2)+SUMIFS([2]业务报告!T:T,[2]业务报告!$A:$A,$N34,[2]业务报告!$B:$B,$T$2) -> 0 | S34: =IFERROR((R34+V34)/Q34,0) -> 0 | T34: =SUMIFS([2]业务报告!X:X,[2]业务报告!$A:$A,$N34,[2]业务报告!$B:$B,$P$2)+SUMIFS([2]业务报告!X:X,[2]业务报告!$A:$A,$N34,[2]业务报告!$B:$B,$T$2) -> 0 | U34: =SUMIFS([2]业务报告!AO:AO,[2]业务报告!$A:$A,$N34,[2]业务报告!$B:$B,$P$2)+SUMIFS([2]业务报告!AP:AP,[2]业务报告!$A:$A,$N34,[2]业务报告!$B:$B,$P$2) -> 0 | V34: =SUMIFS([2]WT报告!I:I,[2]WT报告!$C:$C,$N34,[2]WT报告!$H:$H,$X$2) -> 0 | W34: =SUMIFS([2]WT报告!Z:Z,[2]WT报告!$C:$C,$N34,[2]WT报告!$H:$H,$X$2) -> 0 | X34: =SUMIFS([2]业务报告!AS:AS,[2]业务报告!$A:$A,$N34,[2]业务报告!$B:$B,$P$2)+SUMIFS([2]业务报告!AS:AS,[2]业务报告!$A:$A,$N34,[2]业务报告!$B:$B,$T$2)+V34 -> 0 | Y34: =SUMIFS([2]业务报告!AO:AO,[2]业务报告!$A:$A,$N34,[2]业务报告!$B:$B,$P$2)*SUMIFS([2]业务报告!AM:AM,[2]业务报告!$A:$A,$N34,[2]业务报告!$B:$B,$P$2)/$AC$2+SUMIFS([2]业务报告!AP:AP,[2]业务报告!$A:$A,$N34,[2]业务报告!$B:$B,$P$2)*SUMIFS([2]业务报告!AN:AN,[2]业务报告!$A:$A,$N34,[2]业务报告!$B:$B,$P$2)/$AC$2 -> 0 | Z34: =(I34*(1-$AD$2-4%-10%)-$AD$1-$AC$1/$AC$2)*BB34-BC34 -> 0 | AA34: =(I34*(1-$AD$2-4%-10%)-$AD$1-$AC$1/$AC$2)*(R34-IF(R34>V34,SUMIFS([2]业务报告!AO:AO,[2]业务报告!$A:$A,$N34,[2]业务报告!$B:$B,$P$2),0))-BC34 -> 0 | AB34: =IFERROR(AA34/(I34*R34),0) -> 0 | AC34: =AR34*(J34-$AC$1/$AC$2-J34*4%)-AS34 -> 0 | AD34: =(V34-IF(R34<V34,SUMIFS([2]业务报告!AO:AO,[2]业务报告!$A:$A,$N34,[2]业务报告!$B:$B,$P$2),0))*(J34-$AC$1/$AC$2-J34*4%)-AS34 -> 0 | AE34: {=IFERROR(LOOKUP(1,0/(([2]业务报告!$A:$A=$N34)*([2]业务报告!$B:$B=$P$2)),[2]业务报告!AQ:AQ),0)*$AH$2} -> 0 | AF34: {=IFERROR(LOOKUP(1,0/(([2]业务报告!$A:$A=$N34)*([2]业务报告!$B:$B=$P$2)),[2]业务报告!AR:AR),0)*$AG$2} -> 0 | AG34: =AA34+AD34+AE34+AF34-Y34 -> 0 | AH34: =IFERROR((AG34)/(T34+J34*V34),0) -> 0 | AI34: =IFERROR((AG34)/(X34),0) -> 0 | AJ34: =IFERROR(AS34/(V34*J34),0) -> 0 | AK34: =IFERROR(ROUNDUP(AS34/V34,1),0) -> 0 | AL34: =SUMIFS([2]WT报告!S:S,[2]WT报告!$C:$C,$N34,[2]WT报告!$H:$H,$X$2) -> 0 | AM34: =IFERROR((AR34)/AP34,0) -> 0 | AN34: =SUMIFS([2]WT报告!N:N,[2]WT报告!$C:$C,$N34,[2]WT报告!$H:$H,$X$2) -> 0 | AO34: =IFERROR(AR34/(V34),0) -> 0 | AP34: =SUMIFS([2]WT报告!P:P,[2]WT报告!$C:$C,$N34,[2]WT报告!$H:$H,$X$2) -> 0 | AQ34: =SUMIFS([2]WT报告!Q:Q,[2]WT报告!$C:$C,$N34,[2]WT报告!$H:$H,$X$2) -> 0 | AR34: =SUMIFS([2]WT报告!J:J,[2]WT报告!$C:$C,$N34,[2]WT报告!$H:$H,$X$2) -> 0 | AS34: =SUMIFS([2]WT报告!M:M,[2]WT报告!$C:$C,$N34,[2]WT报告!$H:$H,$X$2) -> 0 | AT34: =IFERROR((BO34+BX34+CG34)/(R34*I34),0) -> 0 | AU34: =IFERROR(ROUNDUP(BC34/R34,1),0) -> 0 | AV34: =IFERROR(ROUNDUP(BC34/BB34,1),0) -> 0 | AW34: =IFERROR((BB34)/AZ34,0) -> 0 | AX34: =IFERROR(BC34/AZ34,0) -> 0 | AY34: =IFERROR((BL34+BU34+CD34)/(R34+V34),0) -> 0 | AZ34: =BI34+BR34+CA34 -> 0 | BA34: =IFERROR((BI34+BR34+CA34)/(BH34+BQ34+BZ34),0) -> 0 | BB34: =BL34+BU34+CD34 -> 0 | BC34: =ROUND(BO34+BX34+CG34,2) -> 0 | BD34: =IFERROR(BC34/(BM34+BV34+CE34),0) -> 0 | BE34: =IFERROR(ROUNDUP((BO34+CG34)/BG34,1),0) -> 0 | BF34: =IFERROR(BG34/(BI34+CA34),0) -> 0 | BG34: =BL34+CD34 -> 0 | BH34: =SUMIFS([2]SP!J:J,[2]SP!A:A,N34,[2]SP!H:H,$P$2)+SUMIFS([2]SP!J:J,[2]SP!A:A,N34,[2]SP!H:H,$T$2) -> 0 | BI34: =SUMIFS([2]SP!K:K,[2]SP!A:A,N34,[2]SP!H:H,$P$2)+SUMIFS([2]SP!K:K,[2]SP!A:A,N34,[2]SP!H:H,$T$2) -> 0 | BJ34: =IFERROR(BI34/BH34,0) -> 0 | BK34: =IFERROR(BO34/BI34,0) -> 0 | BL34: =SUMIFS([2]SP!R:R,[2]SP!A:A,N34,[2]SP!H:H,$P$2)+SUMIFS([2]SP!R:R,[2]SP!A:A,N34,[2]SP!H:H,$T$2) -> 0 | BM34: =SUMIFS([2]SP!O:O,[2]SP!A:A,$N34,[2]SP!H:H,$P$2)+SUMIFS([2]SP!O:O,[2]SP!A:A,$N34,[2]SP!H:H,$T$2) -> 0 | BN34: =IFERROR(BL34/BI34,0) -> 0 | BO34: =SUMIFS([2]SP!N:N,[2]SP!A:A,N34,[2]SP!H:H,$P$2)+SUMIFS([2]SP!N:N,[2]SP!A:A,N34,[2]SP!H:H,$T$2) -> 0 | BP34: =IFERROR(BO34/BM34,0) -> 0 | BQ34: =SUMIFS([2]SD!J:J,[2]SD!A:A,N34,[2]SD!H:H,$P$2)+SUMIFS([2]SD!J:J,[2]SD!A:A,N34,[2]SD!H:H,$T$2) -> 0 | BR34: =SUMIFS([2]SD!L:L,[2]SD!A:A,N34,[2]SD!H:H,$P$2)+SUMIFS([2]SD!L:L,[2]SD!A:A,N34,[2]SD!H:H,$T$2) -> 0 | BS34: =IFERROR(BR34/BQ34,0) -> 0 | BT34: =IFERROR(BX34/BR34,0) -> 0 | BU34: =SUMIFS([2]SD!U:U,[2]SD!A:A,N34,[2]SD!H:H,$P$2)+SUMIFS([2]SD!U:U,[2]SD!A:A,N34,[2]SD!H:H,$T$2) -> 0 | BV34: =SUMIFS([2]SD!V:V,[2]SD!A:A,N34,[2]SD!H:H,$P$2)+SUMIFS([2]SD!V:V,[2]SD!A:A,N34,[2]SD!H:H,$T$2) -> 0 | BW34: =IFERROR(BU34/BR34,0) -> 0 | BX34: =SUMIFS([2]SD!O:O,[2]SD!A:A,N34,[2]SD!H:H,$P$2)+SUMIFS([2]SD!O:O,[2]SD!A:A,N34,[2]SD!H:H,$T$2) -> 0 | BY34: =IFERROR(BX34/BV34,0) -> 0 | BZ34: =SUMIFS([2]SB!H:H,[2]SB!B:B,N34,[2]SB!A:A,$P$2)+SUMIFS([2]SB!H:H,[2]SB!B:B,N34,[2]SB!A:A,$T$2) -> 0 | CA34: =SUMIFS([2]SB!I:I,[2]SB!B:B,N34,[2]SB!A:A,$P$2)+SUMIFS([2]SB!I:I,[2]SB!B:B,N34,[2]SB!A:A,$T$2) -> 0 | CB34: =IFERROR(CA34/BZ34,0) -> 0 | CC34: =IFERROR(CG34/CA34,0) -> 0 | CD34: =SUMIFS([2]SB!Q:Q,[2]SB!B:B,N34,[2]SB!A:A,$P$2)+SUMIFS([2]SB!Q:Q,[2]SB!B:B,N34,[2]SB!A:A,$T$2) -> 0 | CE34: =SUMIFS([2]SB!O:O,[2]SB!B:B,N34,[2]SB!A:A,$P$2)+SUMIFS([2]SB!O:O,[2]SB!B:B,N34,[2]SB!A:A,$T$2) -> 0 | CF34: =IFERROR(CD34/CA34,0) -> 0 | CG34: =SUMIFS([2]SB!L:L,[2]SB!B:B,N34,[2]SB!A:A,$P$2)+SUMIFS([2]SB!L:L,[2]SB!B:B,N34,[2]SB!A:A,$T$2) -> 0 | CH34: =IFERROR(CG34/CE34,0) -> 0
A35: {=IFERROR(LOOKUP(1,0/(([2]业务报告!$A:$A=$N35)*([2]业务报告!$B:$B=$P$2)),[2]业务报告!AU:AU),"")} | B35: {=IFERROR(LOOKUP(1,0/(([2]业务报告!$A:$A=$N35)*([2]业务报告!$B:$B=$P$2)),[2]业务报告!AV:AV),"")} | C35: =SUMIFS([2]业务报告!AC:AC,[2]业务报告!$A:$A,$N35,[2]业务报告!$B:$B,$P$2) -> 0 | D35: =SUMIFS([2]业务报告!AD:AD,[2]业务报告!$A:$A,$N35,[2]业务报告!$B:$B,$P$2) -> 0 | E35: {=_xlfn.XLOOKUP($N35&$P$2,[2]业务报告!$A:$A&[2]业务报告!$B:$B,[2]业务报告!AE:AE,"")} | F35: {=IFERROR(LOOKUP(1,0/(([2]业务报告!$A:$A=$N35)*([2]业务报告!$B:$B=$P$2)),[2]业务报告!AK:AK),0)} -> 0 | G35: =SUMIFS([2]业务报告!AF:AF,[2]业务报告!$A:$A,$N35,[2]业务报告!$B:$B,$P$2) -> 0 | H35: {=IFERROR(LOOKUP(1,0/(([2]业务报告!$A:$A=$N35)*([2]业务报告!B:B=$P$2)),[2]业务报告!AG:AG),0)} -> 0 | I35: {=IFERROR(LOOKUP(1,0/(([2]业务报告!$A:$A=$N35)*([2]业务报告!$B:$B=$P$2)),[2]业务报告!AH:AH),0)} -> 0 | J35: =SUMIFS([2]WT报告!A:A,[2]WT报告!$C:$C,$N35,[2]WT报告!$H:$H,$X$2) -> 0 | K35: {=IFERROR(LOOKUP(1,0/(([2]业务报告!$A:$A=$N35)*([2]业务报告!$B:$B=$P$2)),[2]业务报告!AI:AI),0)} -> 0 | L35: {=IFERROR(LOOKUP(1,0/(([2]业务报告!$A:$A=$N35)*([2]业务报告!$B:$B=$P$2)),[2]业务报告!AJ:AJ),0)} -> 0 | M35: =IFERROR("周"&WEEKDAY(N35,2),"-") -> - | N35: =IFERROR(IF(MONTH(DATE($O$1,$O$2,DAY(N34)+1))=$O$2,DATE($O$1,$O$2,DAY(N34)+1),"-"),IFERROR(IF(FIND("-",N34,1)>0,"-",0),"其他")) -> - | O35: =SUMIFS([2]业务报告!G:G,[2]业务报告!$A:$A,$N35,[2]业务报告!$B:$B,$P$2)+SUMIFS([2]业务报告!G:G,[2]业务报告!$A:$A,$N35,[2]业务报告!$B:$B,$T$2) -> 0 | P35: =SUMIFS([2]业务报告!H:H,[2]业务报告!$A:$A,$N35,[2]业务报告!$B:$B,$P$2)+SUMIFS([2]业务报告!H:H,[2]业务报告!$A:$A,$N35,[2]业务报告!$B:$B,$T$2) -> 0 | Q35: =SUMIFS([2]业务报告!I:I,[2]业务报告!$A:$A,$N35,[2]业务报告!$B:$B,$P$2)+SUMIFS([2]业务报告!I:I,[2]业务报告!$A:$A,$N35,[2]业务报告!$B:$B,$T$2) -> 0 | R35: =SUMIFS([2]业务报告!T:T,[2]业务报告!$A:$A,$N35,[2]业务报告!$B:$B,$P$2)+SUMIFS([2]业务报告!T:T,[2]业务报告!$A:$A,$N35,[2]业务报告!$B:$B,$T$2) -> 0 | S35: =IFERROR((R35+V35)/Q35,0) -> 0 | T35: =SUMIFS([2]业务报告!X:X,[2]业务报告!$A:$A,$N35,[2]业务报告!$B:$B,$P$2)+SUMIFS([2]业务报告!X:X,[2]业务报告!$A:$A,$N35,[2]业务报告!$B:$B,$T$2) -> 0 | U35: =SUMIFS([2]业务报告!AO:AO,[2]业务报告!$A:$A,$N35,[2]业务报告!$B:$B,$P$2)+SUMIFS([2]业务报告!AP:AP,[2]业务报告!$A:$A,$N35,[2]业务报告!$B:$B,$P$2) -> 0 | V35: =SUMIFS([2]WT报告!I:I,[2]WT报告!$C:$C,$N35,[2]WT报告!$H:$H,$X$2) -> 0 | W35: =SUMIFS([2]WT报告!Z:Z,[2]WT报告!$C:$C,$N35,[2]WT报告!$H:$H,$X$2) -> 0 | X35: =SUMIFS([2]业务报告!AS:AS,[2]业务报告!$A:$A,$N35,[2]业务报告!$B:$B,$P$2)+SUMIFS([2]业务报告!AS:AS,[2]业务报告!$A:$A,$N35,[2]业务报告!$B:$B,$T$2)+V35 -> 0 | Y35: =SUMIFS([2]业务报告!AO:AO,[2]业务报告!$A:$A,$N35,[2]业务报告!$B:$B,$P$2)*SUMIFS([2]业务报告!AM:AM,[2]业务报告!$A:$A,$N35,[2]业务报告!$B:$B,$P$2)/$AC$2+SUMIFS([2]业务报告!AP:AP,[2]业务报告!$A:$A,$N35,[2]业务报告!$B:$B,$P$2)*SUMIFS([2]业务报告!AN:AN,[2]业务报告!$A:$A,$N35,[2]业务报告!$B:$B,$P$2)/$AC$2 -> 0 | Z35: =(I35*(1-$AD$2-4%-10%)-$AD$1-$AC$1/$AC$2)*BB35-BC35 -> 0 | AA35: =(I35*(1-$AD$2-4%-10%)-$AD$1-$AC$1/$AC$2)*(R35-IF(R35>V35,SUMIFS([2]业务报告!AO:AO,[2]业务报告!$A:$A,$N35,[2]业务报告!$B:$B,$P$2),0))-BC35 -> 0 | AB35: =IFERROR(AA35/(I35*R35),0) -> 0 | AC35: =AR35*(J35-$AC$1/$AC$2-J35*4%)-AS35 -> 0 | AD35: =(V35-IF(R35<V35,SUMIFS([2]业务报告!AO:AO,[2]业务报告!$A:$A,$N35,[2]业务报告!$B:$B,$P$2),0))*(J35-$AC$1/$AC$2-J35*4%)-AS35 -> 0 | AE35: {=IFERROR(LOOKUP(1,0/(([2]业务报告!$A:$A=$N35)*([2]业务报告!$B:$B=$P$2)),[2]业务报告!AQ:AQ),0)*$AH$2} -> 0 | AF35: {=IFERROR(LOOKUP(1,0/(([2]业务报告!$A:$A=$N35)*([2]业务报告!$B:$B=$P$2)),[2]业务报告!AR:AR),0)*$AG$2} -> 0 | AG35: =AA35+AD35+AE35+AF35-Y35 -> 0 | AH35: =IFERROR((AG35)/(T35+J35*V35),0) -> 0 | AI35: =IFERROR((AG35)/(X35),0) -> 0 | AJ35: =IFERROR(AS35/(V35*J35),0) -> 0 | AK35: =IFERROR(ROUNDUP(AS35/V35,1),0) -> 0 | AL35: =SUMIFS([2]WT报告!S:S,[2]WT报告!$C:$C,$N35,[2]WT报告!$H:$H,$X$2) -> 0 | AM35: =IFERROR((AR35)/AP35,0) -> 0 | AN35: =SUMIFS([2]WT报告!N:N,[2]WT报告!$C:$C,$N35,[2]WT报告!$H:$H,$X$2) -> 0 | AO35: =IFERROR(AR35/(V35),0) -> 0 | AP35: =SUMIFS([2]WT报告!P:P,[2]WT报告!$C:$C,$N35,[2]WT报告!$H:$H,$X$2) -> 0 | AQ35: =SUMIFS([2]WT报告!Q:Q,[2]WT报告!$C:$C,$N35,[2]WT报告!$H:$H,$X$2) -> 0 | AR35: =SUMIFS([2]WT报告!J:J,[2]WT报告!$C:$C,$N35,[2]WT报告!$H:$H,$X$2) -> 0 | AS35: =SUMIFS([2]WT报告!M:M,[2]WT报告!$C:$C,$N35,[2]WT报告!$H:$H,$X$2) -> 0 | AT35: =IFERROR((BO35+BX35+CG35)/(R35*I35),0) -> 0 | AU35: =IFERROR(ROUNDUP(BC35/R35,1),0) -> 0 | AV35: =IFERROR(ROUNDUP(BC35/BB35,1),0) -> 0 | AW35: =IFERROR((BB35)/AZ35,0) -> 0 | AX35: =IFERROR(BC35/AZ35,0) -> 0 | AY35: =IFERROR((BL35+BU35+CD35)/(R35+V35),0) -> 0 | AZ35: =BI35+BR35+CA35 -> 0 | BA35: =IFERROR((BI35+BR35+CA35)/(BH35+BQ35+BZ35),0) -> 0 | BB35: =BL35+BU35+CD35 -> 0 | BC35: =ROUND(BO35+BX35+CG35,2) -> 0 | BD35: =IFERROR(BC35/(BM35+BV35+CE35),0) -> 0 | BE35: =IFERROR(ROUNDUP((BO35+CG35)/BG35,1),0) -> 0 | BF35: =IFERROR(BG35/(BI35+CA35),0) -> 0 | BG35: =BL35+CD35 -> 0 | BH35: =SUMIFS([2]SP!J:J,[2]SP!A:A,N35,[2]SP!H:H,$P$2)+SUMIFS([2]SP!J:J,[2]SP!A:A,N35,[2]SP!H:H,$T$2) -> 0 | BI35: =SUMIFS([2]SP!K:K,[2]SP!A:A,N35,[2]SP!H:H,$P$2)+SUMIFS([2]SP!K:K,[2]SP!A:A,N35,[2]SP!H:H,$T$2) -> 0 | BJ35: =IFERROR(BI35/BH35,0) -> 0 | BK35: =IFERROR(BO35/BI35,0) -> 0 | BL35: =SUMIFS([2]SP!R:R,[2]SP!A:A,N35,[2]SP!H:H,$P$2)+SUMIFS([2]SP!R:R,[2]SP!A:A,N35,[2]SP!H:H,$T$2) -> 0 | BM35: =SUMIFS([2]SP!O:O,[2]SP!A:A,$N35,[2]SP!H:H,$P$2)+SUMIFS([2]SP!O:O,[2]SP!A:A,$N35,[2]SP!H:H,$T$2) -> 0 | BN35: =IFERROR(BL35/BI35,0) -> 0 | BO35: =SUMIFS([2]SP!N:N,[2]SP!A:A,N35,[2]SP!H:H,$P$2)+SUMIFS([2]SP!N:N,[2]SP!A:A,N35,[2]SP!H:H,$T$2) -> 0 | BP35: =IFERROR(BO35/BM35,0) -> 0 | BQ35: =SUMIFS([2]SD!J:J,[2]SD!A:A,N35,[2]SD!H:H,$P$2)+SUMIFS([2]SD!J:J,[2]SD!A:A,N35,[2]SD!H:H,$T$2) -> 0 | BR35: =SUMIFS([2]SD!L:L,[2]SD!A:A,N35,[2]SD!H:H,$P$2)+SUMIFS([2]SD!L:L,[2]SD!A:A,N35,[2]SD!H:H,$T$2) -> 0 | BS35: =IFERROR(BR35/BQ35,0) -> 0 | BT35: =IFERROR(BX35/BR35,0) -> 0 | BU35: =SUMIFS([2]SD!U:U,[2]SD!A:A,N35,[2]SD!H:H,$P$2)+SUMIFS([2]SD!U:U,[2]SD!A:A,N35,[2]SD!H:H,$T$2) -> 0 | BV35: =SUMIFS([2]SD!V:V,[2]SD!A:A,N35,[2]SD!H:H,$P$2)+SUMIFS([2]SD!V:V,[2]SD!A:A,N35,[2]SD!H:H,$T$2) -> 0 | BW35: =IFERROR(BU35/BR35,0) -> 0 | BX35: =SUMIFS([2]SD!O:O,[2]SD!A:A,N35,[2]SD!H:H,$P$2)+SUMIFS([2]SD!O:O,[2]SD!A:A,N35,[2]SD!H:H,$T$2) -> 0 | BY35: =IFERROR(BX35/BV35,0) -> 0 | BZ35: =SUMIFS([2]SB!H:H,[2]SB!B:B,N35,[2]SB!A:A,$P$2)+SUMIFS([2]SB!H:H,[2]SB!B:B,N35,[2]SB!A:A,$T$2) -> 0 | CA35: =SUMIFS([2]SB!I:I,[2]SB!B:B,N35,[2]SB!A:A,$P$2)+SUMIFS([2]SB!I:I,[2]SB!B:B,N35,[2]SB!A:A,$T$2) -> 0 | CB35: =IFERROR(CA35/BZ35,0) -> 0 | CC35: =IFERROR(CG35/CA35,0) -> 0 | CD35: =SUMIFS([2]SB!Q:Q,[2]SB!B:B,N35,[2]SB!A:A,$P$2)+SUMIFS([2]SB!Q:Q,[2]SB!B:B,N35,[2]SB!A:A,$T$2) -> 0 | CE35: =SUMIFS([2]SB!O:O,[2]SB!B:B,N35,[2]SB!A:A,$P$2)+SUMIFS([2]SB!O:O,[2]SB!B:B,N35,[2]SB!A:A,$T$2) -> 0 | CF35: =IFERROR(CD35/CA35,0) -> 0 | CG35: =SUMIFS([2]SB!L:L,[2]SB!B:B,N35,[2]SB!A:A,$P$2)+SUMIFS([2]SB!L:L,[2]SB!B:B,N35,[2]SB!A:A,$T$2) -> 0 | CH35: =IFERROR(CG35/CE35,0) -> 0
A36: - | B36: - | C36: - | D36: - | G36: 109.99 | H36: - | J36: 38.5 | K36: - | L36: =SUM(L5:L35) -> 0 | M36: =IFERROR("周"&WEEKDAY(N36,2),"-") -> - | N36: =O2&"月份 汇总" -> 9月份 汇总 | O36: =SUM(O5:O35) -> 0 | P36: =SUM(P5:P35) -> 0 | Q36: =SUM(Q5:Q35) -> 0 | R36: =SUM(R5:R35) -> 0 | S36: =IFERROR(R36/O36,0) -> 0 | T36: =SUM(T5:T35) -> 0 | U36: =SUM(U5:U35) -> 0 | V36: =SUM(V5:V35) -> 0 | W36: =SUM(W5:W35) -> 0 | X36: =SUM(X5:X35) -> 0 | Y36: =SUM(Y5:Y35) -> 0 | Z36: =SUM(Z5:Z35) -> 0 | AA36: =SUM(AA5:AA35) -> 0 | AB36: / | AC36: =SUM(AC5:AC35) -> 0 | AD36: =SUM(AD5:AD35) -> 0 | AF36: =SUM(AF5:AF35) -> 0 | AG36: =SUM(AG5:AG35) -> 0 | AH36: =IFERROR((AG36)/(T36+J36*V36),0) -> 0 | AI36: =IFERROR((AG36)/(R36+V36),0) -> 0 | AJ36: =IFERROR((BB36+BL36)/I36,0) -> 0 | AK36: =IFERROR(ROUNDUP(AS36/G36,1),0) -> 0 | AL36: =SUM(AL5:AL35) -> 0 | AM36: =IFERROR((AR36)/AP36,0) -> 0 | AN36: =IFERROR(AT36/AP36,0) -> 0 | AO36: =IFERROR(AR36/(V36),0) -> 0 | AP36: =SUM(AP5:AP35) -> 0 | AQ36: - | AR36: =SUM(AR5:AR35) -> 0 | AS36: =SUM(AS5:AS35) -> 0 | AT36: =IFERROR((BO36+BX36)/T36,0) -> 0 | AU36: =IFERROR(ROUNDUP(BC36/R36,1),0) -> 0 | AW36: =IFERROR((BB36)/AZ36,0) -> 0 | AX36: =IFERROR(BC36/AZ36,0) -> 0 | AY36: =IFERROR((BL36+BU36+CD36)/R36,0) -> 0 | AZ36: =SUM(AZ5:AZ35) -> 0 | BA36: =IFERROR((BI36+BR36+CA36)/(BH36+BQ36+BZ36),0) -> 0 | BB36: =SUM(BB5:BB35) -> 0 | BC36: =SUM(BC5:BC35) -> 0 | BD36: =IFERROR(BC36/(BM36+BV36+CE36),0) -> 0 | BF36: =IFERROR(BG36/(BI36+CA36),0) -> 0 | BG36: =SUM(BG5:BG35) -> 0 | BH36: =SUM(BH5:BH35) -> 0 | BI36: =SUM(BI5:BI35) -> 0 | BJ36: =IFERROR(BI36/BH36,0) -> 0 | BK36: =IFERROR(BO36/BI36,0) -> 0 | BL36: =SUM(BL5:BL35) -> 0 | BM36: =SUM(BM5:BM35) -> 0 | BN36: =IFERROR(BL36/BI36,0) -> 0 | BO36: =SUM(BO5:BO35) -> 0 | BP36: =IFERROR(BO36/BM36,0) -> 0 | BQ36: =SUM(BQ5:BQ35) -> 0 | BR36: =SUM(BR5:BR35) -> 0 | BS36: =IFERROR(BR36/BQ36,0) -> 0 | BT36: =IFERROR(BX36/BR36,0) -> 0 | BU36: =SUM(BU5:BU35) -> 0 | BV36: =SUM(BV5:BV35) -> 0 | BW36: =IFERROR(BU36/BR36,0) -> 0 | BX36: =SUM(BX5:BX35) -> 0 | BY36: =IFERROR(BX36/BV36,0) -> 0 | BZ36: =SUM(BZ5:BZ35) -> 0 | CA36: =SUM(CA5:CA35) -> 0 | CB36: =IFERROR(CA36/BZ36,0) -> 0 | CC36: =IFERROR(CG36/CA36,0) -> 0 | CD36: =SUM(CD5:CD35) -> 0 | CE36: =SUM(CE5:CE35) -> 0 | CF36: =IFERROR(CD36/CA36,0) -> 0 | CG36: =SUM(CG5:CG35) -> 0 | CH36: =IFERROR(CG36/CE36,0) -> 0
R37: =R36+V36 -> 0 | AA37: =AA36*$AC$2 -> 0 | AD37: =AD36*$AC$2 -> 0 | AF37: =AF36*$AC$2 -> 0 | AG37: =AG36*$AC$2 -> 0
